Workbook
Name o28\: WC!$P$33

Sheet Valuation
A1: Minh Huyền | K1: Prepared by: TV
A2: Entity: | B2: SAB | K2: Reviewed by: LB
A3: Fiscal year: | B3: 46022 | K3: Date:
A4: Date of report: | B4: 45748
A8: Ticker | B8: SAB VN Equity | I8: Adjusted Beta | R8: Violet | S8: Other sheets
A9: Target Price | B9: =ROUND(E21,-2) -> 55700 | L9: WACC | M9: =M10*M11*(1+B15)+M13*M12 -> 0.10392437 | R9: Blue | S9: Input
A10: Upside | B10: =B9/B11-1 -> 0.25733634 | H10: Cost of Equity | J10: =J12+J11*J13 -> 0.104232 | L10: Cost of Debt | M10: =-Debt!N91 -> 0.078862231 | R10: Black | S10: Same sheet
A11: Current Price | B11: 44300 | H11: Beta | J11: 0.74 | L11: Weight of Debt | M11: =1-M13 -> 0.0076102448
A12: Outstanding share (bn) | B12: 1282 | H12: Rf | J12: 0.04 | L12: Cost of Equity | M12: =J10 -> 0.104232 | R12: Weighted Average Cost of Capital (WACC)
A13: Equity value | B13: =B12*B11 -> 56792600 | H13: Equity Risk Premium | J13: 0.0868 | L13: Weight of Equity | M13: =M14/(M14+M15) -> 0.99238976 | R13: WACC (%) | S13: =M9 -> 0.10392437
A14: Total debt | B14: =H73 -> 435520 | L14: MV of Equity | M14: =B13 -> 56792600 | R14: Risk-free rate (%) | S14: =J12 -> 0.04
A15: Tax rate | B15: ='1IS'!O47 -> -0.19087889 | L15: MV of Debt | M15: =B14 -> 435520 | R15: Equity risk premium (%) | S15: =J13 -> 0.0868
R16: Beta | S16: =J11 -> 0.74
B17: Tổng hợp định gía | R17: Debt cost (%) | S17: =M10 -> 0.078862231
D18: Weight | E18: Target Price | R18: The cost of equity(%) | S18: =M12 -> 0.104232
B19: FCFF | D19: 0.5 | E19: =D98 -> 57700 | R19: Debt-to-equity ratio | S19: =M15/M14 -> 0.0076686047
B20: P/E | D20: =1-D19 -> 0.5 | E20: =D124 -> 53657.891 | R20: Total debt | S20: =M15 -> 435520
B21: Total | D21: 1 | E21: =SUMPRODUCT(D19:D20,E19:E20) -> 55678.945
E25: =E27/D27 -> 1.2197259 | F25: =F27/E27 -> 0.91931284 | G25: =G27/F27 -> 0.79591403 | H25: =H27/G27 -> 1.3996872 | I25: =I27/H27 -> 0.77367441 | J25: =J27/I27 -> 1.056338 | K25: =K27/J27 -> 1.0174316 | L25: =L27/K27 -> 0.99691456 | ... N25: =N27/M27 -> 1.0954781
B26: FCFF | D26: 2018 | E26: 1019 | F26: 2020 | G26: 2021 | H26: 2022 | I26: 2023 | J26: 2024 | K26: 2025 | L26: 2026 | M26: 2027 | N26: 2028
B27: NI | D27: ='1IS'!H21 -> 4402750 | E27: ='1IS'!I21 -> 5370148 | F27: ='1IS'!J21 -> 4936846 | G27: ='1IS'!K21 -> 3929305 | H27: ='1IS'!L21 -> 5499798 | I27: ='1IS'!M21 -> 4255053 | J27: ='1IS'!N21 -> 4494774 | K27: ='1IS'!O21 -> 4573125 | ... N27: ='1IS'!R21 -> 5159881.4
A28: + | B28: NCC | I28: =SUM('1CF'!J8:J9) -> 573450 | J28: =SUM('1CF'!K8:K9) -> 553199 | K28: =SUM('1CF'!L8:L9) -> 772739 | L28: =SUM('1CF'!M8:M9) -> 547559.25 | M28: =SUM('1CF'!N8:N9) -> 722511.26 | N28: =SUM('1CF'!O8:O9) -> 870123.89
A29: + | B29: Int(1-t) | I29: =-'1IS'!M8*(1+$B$15) -> 40630.017 | J29: =-'1IS'!N8*(1+$B$15) -> 22210.374 | K29: =-'1IS'!O8*(1+$B$15) -> 27790.074 | L29: =-'1IS'!P8*(1+$B$15) -> 26885.738 | M29: =-'1IS'!Q8*(1+$B$15) -> 28257.776 | N29: =-'1IS'!R8*(1+$B$15) -> 30638.399
A30: - | B30: WCInv | I30: =-SUM('1CF'!J16:J19) -> 1108889 | J30: =-SUM('1CF'!K16:K19) -> -691269 | K30: =-SUM('1CF'!L16:L19) -> 38289 | L30: =-SUM('1CF'!M16:M19) -> 655074.92 | M30: =-SUM('1CF'!N16:N19) -> 85454.636 | N30: =-SUM('1CF'!O16:O19) -> -179069.22
A31: - | B31: Capex | I31: =-'1CF'!M21 -> 33228.324 | J31: =-'1CF'!N21 -> 34924.037 | K31: =-'1CF'!O21 -> 37866.271 | L31: =-'1CF'!P21 -> 39228.538 | M31: =-'1CF'!Q21 -> 41647.58 | N31: =-'1CF'!R21 -> 44356.65
B32: FCFF | I32: =I27+I28+I29-I30-I31 -> 3727015.7 | J32: =J27+J28+J29-J30-J31 -> 5726528.3 | K32: =K27+K28+K29-K30-K31 -> 5297498.8 | L32: =L27+L28+L29-L30-L31 -> 4439156.4 | M32: =M27+M28+M29-M30-M31 -> 5333830.9 | N32: =N27+N28+N29-N30-N31 -> 6195356.3
I34: =I26 -> 2023 | J34: =J26 -> 2024 | K34: =K26 -> 2025 | L34: =L26 -> 2026 | M34: =M26 -> 2027 | N34: =N26 -> 2028
B35: WACC | D35: =M9 -> 0.10392437
B36: Discount factor | J36: =1/((1+$D$35)^(J26-2020)) -> 0.67335287 | K36: =1/((1+$D$35)^(K26-2020)) -> 0.60996286 | L36: =1/((1+$D$35)^(L26-2020)) -> 0.55254044 | M36: =1/((1+$D$35)^(M26-2020)) -> 0.50052382 | N36: =1/((1+$D$35)^(N26-2020)) -> 0.45340408
B37: PV of FCFF | J37: =J32*J36 -> 3855974.3 | K37: =K32*K36 -> 3231277.5 | L37: =L32*L36 -> 2452813.5 | M37: =M32*M36 -> 2669709.4 | N37: =N32*N36 -> 2808999.8
B38: PV of Terminal Value | N38: =N37*(1+D48)/(D35-D48)*N36 -> 12255181
B48: Terminal Growth | D48: 0
B49: Enterprise Value (VND bn) | D49: =SUM(J37:N37)+N38 -> 27273956
B50: (-) Total Debt | D50: =Debt!K5+Debt!K13 -> 1033059 | E50: 2022
B51: (+) Cash&Cash Equivalents | D51: ='1BS'!L4 -> 4069464 | E51: 2022
B52: Minority int | D52: 0
B53: Implied Equity Value | D53: =D49-D50+D51 -> 30310361
B54: Share outstanding | D54: =B12 -> 1282
B55: Price per Share (VND) | D55: =D53/D54 -> 23643.027
B57: FCFF | I57: 2023 | J57: 2024 | K57: 2025 | L57: 2026 | M57: 2027 | N57: 2028 | O57: 2029 | P57: 2030 | Q57: 2031
L58: 46387 | M58: 46752 | N58: 47118 | O58: 47483 | P58: 47848 | Q58: 48213
B59: NI | I59: ='1IS'!M21 -> 4255053 | J59: ='1IS'!N21 -> 4494774 | K59: ='1IS'!O21 -> 4573125 | L59: ='1IS'!P21 -> 4559014.9 | M59: ='1IS'!Q21 -> 4710164.1 | N59: ='1IS'!R21 -> 5159881.4 | O59: ='1IS'!S21 -> 5266768.5 | P59: ='1IS'!T21 -> 5525888.5 | Q59: ='1IS'!U21 -> 5763061.8
A60: Plus | B60: NCC | I60: ='1CF'!J8 -> 570032 | J60: ='1CF'!K8 -> 548884 | K60: ='1CF'!L8 -> 730272 | L60: ='1CF'!M8 -> 800488.6 | M60: ='1CF'!N8 -> 812226.28 | N60: ='1CF'!O8 -> 799683.17 | O60: ='1CF'!P8 -> 813377.07 | P60: ='1CF'!Q8 -> 630981.22 | Q60: ='1CF'!R8 -> 103456.63
A61: Plus | B61: Lãi vay (sau thuế) | I61: =-'1IS'!M8*(1+Valuation!B15) -> 40630.017 | J61: =-'1IS'!N8*(1+Valuation!C15) -> 27450 | K61: =-'1IS'!O8*(1+Valuation!D15) -> 34346 | L61: =-'1IS'!P8*(1+Valuation!E15) -> 33228.324 | M61: =-'1IS'!Q8*(1+Valuation!F15) -> 34924.037 | N61: =-'1IS'!R8*(1+Valuation!G15) -> 37866.271 | O61: =-'1IS'!S8*(1+Valuation!H15) -> 39228.538 | P61: =-'1IS'!T8*(1+Valuation!I15) -> 41647.58 | Q61: =-'1IS'!U8*(1+Valuation!J15) -> 44356.65
A62: Minus | B62: Đầu tư TSCĐ | I62: =-'1CF'!J29 -> 283735 | J62: =-'1CF'!K29 -> 296018 | K62: =-'1CF'!L29 -> 241544 | L62: =-'1CF'!M29 -> -49759.081 | M62: =-'1CF'!N29 -> 12731.453 | N62: =-'1CF'!O29 -> 72097.476 | O62: =-'1CF'!P29 -> 57898.51 | P62: =-'1CF'!Q29 -> 67436.359 | Q62: =-'1CF'!R29 -> 66420.303
A63: Minus | B63: Đầu tư Vốn lưu động | I63: =-SUM('1CF'!J16:J19) -> 1108889 | J63: =-SUM('1CF'!K16:K19) -> -691269 | K63: =-SUM('1CF'!L16:L19) -> 38289 | L63: =-SUM('1CF'!M16:M19) -> 655074.92 | M63: =-SUM('1CF'!N16:N19) -> 85454.636 | N63: =-SUM('1CF'!O16:O19) -> -179069.22 | O63: =-SUM('1CF'!P16:P19) -> -21975.552 | P63: =-SUM('1CF'!Q16:Q19) -> -209368.54 | Q63: =-SUM('1CF'!R16:R19) -> -102730.58
B64: FCFF | I64: =I59+I60+I61-I62-I63 -> 3473091 | J64: =J59+J60+J61-J62-J63 -> 5466359 | K64: =K59+K60+K61-K62-K63 -> 5057910 | L64: =L59+L60+L61-L62-L63 -> 4787416 | M64: =M59+M60+M61-M62-M63 -> 5459128.3 | N64: =N59+N60+N61-N62-N63 -> 6104402.6 | O64: =O59+O60+O61-O62-O63 -> 6083451.2 | P64: =P59+P60+P61-P62-P63 -> 6340449.5 | Q64: =Q59+Q60+Q61-Q62-Q63 -> 5947185.3
B65: Số năm chiết khấu | L65: =L57-$L$57 -> 0 | M65: =M57-$L$57 -> 1 | N65: =N57-$L$57 -> 2 | O65: =O57-$L$57 -> 3 | P65: =P57-$L$57 -> 4 | Q65: =Q57-$L$57 -> 5
B66: Hệ số chiết khấu | L66: =1/(1+$M$9)^L65 -> 1 | M66: =1/(1+$M$9)^M65 -> 0.90585916 | N66: =1/(1+$M$9)^N65 -> 0.82058081 | O66: =1/(1+$M$9)^O65 -> 0.74333064 | P66: =1/(1+$M$9)^P65 -> 0.67335287 | Q66: =1/(1+$M$9)^Q65 -> 0.60996286
B67: Giá trị hiện tại của FCFF | I67: 0 | L67: =L64*L66 -> 4787416 | M67: =M64*M66 -> 4945201.4 | N67: =N64*N66 -> 5009155.6 | O67: =O64*O66 -> 4522015.7 | P67: =P64*P66 -> 4269359.8 | Q67: =Q64*Q66 -> 3627562.2
B68: Tổng giá trị hiện tại của FCFF | H68: =SUM(M67:Q67) -> 22373295
B69: Giá trị dài hạn | H69: =Q64*(1+D48)/(S13-D48) -> 57226089
B70: Giá trị hiện tại của giá trị dài hạn | H70: =H69*Q66 -> 34905789
B71: Giá trị doanh nghiệp | H71: =H70+H68 -> 57279083
B72: Tiền mặt và tiền gửi ngân hàng | H72: ='1BS'!O4+'1BS'!O7 -> 19002371
B73: Vay nợ | H73: ='1BS'!O80+'1BS'!O93 -> 435520
B74: Lợi ích cổ đông thiểu số | H74: ='1BS'!O118 -> 1847031
B75: Giá trị VCSH | H75: =H71+H72-H73-H74 -> 73998903
B76: Số cổ phiếu | H76: =B12 -> 1282
B77: Price per share | H77: =H75/H76 -> 57721.454
B81: Forecast FCF of SAB
C82: Unit: billion VND | D82: 2026F | E82: 2027F | F82: 2028F | G82: 2097F | H82: 2030F | I82: 2031F
C83: Net profit | D83: =L59 -> 4559014.9 | E83: =M59 -> 4710164.1 | F83: =N59 -> 5159881.4 | G83: =O59 -> 5266768.5 | H83: =P59 -> 5525888.5 | I83: =Q59 -> 5763061.8
C84: Plus: After-tax interest expense | D84: =L61 -> 33228.324 | E84: =M61 -> 34924.037 | F84: =N61 -> 37866.271 | G84: =O61 -> 39228.538 | H84: =P61 -> 41647.58 | I84: =Q61 -> 44356.65
C85: Plus: Depreciation & Amortization | D85: =L60 -> 800488.6 | E85: =M60 -> 812226.28 | F85: =N60 -> 799683.17 | G85: =O60 -> 813377.07 | H85: =P60 -> 630981.22 | I85: =Q60 -> 103456.63
C86: Minus: Change in working capital | D86: =L63 -> 655074.92 | E86: =M63 -> 85454.636 | F86: =N63 -> -179069.22 | G86: =O63 -> -21975.552 | H86: =P63 -> -209368.54 | I86: =Q63 -> -102730.58
C87: Minus: CapEx | D87: =L62 -> -49759.081 | E87: =M62 -> 12731.453 | F87: =N62 -> 72097.476 | G87: =O62 -> 57898.51 | H87: =P62 -> 67436.359 | I87: =Q62 -> 66420.303
C88: Free Cash Flow (FCF) | D88: =D83+SUM(D84:D85)-SUM(D86:D87) -> 4787416 | E88: =E83+SUM(E84:E85)-SUM(E86:E87) -> 5459128.3 | F88: =F83+SUM(F84:F85)-SUM(F86:F87) -> 6104402.6 | G88: =G83+SUM(G84:G85)-SUM(G86:G87) -> 6083451.2 | H88: =H83+SUM(H84:H85)-SUM(H86:H87) -> 6340449.5 | I88: =I83+SUM(I84:I85)-SUM(I86:I87) -> 5947185.3
C89: Discount rate | D89: =L66 -> 1 | E89: =M66 -> 0.90585916 | F89: =N66 -> 0.82058081 | G89: =O66 -> 0.74333064 | H89: =P66 -> 0.67335287 | I89: =Q66 -> 0.60996286
C90: PV of FCF | D90: =H68 -> 22373295
C91: Growth rate | D91: =D48 -> 0
C92: Present value of long-term value | D92: =H70 -> 34905789
C93: Enterprise value | D93: =SUM(D92,D90:H90) -> 57279083
C94: Debt | D94: =H73 -> 435520
C95: Cash and cash equivalents | D95: =H72 -> 19002371
C96: Minority interest | D96: =H74 -> 1847031
C97: Number of shares outstanding (billion units) | D97: =B12 -> 1282
C98: Target price (VND) | D98: =FLOOR((D93+D95-D94-D96)/D97,100) -> 57700
B110: So sánh các doanh nghiệp trong ngành
B111: Mã chứng khoán | D111: PE | E111: Vốn hóa | F111: Tăng trưởng | G111: Tăng trưởng | H111: ROE (%)
E112: (tỷ VND) | F112: Doanh thu (%) | G112: EPS (%)
B115: HEIM MK Equity | C115: HEINEKEN MALAYSIA BHD | D115: 14.9 | E115: 45321 | F115: 0.1 | G115: -1.6 | H115: 85.8
B116: CAB MK Equity | C116: CARLSBERG BREWERY MALAYSIA BHD | D116: 13.7 | E116: 33777 | F116: 5.11 | G116: 2.57 | H116: 125.3
B117: MLBI IJ Equity | C117: MULTI BINTANG INDONESIA TPK | D117: 10.1 | E117: 18044 | F117: 4.7 | G117: 3.6 | H117: 88.5
B118: LION SL Equity | C118: LION BREWERY CEYLON PLC | D118: 13.2 | E118: 11406 | F118: 12.46 | G118: 16.9 | H118: 30.67
B119: BHN VN Equity | C119: HANOI BEER ALCOHOL & BEVERAG | D119: 14.7 | E119: 6838 | F119: 3.7 | G119: 26.4 | H119: 10.1
C120: Trung bình | D120: =AVERAGE(D115:D119) -> 13.32
C121: P/E bình quân 5 năm | D121: 18.9
C122: P/E mục tiêu | D122: =AVERAGE(D120:D121) -> 16.11
C123: EPS forward (2026F) | D123: ='1IS'!P24 -> 3330.7195
C124: Giá mục tiêu | D124: =D122*D123 -> 53657.891

Sheet 1BS
C1: Input | Y1: Var
C2: 2013 | D2: =C2+1 -> 2014 | E2: =D2+1 -> 2015 | F2: =E2+1 -> 2016 | G2: =F2+1 -> 2017 | H2: =G2+1 -> 2018 | I2: =H2+1 -> 2019 | J2: =I2+1 -> 2020 | K2: =J2+1 -> 2021 | ... U2: =T2+1 -> 2031 | V2: Note | X2: Code for CF | Y2: 2024 | Z2: 2025 | AA2: 2026 | AB2: 2027 | AC2: 2028 | AD2: 2029 | AE2: 2030 | AF2: 2031
A3: 100 | B3: CURRENT ASSETS | C3: =BS!G2 -> 8481709 | D3: =BS!H2 -> 10547147 | E3: =BS!I2 -> 12194294 | F3: =BS!J2 -> 10714346 | G3: =BS!K2 -> 13686327 | H3: =BS!L2 -> 14690168 | I3: =BS!M2 -> 19164603 | J3: =BS!N2 -> 19513381 | ... O3: =BS!S2 -> 22140978 | P3: =SUM(P4,P7,P11,P20,P23) -> 21786543 | Q3: =SUM(Q4,Q7,Q11,Q20,Q23) -> 22218601 | R3: =SUM(R4,R7,R11,R20,R23) -> 23752581 | S3: =SUM(S4,S7,S11,S20,S23) -> 24975052 | T3: =SUM(T4,T7,T11,T20,T23) -> 26566335 | U3: =SUM(U4,U7,U11,U20,U23) -> 27759472 | X3: x | Y3: =N3-M3 -> -1486673 | Z3: =O3-N3 -> -2925755 | AA3: =P3-O3 -> -354434.56 | AB3: =Q3-P3 -> 432057.81 | AC3: =R3-Q3 -> 1533979.8 | AD3: =S3-R3 -> 1222470.5 | AE3: =T3-S3 -> 1591283.5 | AF3: =U3-T3 -> 1193137.3
A4: 110 | B4: Cash and cash equivalents | C4: =BS!G3 -> 1848256 | D4: =BS!H3 -> 1817059 | E4: =BS!I3 -> 7935974 | F4: =BS!J3 -> 3444825 | G4: =BS!K3 -> 4268599 | H4: =BS!L3 -> 4467392 | I4: =BS!M3 -> 4115885 | J4: =BS!N3 -> 2726137 | ... O4: =BS!S3 -> 4016882 | P4: =SUM(P5:P6) -> 3747577.4 | Q4: =SUM(Q5:Q6) -> 4922413.3 | R4: =SUM(R5:R6) -> 6413066.7 | S4: =SUM(S5:S6) -> 7541761.5 | T4: =SUM(T5:T6) -> 9076879.8 | U4: =SUM(U5:U6) -> 9805123.4 | X4: x | Y4: =N4-M4 -> -562406 | Z4: =O4-N4 -> -460620 | AA4: =P4-O4 -> -269304.56 | AB4: =Q4-P4 -> 1174835.9 | AC4: =R4-Q4 -> 1490653.4 | AD4: =S4-R4 -> 1128694.8 | AE4: =T4-S4 -> 1535118.2 | AF4: =U4-T4 -> 728243.66
A5: 111 | B5: Cash | C5: =BS!G4 -> 740070 | D5: =BS!H4 -> 991789 | E5: =BS!I4 -> 746447 | F5: =BS!J4 -> 1067588 | G5: =BS!K4 -> 1631825 | H5: =BS!L4 -> 1595189 | I5: =BS!M4 -> 953479 | J5: =BS!N4 -> 844203 | ... O5: =BS!S4 -> 1174863 | P5: ='1CF'!M57 -> 3747577.4 | Q5: ='1CF'!N57 -> 4922413.3 | R5: ='1CF'!O57 -> 6413066.7 | S5: ='1CF'!P57 -> 7541761.5 | T5: ='1CF'!Q57 -> 9076879.8 | U5: ='1CF'!R57 -> 9805123.4 | X5: x | Y5: =N5-M5 -> -85288 | Z5: =O5-N5 -> -162898 | AA5: =P5-O5 -> 2572714.4 | AB5: =Q5-P5 -> 1174835.9 | AC5: =R5-Q5 -> 1490653.4 | AD5: =S5-R5 -> 1128694.8 | AE5: =T5-S5 -> 1535118.2 | AF5: =U5-T5 -> 728243.66
A6: 112 | B6: Cash equivalents | C6: =BS!G5 -> 1108185 | D6: =BS!H5 -> 825269 | E6: =BS!I5 -> 7189527 | F6: =BS!J5 -> 2377237 | G6: =BS!K5 -> 2636774 | H6: =BS!L5 -> 2872203 | I6: =BS!M5 -> 3162406 | J6: =BS!N5 -> 1881934 | ... O6: =BS!S5 -> 2842019 | P6: 0 | Q6: 0 | R6: 0 | S6: 0 | T6: 0 | U6: 0 | X6: x | Y6: =N6-M6 -> -477119 | Z6: =O6-N6 -> -297721 | AA6: =P6-O6 -> -2842019 | AB6: =Q6-P6 -> 0 | AC6: =R6-Q6 -> 0 | AD6: =S6-R6 -> 0 | AE6: =T6-S6 -> 0 | AF6: =U6-T6 -> 0
A7: 120 | B7: Short-term investments | C7: =BS!G6 -> 4054767 | D7: =BS!H6 -> 5719665 | E7: =BS!I6 -> 942767 | F7: =BS!J6 -> 3174321 | G7: =BS!K6 -> 6558801 | H7: =BS!L6 -> 7544188 | I7: =BS!M6 -> 12393227 | J7: =BS!N6 -> 14547419 | ... O7: =BS!S6 -> 14985489 | P7: =SUM(P8:P10) -> 14838769 | Q7: =SUM(Q8:Q10) -> 14108562 | R7: =SUM(R8:R10) -> 13884887 | S7: =SUM(S8:S10) -> 13930853 | T7: =SUM(T8:T10) -> 13869148 | U7: =SUM(U8:U10) -> 14213259 | V7: x | X7: x | Y7: =N7-M7 -> -1174813 | Z7: =O7-N7 -> -1580750 | AA7: =P7-O7 -> -146720.03 | AB7: =Q7-P7 -> -730207.4 | AC7: =R7-Q7 -> -223674.78 | AD7: =S7-R7 -> 45966.644 | AE7: =T7-S7 -> -61705.126 | AF7: =U7-T7 -> 344110.95
A8: 121 | B8: Short-term investments | C8: =BS!G7 -> 0 | D8: =BS!H7 -> 0 | E8: =BS!I7 -> 0 | F8: =BS!J7 -> 0 | G8: =BS!K7 -> 0 | H8: =BS!L7 -> 0 | I8: =BS!M7 -> 0 | J8: =BS!N7 -> 0 | ... O8: =BS!S7 -> 0 | P8: =WC!O4 -> 0 | Q8: =WC!P4 -> 0 | R8: =WC!Q4 -> 0 | S8: =WC!R4 -> 0 | T8: =WC!S4 -> 0 | U8: =WC!T4 -> 0 | X8: 23 | Y8: =N8-M8 -> 0 | Z8: =O8-N8 -> 0 | AA8: =P8-O8 -> 0 | AB8: =Q8-P8 -> 0 | AC8: =R8-Q8 -> 0 | AD8: =S8-R8 -> 0 | AE8: =T8-S8 -> 0 | AF8: =U8-T8 -> 0
A9: 122 | B9: Provision for diminution | C9: =BS!G8 -> 0 | D9: =BS!H8 -> 0 | E9: =BS!I8 -> 0 | F9: =BS!J8 -> 0 | G9: =BS!K8 -> 0 | H9: =BS!L8 -> 0 | I9: =BS!M8 -> 0 | J9: =BS!N8 -> 0 | ... O9: =BS!S8 -> 0 | P9: =WC!O5 -> 0 | Q9: =WC!P5 -> 0 | R9: =WC!Q5 -> 0 | S9: =WC!R5 -> 0 | T9: =WC!S5 -> 0 | U9: =WC!T5 -> 0 | X9: 3 | Y9: =N9-M9 -> 0 | Z9: =O9-N9 -> 0 | AA9: =P9-O9 -> 0 | AB9: =Q9-P9 -> 0 | AC9: =R9-Q9 -> 0 | AD9: =S9-R9 -> 0 | AE9: =T9-S9 -> 0 | AF9: =U9-T9 -> 0
A10: 123 | B10: Held-to-maturity investment | C10: =BS!G9 -> 4054767 | D10: =BS!H9 -> 5719665 | E10: =BS!I9 -> 942767 | F10: =BS!J9 -> 3174321 | G10: =BS!K9 -> 6558801 | H10: =BS!L9 -> 7544188 | I10: =BS!M9 -> 12393227 | J10: =BS!N9 -> 14547419 | ... O10: =BS!S9 -> 14985489 | P10: =WC!O6 -> 14838769 | Q10: =WC!P6 -> 14108562 | R10: =WC!Q6 -> 13884887 | S10: =WC!R6 -> 13930853 | T10: =WC!S6 -> 13869148 | U10: =WC!T6 -> 14213259 | X10: 23 | Y10: =N10-M10 -> -1174813 | Z10: =O10-N10 -> -1580750 | AA10: =P10-O10 -> -146720.03 | AB10: =Q10-P10 -> -730207.4 | AC10: =R10-Q10 -> -223674.78 | AD10: =S10-R10 -> 45966.644 | AE10: =T10-S10 -> -61705.126 | AF10: =U10-T10 -> 344110.95
A11: 130 | B11: Accounts receivable | C11: =BS!G10 -> 766054 | D11: =BS!H10 -> 1031471 | E11: =BS!I10 -> 1085027 | F11: =BS!J10 -> 1090133 | G11: =BS!K10 -> 715326 | H11: =BS!L10 -> 765631 | I11: =BS!M10 -> 568608 | J11: =BS!N10 -> 590846 | ... O11: =BS!S10 -> 902823 | P11: =SUM(P12:P19) -> 1047528.8 | Q11: =SUM(Q12:Q19) -> 1015073.3 | R11: =SUM(R12:R19) -> 1093678 | S11: =SUM(S12:S19) -> 1131510.5 | T11: =SUM(T12:T19) -> 1152919.5 | U11: =SUM(U12:U19) -> 1196605.3 | V11: x | X11: x | Y11: =N11-M11 -> 589071 | Z11: =O11-N11 -> -915649 | AA11: =P11-O11 -> 144705.85 | AB11: =Q11-P11 -> -32455.544 | AC11: =R11-Q11 -> 78604.717 | AD11: =S11-R11 -> 37832.434 | AE11: =T11-S11 -> 21409.059 | AF11: =U11-T11 -> 43685.798
A12: 131 | B12: Trade accounts receivable | C12: =BS!G11 -> 546565 | D12: =BS!H11 -> 551396 | E12: =BS!I11 -> 621408 | F12: =BS!J11 -> 551219 | G12: =BS!K11 -> 171321 | H12: =BS!L11 -> 244119 | I12: =BS!M11 -> 157655 | J12: =BS!N11 -> 69332 | ... O12: =BS!S11 -> 697568 | P12: =WC!O8 -> 503153.95 | Q12: =WC!P8 -> 387817.98 | R12: =WC!Q8 -> 472563.18 | S12: =WC!R8 -> 484230.26 | T12: =WC!S8 -> 479745.04 | U12: =WC!T8 -> 507907.95 | X12: 9 | Y12: =N12-M12 -> -34226 | Z12: =O12-N12 -> 264427 | AA12: =P12-O12 -> -194414.05 | AB12: =Q12-P12 -> -115335.96 | AC12: =R12-Q12 -> 84745.195 | AD12: =S12-R12 -> 11667.082 | AE12: =T12-S12 -> -4485.2134 | AF12: =U12-T12 -> 28162.907
A13: 132 | B13: Prepayments to suppliers | C13: =BS!G12 -> 160999 | D13: =BS!H12 -> 133998 | E13: =BS!I12 -> 71472 | F13: =BS!J12 -> 166785 | G13: =BS!K12 -> 108550 | H13: =BS!L12 -> 74758 | I13: =BS!M12 -> 54679 | J13: =BS!N12 -> 164204 | ... O13: =BS!S12 -> 31631 | P13: =WC!O9 -> 34511.464 | Q13: =WC!P9 -> 37098.206 | R13: =WC!Q9 -> 37066.296 | S13: =WC!R9 -> 38552.431 | T13: =WC!S9 -> 40308.371 | U13: =WC!T9 -> 40956.534 | X13: 9 | Y13: =N13-M13 -> 15109 | Z13: =O13-N13 -> -16760 | AA13: =P13-O13 -> 2880.4644 | AB13: =Q13-P13 -> 2586.7418 | AC13: =R13-Q13 -> -31.909818 | AD13: =S13-R13 -> 1486.1344 | AE13: =T13-S13 -> 1755.9399 | AF13: =U13-T13 -> 648.16333
A14: 133 | B14: Intercompany receivables | C14: =BS!G13 -> 0 | D14: =BS!H13 -> 0 | E14: =BS!I13 -> 0 | F14: =BS!J13 -> 0 | G14: =BS!K13 -> 0 | H14: =BS!L13 -> 0 | I14: =BS!M13 -> 0 | J14: =BS!N13 -> 0 | ... O14: =BS!S13 -> 0 | P14: =WC!O10 -> 0 | Q14: =WC!P10 -> 0 | R14: =WC!Q10 -> 0 | S14: =WC!R10 -> 0 | T14: =WC!S10 -> 0 | U14: =WC!T10 -> 0 | X14: 9 | Y14: =N14-M14 -> 0 | Z14: =O14-N14 -> 0 | AA14: =P14-O14 -> 0 | AB14: =Q14-P14 -> 0 | AC14: =R14-Q14 -> 0 | AD14: =S14-R14 -> 0 | AE14: =T14-S14 -> 0 | AF14: =U14-T14 -> 0
A15: 134 | B15: Construction contract in progress receivables | C15: =BS!G14 -> 0 | D15: =BS!H14 -> 0 | E15: =BS!I14 -> 0 | F15: =BS!J14 -> 0 | G15: =BS!K14 -> 0 | H15: =BS!L14 -> 0 | I15: =BS!M14 -> 0 | J15: =BS!N14 -> 0 | ... O15: =BS!S14 -> 0 | P15: =WC!O11 -> 0 | Q15: =WC!P11 -> 0 | R15: =WC!Q11 -> 0 | S15: =WC!R11 -> 0 | T15: =WC!S11 -> 0 | U15: =WC!T11 -> 0 | X15: 0 | Y15: =N15-M15 -> 0 | Z15: =O15-N15 -> 0 | AA15: =P15-O15 -> 0 | AB15: =Q15-P15 -> 0 | AC15: =R15-Q15 -> 0 | AD15: =S15-R15 -> 0 | AE15: =T15-S15 -> 0 | AF15: =U15-T15 -> 0
A16: 135 | B16: Short-term loans receivables | C16: =BS!G15 -> 0 | D16: =BS!H15 -> 0 | E16: =BS!I15 -> 0 | F16: =BS!J15 -> 0 | G16: =BS!K15 -> 0 | H16: =BS!L15 -> 502625 | I16: =BS!M15 -> 0 | J16: =BS!N15 -> 0 | ... O16: =BS!S15 -> 0 | P16: =WC!O12 -> 0 | Q16: =WC!P12 -> 0 | R16: =WC!Q12 -> 0 | S16: =WC!R12 -> 0 | T16: =WC!S12 -> 0 | U16: =WC!T12 -> 0 | X16: 9 | Y16: =N16-M16 -> 0 | Z16: =O16-N16 -> 0 | AA16: =P16-O16 -> 0 | AB16: =Q16-P16 -> 0 | AC16: =R16-Q16 -> 0 | AD16: =S16-R16 -> 0 | AE16: =T16-S16 -> 0 | AF16: =U16-T16 -> 0
A17: 136 | B17: Other receivables | C17: =BS!G16 -> 103703 | D17: =BS!H16 -> 391899 | E17: =BS!I16 -> 440463 | F17: =BS!J16 -> 421976 | G17: =BS!K16 -> 488911 | H17: =BS!L16 -> -55871 | I17: =BS!M16 -> 702587 | J17: =BS!N16 -> 699600 | ... O17: =BS!S16 -> 746762 | P17: =WC!O13 -> 843903.66 | Q17: =WC!P13 -> 832227.04 | R17: =WC!Q13 -> 887637.38 | S17: =WC!R13 -> 900667.56 | T17: =WC!S13 -> 941211.16 | U17: =WC!T13 -> 962196.73 | X17: 9 | Y17: =N17-M17 -> 621921 | Z17: =O17-N17 -> -899716 | AA17: =P17-O17 -> 97141.665 | AB17: =Q17-P17 -> -11676.625 | AC17: =R17-Q17 -> 55410.336 | AD17: =S17-R17 -> 13030.182 | AE17: =T17-S17 -> 40543.601 | AF17: =U17-T17 -> 20985.567
A18: 137 | B18: Provision for doubtful debts | C18: =BS!G17 -> -45213 | D18: =BS!H17 -> -45822 | E18: =BS!I17 -> -48316 | F18: =BS!J17 -> -49846 | G18: =BS!K17 -> -53456 | H18: =BS!L17 -> 0 | I18: =BS!M17 -> -346313 | J18: =BS!N17 -> -342290 | ... O18: =BS!S17 -> -573138 | P18: =WC!O14 -> -334040.23 | Q18: =WC!P14 -> -242069.92 | R18: =WC!Q14 -> -303588.83 | S18: =WC!R14 -> -291939.79 | T18: =WC!S14 -> -308345.06 | U18: =WC!T14 -> -314455.9 | X18: 3 | Y18: =N18-M18 -> -13734 | Z18: =O18-N18 -> -263600 | AA18: =P18-O18 -> 239097.77 | AB18: =Q18-P18 -> 91970.304 | AC18: =R18-Q18 -> -61518.905 | AD18: =S18-R18 -> 11649.035 | AE18: =T18-S18 -> -16405.268 | AF18: =U18-T18 -> -6110.8388
A19: 139 | B19: Shortage of current assets waiting for solution | C19: 0 | D19: 0 | E19: 0 | F19: 0 | G19: 0 | H19: 0 | I19: 0 | J19: 0 | K19: 0 | L19: 0 | M19: 0 | N19: 0 | O19: 0 | P19: =WC!O15 -> 0 | Q19: =WC!P15 -> 0 | R19: =WC!Q15 -> 0 | S19: =WC!R15 -> 0 | T19: =WC!S15 -> 0 | U19: =WC!T15 -> 0 | X19: 0 | Y19: =N19-M19 -> 0 | Z19: =O19-N19 -> 0 | AA19: =P19-O19 -> 0 | AB19: =Q19-P19 -> 0 | AC19: =R19-Q19 -> 0 | AD19: =S19-R19 -> 0 | AE19: =T19-S19 -> 0 | AF19: =U19-T19 -> 0
A20: 140 | B20: Inventories | C20: =BS!G18 -> 1686954 | D20: =BS!H18 -> 1868972 | E20: =BS!I18 -> 1924904 | F20: =BS!J18 -> 2126217 | G20: =BS!K18 -> 2003535 | H20: =BS!L18 -> 1813754 | I20: =BS!M18 -> 1967138 | J20: =BS!N18 -> 1446833 | ... O20: =BS!S18 -> 2027352 | P20: =SUM(P21:P22) -> 1949659 | Q20: =SUM(Q21:Q22) -> 1963349.4 | R20: =SUM(R21:R22) -> 2137713.7 | S20: =SUM(S21:S22) -> 2145593.4 | T20: =SUM(T21:T22) -> 2232284.9 | U20: =SUM(U21:U22) -> 2302870 | V20: x | X20: x | Y20: =N20-M20 -> -338961 | Z20: =O20-N20 -> 48808 | AA20: =P20-O20 -> -77693.032 | AB20: =Q20-P20 -> 13690.436 | AC20: =R20-Q20 -> 174364.25 | AD20: =S20-R20 -> 7879.7487 | AE20: =T20-S20 -> 86691.511 | AF20: =U20-T20 -> 70585.091
A21: 141 | B21: Inventories | C21: =BS!G19 -> 1733089 | D21: =BS!H19 -> 1909069 | E21: =BS!I19 -> 1960526 | F21: =BS!J19 -> 2171045 | G21: =BS!K19 -> 2116546 | H21: =BS!L19 -> 2034064 | I21: =BS!M19 -> 2169541 | J21: =BS!N19 -> 1525039 | ... O21: =BS!S19 -> 2109850 | P21: =WC!O17 -> 2018394.7 | Q21: =WC!P17 -> 2034303.2 | R21: =WC!Q17 -> 2217571.9 | S21: =WC!R17 -> 2223370.5 | T21: =WC!S17 -> 2313945.5 | U21: =WC!T17 -> 2387452.5 | X21: 10 | Y21: =N21-M21 -> -350232 | Z21: =O21-N21 -> 66997 | AA21: =P21-O21 -> -91455.261 | AB21: =Q21-P21 -> 15908.465 | AC21: =R21-Q21 -> 183268.69 | AD21: =S21-R21 -> 5798.6514 | AE21: =T21-S21 -> 90574.954 | AF21: =U21-T21 -> 73507.039
A22: 149 | B22: Provision for decline in inventories | C22: =BS!G20 -> -46135 | D22: =BS!H20 -> -40097 | E22: =BS!I20 -> -35622 | F22: =BS!J20 -> -44828 | G22: =BS!K20 -> -113011 | H22: =BS!L20 -> -220310 | I22: =BS!M20 -> -202403 | J22: =BS!N20 -> -78206 | ... O22: =BS!S20 -> -82498 | P22: =WC!O18 -> -68735.771 | Q22: =WC!P18 -> -70953.8 | R22: =WC!Q18 -> -79858.242 | S22: =WC!R18 -> -77777.144 | T22: =WC!S18 -> -81660.588 | U22: =WC!T18 -> -84582.536 | X22: 3 | Y22: =N22-M22 -> 11271 | Z22: =O22-N22 -> -18189 | AA22: =P22-O22 -> 13762.229 | AB22: =Q22-P22 -> -2218.0287 | AC22: =R22-Q22 -> -8904.442 | AD22: =S22-R22 -> 2081.0973 | AE22: =T22-S22 -> -3883.4434 | AF22: =U22-T22 -> -2921.9484
A23: 150 | B23: Other current assets | C23: =BS!G21 -> 125679 | D23: =BS!H21 -> 109981 | E23: =BS!I21 -> 305623 | F23: =BS!J21 -> 878849 | G23: =BS!K21 -> 140066 | H23: =BS!L21 -> 99203 | I23: =BS!M21 -> 119745 | J23: =BS!N21 -> 202146 | ... O23: =BS!S21 -> 208433 | P23: =SUM(P24:P28) -> 203009.22 | Q23: =SUM(Q24:Q28) -> 209203.65 | R23: =SUM(R24:R28) -> 223235.91 | S23: =SUM(S24:S28) -> 225332.75 | T23: =SUM(T24:T28) -> 235102.58 | U23: =SUM(U24:U28) -> 241614.34 | V23: x | X23: x | Y23: =N23-M23 -> 437 | Z23: =O23-N23 -> -17543 | AA23: =P23-O23 -> -5423.7817 | AB23: =Q23-P23 -> 6194.4272 | AC23: =R23-Q23 -> 14032.269 | AD23: =S23-R23 -> 2096.8335 | AE23: =T23-S23 -> 9769.8287 | AF23: =U23-T23 -> 6511.7649
A24: 151 | B24: Short-term prepaid expenses | C24: =BS!G22 -> 26156 | D24: =BS!H22 -> 31533 | E24: =BS!I22 -> 128076 | F24: =BS!J22 -> 67695 | G24: =BS!K22 -> 24913 | H24: =BS!L22 -> 86457 | I24: =BS!M22 -> 97130 | J24: =BS!N22 -> 143822 | ... O24: =BS!S22 -> 139821 | P24: =WC!O20 -> 140696.45 | Q24: =WC!P20 -> 140163.33 | R24: =WC!Q20 -> 151303.72 | S24: =WC!R20 -> 153278.97 | T24: =WC!S20 -> 158933.39 | U24: =WC!T20 -> 163815.81 | X24: 12 | Y24: =N24-M24 -> -26572 | Z24: =O24-N24 -> -5839 | AA24: =P24-O24 -> 875.45063 | AB24: =Q24-P24 -> -533.1164 | AC24: =R24-Q24 -> 11140.384 | AD24: =S24-R24 -> 1975.2509 | AE24: =T24-S24 -> 5654.4197 | AF24: =U24-T24 -> 4882.4192
A25: 152 | B25: VAT to be claimed | C25: =BS!G23 -> 64106 | D25: =BS!H23 -> 32289 | E25: =BS!I23 -> 70980 | F25: =BS!J23 -> 133497 | G25: =BS!K23 -> 112192 | H25: =BS!L23 -> 7565 | I25: =BS!M23 -> 18204 | J25: =BS!N23 -> 22192 | ... O25: =BS!S23 -> 58809 | P25: =WC!O21 -> 52376.791 | Q25: =WC!P21 -> 59770.973 | R25: =WC!Q21 -> 61492.928 | S25: =WC!R21 -> 61537.846 | T25: =WC!S21 -> 65373.227 | U25: =WC!T21 -> 66575.144 | X25: 9 | Y25: =N25-M25 -> 33043 | Z25: =O25-N25 -> -13303 | AA25: =P25-O25 -> -6432.2092 | AB25: =Q25-P25 -> 7394.1826 | AC25: =R25-Q25 -> 1721.9549 | AD25: =S25-R25 -> 44.918082 | AE25: =T25-S25 -> 3835.3809 | AF25: =U25-T25 -> 1201.9163
A26: 153 | B26: Other taxes receivable | C26: =BS!G24 -> 9186 | D26: =BS!H24 -> 11025 | E26: =BS!I24 -> 106510 | F26: =BS!J24 -> 677657 | G26: =BS!K24 -> 2961 | H26: =BS!L24 -> 5182 | I26: =BS!M24 -> 4411 | J26: =BS!N24 -> 36132 | ... O26: =BS!S24 -> 9803 | P26: =WC!O22 -> 9935.977 | Q26: =WC!P22 -> 9269.3379 | R26: =WC!Q22 -> 10439.268 | S26: =WC!R22 -> 10515.932 | T26: =WC!S22 -> 10795.96 | U26: =WC!T22 -> 11223.39 | X26: 9 | Y26: =N26-M26 -> -6035 | Z26: =O26-N26 -> 1600 | AA26: =P26-O26 -> 132.97695 | AB26: =Q26-P26 -> -666.63905 | AC26: =R26-Q26 -> 1169.93 | AD26: =S26-R26 -> 76.664456 | AE26: =T26-S26 -> 280.02811 | AF26: =U26-T26 -> 427.42936
A27: 154 | B27: Government bonds purchased for resale | C27: =BS!G25 -> 0 | D27: =BS!H25 -> 0 | E27: =BS!I25 -> 0 | F27: =BS!J25 -> 0 | G27: =BS!K25 -> 0 | H27: =BS!L25 -> 0 | I27: =BS!M25 -> 0 | J27: =BS!N25 -> 0 | ... O27: =BS!S25 -> 0 | P27: =WC!O23 -> 0 | Q27: =WC!P23 -> 0 | R27: =WC!Q23 -> 0 | S27: =WC!R23 -> 0 | T27: =WC!S23 -> 0 | U27: =WC!T23 -> 0 | X27: 0 | Y27: =N27-M27 -> 0 | Z27: =O27-N27 -> 0 | AA27: =P27-O27 -> 0 | AB27: =Q27-P27 -> 0 | AC27: =R27-Q27 -> 0 | AD27: =S27-R27 -> 0 | AE27: =T27-S27 -> 0 | AF27: =U27-T27 -> 0
A28: 158 | B28: Other current assets | C28: =BS!G26 -> 26231 | D28: =BS!H26 -> 35134 | E28: =BS!I26 -> 57 | F28: =BS!J26 -> 0 | G28: =BS!K26 -> 0 | H28: =BS!L26 -> 0 | I28: =BS!M26 -> 0 | J28: =BS!N26 -> 0 | ... O28: =BS!S26 -> 0 | P28: =WC!O24 -> 0 | Q28: =WC!P24 -> 0 | R28: =WC!Q24 -> 0 | S28: =WC!R24 -> 0 | T28: =WC!S24 -> 0 | U28: =WC!T24 -> 0 | X28: 12 | Y28: =N28-M28 -> 0 | Z28: =O28-N28 -> 0 | AA28: =P28-O28 -> 0 | AB28: =Q28-P28 -> 0 | AC28: =R28-Q28 -> 0 | AD28: =S28-R28 -> 0 | AE28: =T28-S28 -> 0 | AF28: =U28-T28 -> 0
A29: 200 | B29: LONG-TERM ASSETS | C29: =BS!G27 -> 10333058 | D29: =BS!H27 -> 11126890 | E29: =BS!I27 -> 9377631 | F29: =BS!J27 -> 8478519 | G29: =BS!K27 -> 8327362 | H29: =BS!L27 -> 7676575 | I29: =BS!M27 -> 7797874 | J29: =BS!N27 -> 7861591 | ... O29: =BS!S27 -> 10456376 | P29: =SUM(P30,P38,P49,P52,P55,P61,P62) -> 9606126.3 | Q29: =SUM(Q30,Q38,Q49,Q52,Q55,Q61,Q62) -> 8806631.5 | R29: =SUM(R30,R38,R49,R52,R55,R61,R62) -> 8079045.8 | S29: =SUM(S30,S38,S49,S52,S55,S61,S62) -> 7323568.2 | T29: =SUM(T30,T38,T49,T52,T55,T61,T62) -> 6760023.4 | U29: =SUM(U30,U38,U49,U52,U55,U61,U62) -> 6722987.1 | X29: x | Y29: =N29-M29 -> 869455 | Z29: =O29-N29 -> 2083702 | AA29: =P29-O29 -> -850249.68 | AB29: =Q29-P29 -> -799494.82 | AC29: =R29-Q29 -> -727585.69 | AD29: =S29-R29 -> -755477.56 | AE29: =T29-S29 -> -563544.86 | AF29: =U29-T29 -> -37036.323
A30: 210 | B30: Long-term trade receivables | C30: =BS!G28 -> 34 | D30: =BS!H28 -> 8000 | E30: =BS!I28 -> 34495 | F30: =BS!J28 -> 38349 | G30: =BS!K28 -> 20094 | H30: =BS!L28 -> 5861 | I30: =BS!M28 -> 9110 | J30: =BS!N28 -> 11958 | ... O30: =BS!S28 -> 34949 | P30: =O30 -> 34949 | Q30: =P30 -> 34949 | R30: =Q30 -> 34949 | S30: =R30 -> 34949 | T30: =S30 -> 34949 | U30: =T30 -> 34949 | V30: x | X30: x | Y30: =N30-M30 -> -737 | Z30: =O30-N30 -> 984 | AA30: =P30-O30 -> 0 | AB30: =Q30-P30 -> 0 | AC30: =R30-Q30 -> 0 | AD30: =S30-R30 -> 0 | AE30: =T30-S30 -> 0 | AF30: =U30-T30 -> 0
A31: 211 | B31: Long-term trade receivables from customers | C31: =BS!G29 -> 0 | D31: =BS!H29 -> 0 | E31: =BS!I29 -> 0 | F31: =BS!J29 -> 5317 | G31: =BS!K29 -> 4761 | H31: =BS!L29 -> 6078 | I31: =BS!M29 -> 6005 | J31: =BS!N29 -> 5988 | ... O31: =BS!S29 -> 5949 | P31: =O31 -> 5949 | Q31: =P31 -> 5949 | R31: =Q31 -> 5949 | S31: =R31 -> 5949 | T31: =S31 -> 5949 | U31: =T31 -> 5949 | X31: 9 | Y31: =N31-M31 -> 0 | Z31: =O31-N31 -> 0 | AA31: =P31-O31 -> 0 | AB31: =Q31-P31 -> 0 | AC31: =R31-Q31 -> 0 | AD31: =S31-R31 -> 0 | AE31: =T31-S31 -> 0 | AF31: =U31-T31 -> 0
A32: 212 | B32: Long-term prepayments to suppliers | C32: =BS!G30 -> 0 | D32: =BS!H30 -> 0 | E32: =BS!I30 -> 0 | F32: =BS!J30 -> 0 | G32: =BS!K30 -> 0 | H32: =BS!L30 -> 0 | I32: =BS!M30 -> 0 | J32: =BS!N30 -> 0 | ... O32: =BS!S30 -> 0 | P32: =O32 -> 0 | Q32: =P32 -> 0 | R32: =Q32 -> 0 | S32: =R32 -> 0 | T32: =S32 -> 0 | U32: =T32 -> 0 | X32: 9 | Y32: =N32-M32 -> 0 | Z32: =O32-N32 -> 0 | AA32: =P32-O32 -> 0 | AB32: =Q32-P32 -> 0 | AC32: =R32-Q32 -> 0 | AD32: =S32-R32 -> 0 | AE32: =T32-S32 -> 0 | AF32: =U32-T32 -> 0
A33: 213 | B33: Paid-in capital in wholly-owned subsidiaries | C33: 0 | D33: 0 | E33: 0 | F33: 0 | G33: 0 | H33: 0 | I33: 0 | J33: 0 | K33: 0 | L33: 0 | M33: 0 | N33: 0 | O33: 0 | P33: =O33 -> 0 | Q33: =P33 -> 0 | R33: =Q33 -> 0 | S33: =R33 -> 0 | T33: =S33 -> 0 | U33: =T33 -> 0 | X33: 9 | Y33: =N33-M33 -> 0 | Z33: =O33-N33 -> 0 | AA33: =P33-O33 -> 0 | AB33: =Q33-P33 -> 0 | AC33: =R33-Q33 -> 0 | AD33: =S33-R33 -> 0 | AE33: =T33-S33 -> 0 | AF33: =U33-T33 -> 0
A34: 214 | B34: Long-term intercompany receivables | C34: =BS!G31 -> 0 | D34: =BS!H31 -> 0 | E34: =BS!I31 -> 0 | F34: =BS!J31 -> 0 | G34: =BS!K31 -> 0 | H34: =BS!L31 -> 0 | I34: =BS!M31 -> 0 | J34: =BS!N31 -> 0 | ... O34: =BS!S31 -> 0 | P34: =O34 -> 0 | Q34: =P34 -> 0 | R34: =Q34 -> 0 | S34: =R34 -> 0 | T34: =S34 -> 0 | U34: =T34 -> 0 | X34: 9 | Y34: =N34-M34 -> 0 | Z34: =O34-N34 -> 0 | AA34: =P34-O34 -> 0 | AB34: =Q34-P34 -> 0 | AC34: =R34-Q34 -> 0 | AD34: =S34-R34 -> 0 | AE34: =T34-S34 -> 0 | AF34: =U34-T34 -> 0
A35: 215 | B35: Long-term loans receivables | C35: =BS!G32 -> 0 | D35: =BS!H32 -> 0 | E35: =BS!I32 -> 4000 | F35: =BS!J32 -> 4000 | G35: =BS!K32 -> 4000 | H35: =BS!L32 -> 4000 | I35: =BS!M32 -> 4000 | J35: =BS!N32 -> 4000 | ... O35: =BS!S32 -> 0 | P35: =O35 -> 0 | Q35: =P35 -> 0 | R35: =Q35 -> 0 | S35: =R35 -> 0 | T35: =S35 -> 0 | U35: =T35 -> 0 | X35: 9 | Y35: =N35-M35 -> 0 | Z35: =O35-N35 -> 0 | AA35: =P35-O35 -> 0 | AB35: =Q35-P35 -> 0 | AC35: =R35-Q35 -> 0 | AD35: =S35-R35 -> 0 | AE35: =T35-S35 -> 0 | AF35: =U35-T35 -> 0
A36: 216 | B36: Other long-term receivables | C36: =BS!G33 -> 34 | D36: =BS!H33 -> 8000 | E36: =BS!I33 -> 42495 | F36: =BS!J33 -> 46504 | G36: =BS!K33 -> 49119 | H36: =BS!L33 -> 35181 | I36: =BS!M33 -> 38495 | J36: =BS!N33 -> 41278 | ... O36: =BS!S33 -> 35400 | P36: =O36 -> 35400 | Q36: =P36 -> 35400 | R36: =Q36 -> 35400 | S36: =R36 -> 35400 | T36: =S36 -> 35400 | U36: =T36 -> 35400 | X36: 9 | Y36: =N36-M36 -> -737 | Z36: =O36-N36 -> 984 | AA36: =P36-O36 -> 0 | AB36: =Q36-P36 -> 0 | AC36: =R36-Q36 -> 0 | AD36: =S36-R36 -> 0 | AE36: =T36-S36 -> 0 | AF36: =U36-T36 -> 0
A37: 219 | B37: Provision for doubtful LT receivable | C37: =BS!G34 -> 0 | D37: =BS!H34 -> 0 | E37: =BS!I34 -> -12000 | F37: =BS!J34 -> -17472 | G37: =BS!K34 -> -37786 | H37: =BS!L34 -> -39398 | I37: =BS!M34 -> -39390 | J37: =BS!N34 -> -39308 | ... O37: =BS!S34 -> -6400 | P37: =O37 -> -6400 | Q37: =P37 -> -6400 | R37: =Q37 -> -6400 | S37: =R37 -> -6400 | T37: =S37 -> -6400 | U37: =T37 -> -6400 | X37: 3 | Y37: =N37-M37 -> 0 | Z37: =O37-N37 -> 0 | AA37: =P37-O37 -> 0 | AB37: =Q37-P37 -> 0 | AC37: =R37-Q37 -> 0 | AD37: =S37-R37 -> 0 | AE37: =T37-S37 -> 0 | AF37: =U37-T37 -> 0
A38: 220 | B38: Fixed assets | C38: =BS!G35 -> 6099450 | D38: =BS!H35 -> 7033461 | E38: =BS!I35 -> 5854864 | F38: =BS!J35 -> 5462594 | G38: =BS!K35 -> 5008100 | H38: =BS!L35 -> 4567091 | I38: =BS!M35 -> 4685440 | J38: =BS!N35 -> 4874504 | ... O38: =BS!S35 -> 5068260 | P38: =SUM(P39,P42,P45,P48) -> 4374176.1 | Q38: =SUM(Q39,Q42,Q45,Q48) -> 3531907.7 | R38: =SUM(R39,R42,R45,R48) -> 2774676.7 | S38: =SUM(S39,S42,S45,S48) -> 1999346.5 | T38: =SUM(T39,T42,T45,T48) -> 1409046.2 | U38: =SUM(U39,U42,U45,U48) -> 1346659.2 | V38: x | X38: x | Y38: =N38-M38 -> -376470 | Z38: =O38-N38 -> 1475006 | AA38: =P38-O38 -> -694083.86 | AB38: =Q38-P38 -> -842268.41 | AC38: =R38-Q38 -> -757231 | AD38: =S38-R38 -> -775330.2 | AE38: =T38-S38 -> -590300.33 | AF38: =U38-T38 -> -62387.012
A39: 221 | B39: Tangible fixed assets | C39: =BS!G36 -> 4455186 | D39: =BS!H36 -> 4915799 | E39: =BS!I36 -> 4843869 | F39: =BS!J36 -> 4478037 | G39: =BS!K36 -> 4044747 | H39: =BS!L36 -> 3614851 | I39: =BS!M36 -> 3743643 | J39: =BS!N36 -> 3753389 | ... O39: =BS!S36 -> 3492859 | P39: =SUM(P40:P41) -> 2827289 | Q39: =SUM(Q40:Q41) -> 2009923 | R39: =SUM(R40:R41) -> 1253204.3 | S39: =SUM(S40:S41) -> 487055.88 | T39: =SUM(T40:T41) -> -93218.104 | U39: =SUM(U40:U41) -> -143137.5 | X39: 0 | Y39: =N39-M39 -> -405499 | Z39: =O39-N39 -> 1008749 | AA39: =P39-O39 -> -665570.01 | AB39: =Q39-P39 -> -817365.95 | AC39: =R39-Q39 -> -756718.74 | AD39: =S39-R39 -> -766148.42 | AE39: =T39-S39 -> -580273.99 | AF39: =U39-T39 -> -49919.393
A40: 222 | B40: Cost | C40: =BS!G37 -> 7482669 | D40: =BS!H37 -> 8472996 | E40: =BS!I37 -> 9001467 | F40: =BS!J37 -> 9163284 | G40: =BS!K37 -> 9343836 | H40: =BS!L37 -> 9497450 | I40: =BS!M37 -> 10190231 | J40: =BS!N37 -> 10774957 | ... O40: =BS!S37 -> 16040238 | P40: =FA!O10 -> 16119753 | Q40: =FA!P10 -> 16059106 | R40: =FA!Q10 -> 16068535 | S40: =FA!R10 -> 16079057 | T40: =FA!S10 -> 16090157 | U40: =FA!T10 -> 16100972 | X40: 21 | Y40: =N40-M40 -> 79515 | Z40: =O40-N40 -> 4472406 | AA40: =P40-O40 -> 79515 | AB40: =Q40-P40 -> -60647.213 | AC40: =R40-Q40 -> 9429.6855 | AD40: =S40-R40 -> 10521.305 | AE40: =T40-S40 -> 11100.615 | AF40: =U40-T40 -> 10814.617 | AG40: Tangible assets
A41: 223 | B41: Accumulated depreciation | C41: =BS!G38 -> -3027483 | D41: =BS!H38 -> -3557197 | E41: =BS!I38 -> -4157598 | F41: =BS!J38 -> -4685247 | G41: =BS!K38 -> -5299089 | H41: =BS!L38 -> -5882599 | I41: =BS!M38 -> -6446588 | J41: =BS!N38 -> -7021568 | ... O41: =BS!S38 -> -12547379 | P41: =FA!O11 -> -13292464 | Q41: =FA!P11 -> -14049183 | R41: =FA!Q11 -> -14815331 | S41: =FA!R11 -> -15592001 | T41: =FA!S11 -> -16183375 | U41: =FA!T11 -> -16244110 | X41: 2 | Y41: =N41-M41 -> -485014 | Z41: =O41-N41 -> -3463657 | AA41: =P41-O41 -> -745085.01 | AB41: =Q41-P41 -> -756718.74 | AC41: =R41-Q41 -> -766148.42 | AD41: =S41-R41 -> -776669.73 | AE41: =T41-S41 -> -591374.6 | AF41: =U41-T41 -> -60734.01
A42: 224 | B42: Finance lease assets | C42: =BS!G39 -> 0 | D42: =BS!H39 -> 0 | E42: =BS!I39 -> 0 | F42: =BS!J39 -> 0 | G42: =BS!K39 -> 0 | H42: =BS!L39 -> 0 | I42: =BS!M39 -> 0 | J42: =BS!N39 -> 178134 | ... O42: =BS!S39 -> 146556 | P42: =SUM(P43:P44) -> 141320.68 | Q42: =SUM(Q43:Q44) -> 136085.35 | R42: =SUM(R43:R44) -> 130850.03 | S42: =SUM(S43:S44) -> 125614.7 | T42: =SUM(T43:T44) -> 120379.38 | U42: =SUM(U43:U44) -> 115144.05 | X42: x | Y42: =N42-M42 -> -5245 | Z42: =O42-N42 -> -5230 | AA42: =P42-O42 -> -5235.3244 | AB42: =Q42-P42 -> -5235.3244 | AC42: =R42-Q42 -> -5235.3244 | AD42: =S42-R42 -> -5235.3244 | AE42: =T42-S42 -> -5235.3244 | AF42: =U42-T42 -> -5235.3244
A43: 225 | B43: Cost | C43: =BS!G40 -> 0 | D43: =BS!H40 -> 0 | E43: =BS!I40 -> 0 | F43: =BS!J40 -> 0 | G43: =BS!K40 -> 0 | H43: =BS!L40 -> 0 | I43: =BS!M40 -> 0 | J43: =BS!N40 -> 179021 | ... O43: =BS!S40 -> 173583 | P43: =FA!O28 -> 173583 | Q43: =FA!P28 -> 173583 | R43: =FA!Q28 -> 173583 | S43: =FA!R28 -> 173583 | T43: =FA!S28 -> 173583 | U43: =FA!T28 -> 173583 | X43: 21 | Y43: =N43-M43 -> 0 | Z43: =O43-N43 -> 0 | AA43: =P43-O43 -> 0 | AB43: =Q43-P43 -> 0 | AC43: =R43-Q43 -> 0 | AD43: =S43-R43 -> 0 | AE43: =T43-S43 -> 0 | AF43: =U43-T43 -> 0
A44: 226 | B44: Accumulated depreciation | C44: =BS!G41 -> 0 | D44: =BS!H41 -> 0 | E44: =BS!I41 -> 0 | F44: =BS!J41 -> 0 | G44: =BS!K41 -> 0 | H44: =BS!L41 -> 0 | I44: =BS!M41 -> 0 | J44: =BS!N41 -> -887 | ... O44: =BS!S41 -> -27027 | P44: =FA!O29 -> -32262.324 | Q44: =FA!P29 -> -37497.649 | R44: =FA!Q29 -> -42732.973 | S44: =FA!R29 -> -47968.298 | T44: =FA!S29 -> -53203.622 | U44: =FA!T29 -> -58438.946 | X44: 2 | Y44: =N44-M44 -> -5245 | Z44: =O44-N44 -> -5231 | AA44: =P44-O44 -> -5235.3244 | AB44: =Q44-P44 -> -5235.3244 | AC44: =R44-Q44 -> -5235.3244 | AD44: =S44-R44 -> -5235.3244 | AE44: =T44-S44 -> -5235.3244 | AF44: =U44-T44 -> -5235.3244
A45: 227 | B45: Intangible fixed assets | C45: =BS!G42 -> 1644264 | D45: =BS!H42 -> 2117662 | E45: =BS!I42 -> 1010996 | F45: =BS!J42 -> 984557 | G45: =BS!K42 -> 963353 | H45: =BS!L42 -> 952240 | I45: =BS!M42 -> 941798 | J45: =BS!N42 -> 942980 | ... O45: =BS!S42 -> 1428845 | P45: =SUM(P46:P47) -> 1405566.5 | Q45: =SUM(Q46:Q47) -> 1385899.3 | R45: =SUM(R46:R47) -> 1390622.4 | S45: =SUM(S46:S47) -> 1386676 | T45: =SUM(T46:T47) -> 1381884.9 | U45: =SUM(U46:U47) -> 1374652.6 | X45: x | Y45: =N45-M45 -> 34274 | Z45: =O45-N45 -> 471487 | AA45: =P45-O45 -> -23278.519 | AB45: =Q45-P45 -> -19667.135 | AC45: =R45-Q45 -> 4723.0639 | AD45: =S45-R45 -> -3946.4573 | AE45: =T45-S45 -> -4791.0191 | AF45: =U45-T45 -> -7232.2951
A46: 228 | B46: Cost | C46: =BS!G43 -> 1695324 | D46: =BS!H43 -> 2177771 | E46: =BS!I43 -> 1113838 | F46: =BS!J43 -> 1098567 | G46: =BS!K43 -> 1088316 | H46: =BS!L43 -> 1091398 | I46: =BS!M43 -> 1091734 | J46: =BS!N43 -> 1102197 | ... O46: =BS!S43 -> 1727503 | P46: =FA!O17 -> 1744097.3 | Q46: =FA!P17 -> 1764407 | R46: =FA!Q17 -> 1787134.1 | S46: =FA!R17 -> 1804364.2 | T46: =FA!S17 -> 1823649.1 | U46: =FA!T17 -> 1843608.7 | X46: 21 | Y46: =N46-M46 -> 59122 | Z46: =O46-N46 -> 553669 | AA46: =P46-O46 -> 16594.328 | AB46: =Q46-P46 -> 20309.668 | AC46: =R46-Q46 -> 22727.075 | AD46: =S46-R46 -> 17230.144 | AE46: =T46-S46 -> 19284.862 | AF46: =U46-T46 -> 19959.583 | AG46: Intangibles
A47: 229 | B47: Accumulated depreciation | C47: =BS!G44 -> -51060 | D47: =BS!H44 -> -60110 | E47: =BS!I44 -> -102842 | F47: =BS!J44 -> -114010 | G47: =BS!K44 -> -124963 | H47: =BS!L44 -> -139157 | I47: =BS!M44 -> -149936 | J47: =BS!N44 -> -159216 | ... O47: =BS!S44 -> -298658 | P47: =FA!O18 -> -338530.85 | Q47: =FA!P18 -> -378507.65 | R47: =FA!Q18 -> -396511.66 | S47: =FA!R18 -> -417688.26 | T47: =FA!S18 -> -441764.15 | U47: =FA!T18 -> -468956.02 | X47: 2 | Y47: =N47-M47 -> -24848 | Z47: =O47-N47 -> -82182 | AA47: =P47-O47 -> -39872.847 | AB47: =Q47-P47 -> -39976.803 | AC47: =R47-Q47 -> -18004.011 | AD47: =S47-R47 -> -21176.602 | AE47: =T47-S47 -> -24075.882 | AF47: =U47-T47 -> -27191.878
B48: Construction in progress (before 2015) | C48: 531470 | D48: 0 | E48: 0 | F48: 0 | G48: 0 | H48: 0 | I48: 0 | J48: 0 | K48: 0 | L48: 0 | M48: 0 | N48: 0 | O48: 0 | P48: =O48 -> 0 | Q48: =P48 -> 0 | R48: =Q48 -> 0 | S48: =R48 -> 0 | T48: =S48 -> 0 | U48: =T48 -> 0 | X48: x | Y48: =N48-M48 -> 0 | Z48: =O48-N48 -> 0 | AA48: =P48-O48 -> 0 | AB48: =Q48-P48 -> 0 | AC48: =R48-Q48 -> 0 | AD48: =S48-R48 -> 0 | AE48: =T48-S48 -> 0 | AF48: =U48-T48 -> 0
A49: 230 | B49: Investment properties | C49: =BS!G45 -> 32921 | D49: =BS!H45 -> 30770 | E49: =BS!I45 -> 45648 | F49: =BS!J45 -> 66481 | G49: =BS!K45 -> 67658 | H49: =BS!L45 -> 54568 | I49: =BS!M45 -> 58433 | J49: =BS!N45 -> 65174 | ... O49: =BS!S45 -> 238599 | P49: =SUM(P50:P51) -> 228521.42 | Q49: =SUM(Q50:Q51) -> 218450.38 | R49: =SUM(R50:R51) -> 208386.07 | S49: =SUM(S50:S51) -> 198328.7 | T49: =SUM(T50:T51) -> 188278.46 | U49: =SUM(U50:U51) -> 178235.58 | X49: x | Y49: =N49-M49 -> -10760 | Z49: =O49-N49 -> -29706 | AA49: =P49-O49 -> -10077.576 | AB49: =Q49-P49 -> -10071.041 | AC49: =R49-Q49 -> -10064.309 | AD49: =S49-R49 -> -10057.376 | AE49: =T49-S49 -> -10050.235 | AF49: =U49-T49 -> -10042.88
A50: 231 | B50: Cost | C50: =BS!G46 -> 43273 | D50: =BS!H46 -> 43273 | E50: =BS!I46 -> 70886 | F50: =BS!J46 -> 94694 | G50: =BS!K46 -> 83725 | H50: =BS!L46 -> 71444 | I50: =BS!M46 -> 80831 | J50: =BS!N46 -> 92669 | ... O50: =BS!S46 -> 281827 | P50: =FA!O35 -> 282044.84 | Q50: =FA!P35 -> 282269.21 | R50: =FA!Q35 -> 282500.32 | S50: =FA!R35 -> 282738.35 | T50: =FA!S35 -> 282983.53 | U50: =FA!T35 -> 283236.07 | X50: 21 | Y50: =N50-M50 -> 616 | Z50: =O50-N50 -> -29888 | AA50: =P50-O50 -> 217.83813 | AB50: =Q50-P50 -> 224.37328 | AC50: =R50-Q50 -> 231.10448 | AD50: =S50-R50 -> 238.03761 | AE50: =T50-S50 -> 245.17874 | AF50: =U50-T50 -> 252.5341
A51: 232 | B51: Accumulated depreciation | C51: =BS!G47 -> -10352 | D51: =BS!H47 -> -12504 | E51: =BS!I47 -> -25237 | F51: =BS!J47 -> -28213 | G51: =BS!K47 -> -16068 | H51: =BS!L47 -> -16876 | I51: =BS!M47 -> -22397 | J51: =BS!N47 -> -27495 | ... O51: =BS!S47 -> -43228 | P51: =FA!O36 -> -53523.414 | Q51: =FA!P36 -> -63818.828 | R51: =FA!Q36 -> -74114.242 | S51: =FA!R36 -> -84409.656 | T51: =FA!S36 -> -94705.069 | U51: =FA!T36 -> -105000.48 | X51: 2 | Y51: =N51-M51 -> -11376 | Z51: =O51-N51 -> 182 | AA51: =P51-O51 -> -10295.414 | AB51: =Q51-P51 -> -10295.414 | AC51: =R51-Q51 -> -10295.414 | AD51: =S51-R51 -> -10295.414 | AE51: =T51-S51 -> -10295.414 | AF51: =U51-T51 -> -10295.414
A52: 240 | B52: Long-term incomplete assets | C52: =BS!G48 -> 530676 | D52: =BS!H48 -> 401815 | E52: =BS!I48 -> 80876 | F52: =BS!J48 -> 76867 | G52: =BS!K48 -> 111506 | H52: =BS!L48 -> 144378 | I52: =BS!M48 -> 307774 | J52: =BS!N48 -> 28139 | ... O52: =BS!S48 -> 141443 | P52: =SUM(P53:P54) -> 114344.25 | Q52: =SUM(Q53:Q54) -> 151999.06 | R52: =SUM(R53:R54) -> 160853.08 | S52: =SUM(S53:S54) -> 173347.85 | T52: =SUM(T53:T54) -> 181323.81 | U52: =SUM(U53:U54) -> 198068.45 | V52: x | X52: x | Y52: =N52-M52 -> -21905 | Z52: =O52-N52 -> 19429 | AA52: =P52-O52 -> -27098.75 | AB52: =Q52-P52 -> 37654.812 | AC52: =R52-Q52 -> 8854.0156 | AD52: =S52-R52 -> 12494.77 | AE52: =T52-S52 -> 7975.9619 | AF52: =U52-T52 -> 16744.64
A53: 241 | B53: Long-term cost of work in progress | C53: =BS!G49 -> 0 | D53: =BS!H49 -> 0 | E53: =BS!I49 -> 0 | F53: =BS!J49 -> 0 | G53: =BS!K49 -> 0 | H53: =BS!L49 -> 0 | I53: =BS!M49 -> 0 | J53: =BS!N49 -> 0 | ... O53: =BS!S49 -> 0 | P53: 0 | Q53: 0 | R53: 0 | S53: 1 | T53: 1 | U53: 1 | X53: x | Y53: =N53-M53 -> 0 | Z53: =O53-N53 -> 0 | AA53: =P53-O53 -> 0 | AB53: =Q53-P53 -> 0 | AC53: =R53-Q53 -> 0 | AD53: =S53-R53 -> 1 | AE53: =T53-S53 -> 0 | AF53: =U53-T53 -> 0
A54: 242 | B54: Construction in progress | C54: =BS!G50 -> 530676 | D54: =BS!H50 -> 401815 | E54: =BS!I50 -> 80876 | F54: =BS!J50 -> 76867 | G54: =BS!K50 -> 111506 | H54: =BS!L50 -> 144378 | I54: =BS!M50 -> 307774 | J54: =BS!N50 -> 28139 | ... O54: =BS!S50 -> 141443 | P54: =FA!O158 -> 114344.25 | Q54: =FA!P158 -> 151999.06 | R54: =FA!Q158 -> 160853.08 | S54: =FA!R158 -> 173346.85 | T54: =FA!S158 -> 181322.81 | U54: =FA!T158 -> 198067.45 | X54: 21 | Y54: =N54-M54 -> -21905 | Z54: =O54-N54 -> 19429 | AA54: =P54-O54 -> -27098.75 | AB54: =Q54-P54 -> 37654.812 | AC54: =R54-Q54 -> 8854.0156 | AD54: =S54-R54 -> 12493.77 | AE54: =T54-S54 -> 7975.9619 | AF54: =U54-T54 -> 16744.64 | AG54: CIP
A55: 250 | B55: Long-term investments | C55: =BS!G51 -> 2426601 | D55: =BS!H51 -> 2297407 | E55: =BS!I51 -> 2220151 | F55: =BS!J51 -> 1938641 | G55: =BS!K51 -> 2152328 | H55: =BS!L51 -> 2119042 | I55: =BS!M51 -> 2162739 | J55: =BS!N51 -> 2351286 | ... O55: =BS!S51 -> 4194795 | P55: =SUM(P56:P60) -> 4194794 | Q55: =SUM(Q56:Q60) -> 4194794 | R55: =SUM(R56:R60) -> 4194794 | S55: =SUM(S56:S60) -> 4194794 | T55: =SUM(T56:T60) -> 4194794 | U55: =SUM(U56:U60) -> 4194794 | V55: x | X55: x | Y55: =N55-M55 -> 1385169 | Z55: =O55-N55 -> 522234 | AA55: =P55-O55 -> -1 | AB55: =Q55-P55 -> 0 | AC55: =R55-Q55 -> 0 | AD55: =S55-R55 -> 0 | AE55: =T55-S55 -> 0 | AF55: =U55-T55 -> 0
A56: 251 | B56: Investments in subsidiaries | C56: =BS!G52 -> 0 | D56: =BS!H52 -> 0 | E56: =BS!I52 -> 0 | F56: =BS!J52 -> 0 | G56: =BS!K52 -> 0 | H56: =BS!L52 -> 0 | I56: =BS!M52 -> 0 | J56: =BS!N52 -> 0 | ... O56: =BS!S52 -> 0 | P56: =O56 -> 0 | Q56: =P56 -> 0 | R56: =Q56 -> 0 | S56: =R56 -> 0 | T56: =S56 -> 0 | U56: =T56 -> 0 | X56: 25 | Y56: =N56-M56 -> 0 | Z56: =O56-N56 -> 0 | AA56: =P56-O56 -> 0 | AB56: =Q56-P56 -> 0 | AC56: =R56-Q56 -> 0 | AD56: =S56-R56 -> 0 | AE56: =T56-S56 -> 0 | AF56: =U56-T56 -> 0
A57: 252 | B57: Investments in associates | C57: =BS!G53 -> 1771504 | D57: =BS!H53 -> 1636021 | E57: =BS!I53 -> 1895601 | F57: =BS!J53 -> 1602030 | G57: =BS!K53 -> 1747121 | H57: =BS!L53 -> 1800203 | I57: =BS!M53 -> 1878458 | J57: =BS!N53 -> 2049029 | ... O57: =BS!S53 -> 2220383 | P57: =O57 -> 2220383 | Q57: =P57 -> 2220383 | R57: =Q57 -> 2220383 | S57: =R57 -> 2220383 | T57: =S57 -> 2220383 | U57: =T57 -> 2220383 | X57: 25 | Y57: =N57-M57 -> 74655 | Z57: =O57-N57 -> -84456 | AA57: =P57-O57 -> 0 | AB57: =Q57-P57 -> 0 | AC57: =R57-Q57 -> 0 | AD57: =S57-R57 -> 0 | AE57: =T57-S57 -> 0 | AF57: =U57-T57 -> 0
A58: 253 | B58: Other long-term investments | C58: =BS!G54 -> 1143904 | D58: =BS!H54 -> 1111348 | E58: =BS!I54 -> 759465 | F58: =BS!J54 -> 763251 | G58: =BS!K54 -> 736653 | H58: =BS!L54 -> 688511 | I58: =BS!M54 -> 665886 | J58: =BS!N54 -> 665886 | ... O58: =BS!S54 -> 362429 | P58: =O58 -> 362429 | Q58: =P58 -> 362429 | R58: =Q58 -> 362429 | S58: =R58 -> 362429 | T58: =S58 -> 362429 | U58: =T58 -> 362429 | X58: 21 | Y58: =N58-M58 -> -23385 | Z58: =O58-N58 -> -48500 | AA58: =P58-O58 -> 0 | AB58: =Q58-P58 -> 0 | AC58: =R58-Q58 -> 0 | AD58: =S58-R58 -> 0 | AE58: =T58-S58 -> 0 | AF58: =U58-T58 -> 0
A59: 254 | B59: Provision for long-term investments | C59: =BS!G55 -> -488807 | D59: =BS!H55 -> -449962 | E59: =BS!I55 -> -462784 | F59: =BS!J55 -> -447509 | G59: =BS!K55 -> -352315 | H59: =BS!L55 -> -390541 | I59: =BS!M55 -> -435474 | J59: =BS!N55 -> -444497 | ... O59: =BS!S55 -> -361518 | P59: =O59 -> -361518 | Q59: =P59 -> -361518 | R59: =Q59 -> -361518 | S59: =R59 -> -361518 | T59: =S59 -> -361518 | U59: =T59 -> -361518 | X59: 3 | Y59: =N59-M59 -> 37619 | Z59: =O59-N59 -> 17189 | AA59: =P59-O59 -> 0 | AB59: =Q59-P59 -> 0 | AC59: =R59-Q59 -> 0 | AD59: =S59-R59 -> 0 | AE59: =T59-S59 -> 0 | AF59: =U59-T59 -> 0
A60: 255 | B60: Held-to-maturity investment | C60: =BS!G56 -> 0 | D60: =BS!H56 -> 0 | E60: =BS!I56 -> 27869 | F60: =BS!J56 -> 20869 | G60: =BS!K56 -> 20869 | H60: =BS!L56 -> 20869 | I60: =BS!M56 -> 53869 | J60: =BS!N56 -> 80869 | ... O60: =BS!S56 -> 1973500 | P60: =O60 -> 1973500 | Q60: =P60 -> 1973500 | R60: =Q60 -> 1973500 | S60: =R60 -> 1973500 | T60: =S60 -> 1973500 | U60: =T60 -> 1973500 | X60: 21 | Y60: =N60-M60 -> 1296280 | Z60: =O60-N60 -> 638000 | AA60: =P60-O60 -> 0 | AB60: =Q60-P60 -> 0 | AC60: =R60-Q60 -> 0 | AD60: =S60-R60 -> 0 | AE60: =T60-S60 -> 0 | AF60: =U60-T60 -> 0
B61: Good will (before 2015) | C61: 0 | D61: 0 | E61: 0 | F61: 0 | G61: 0 | H61: 0 | I61: 0 | J61: 0 | K61: 0 | L61: 0 | M61: 0 | N61: 0 | O61: 0 | P61: =O61 -> 0 | Q61: =P61 -> 0 | R61: =Q61 -> 0 | S61: =R61 -> 0 | T61: =S61 -> 0 | U61: =T61 -> 0 | X61: x | Y61: =N61-M61 -> 0 | Z61: =O61-N61 -> 0 | AA61: =P61-O61 -> 0 | AB61: =Q61-P61 -> 0 | AC61: =R61-Q61 -> 0 | AD61: =S61-R61 -> 0 | AE61: =T61-S61 -> 0 | AF61: =U61-T61 -> 0
A62: 260 | B62: Other long-term assets | C62: =BS!G57 -> 1243375 | D62: =BS!H57 -> 1355438 | E62: =BS!I57 -> 1141597 | F62: =BS!J57 -> 895665 | G62: =BS!K57 -> 967676 | H62: =BS!L57 -> 785635 | I62: =BS!M57 -> 574377 | J62: =BS!N57 -> 530531 | ... O62: =BS!S57 -> 778330 | P62: =SUM(P63:P67) -> 659341.5 | Q62: =SUM(Q63:Q67) -> 674531.32 | R62: =SUM(R63:R67) -> 705386.91 | S62: =SUM(S63:S67) -> 722802.16 | T62: =SUM(T63:T67) -> 751631.9 | U62: =SUM(U63:U67) -> 770280.83 | V62: x | X62: x | Y62: =N62-M62 -> -105842 | Z62: =O62-N62 -> 95755 | AA62: =P62-O62 -> -118988.5 | AB62: =Q62-P62 -> 15189.812 | AC62: =R62-Q62 -> 30855.595 | AD62: =S62-R62 -> 17415.253 | AE62: =T62-S62 -> 28829.741 | AF62: =U62-T62 -> 18648.929
A63: 261 | B63: Long-term prepayments | C63: =BS!G58 -> 1160881 | D63: =BS!H58 -> 1109120 | E63: =BS!I58 -> 626305 | F63: =BS!J58 -> 756356 | G63: =BS!K58 -> 816991 | H63: =BS!L58 -> 551795 | I63: =BS!M58 -> 328605 | J63: =BS!N58 -> 330639 | ... O63: =BS!S58 -> 552323 | P63: =WC!O84 -> 483336.42 | Q63: =WC!P84 -> 494044.56 | R63: =WC!Q84 -> 516644.02 | S63: =WC!R84 -> 529399.41 | T63: =WC!S84 -> 550515.07 | U63: =WC!T84 -> 564174.04 | X63: 21 | Y63: =N63-M63 -> -95269 | Z63: =O63-N63 -> 97288 | AA63: =P63-O63 -> -68986.578 | AB63: =Q63-P63 -> 10708.143 | AC63: =R63-Q63 -> 22599.453 | AD63: =S63-R63 -> 12755.392 | AE63: =T63-S63 -> 21115.664 | AF63: =U63-T63 -> 13658.969
A64: 262 | B64: Deferred income tax assets | C64: =BS!G59 -> 58862 | D64: =BS!H59 -> 217944 | E64: =BS!I59 -> 486985 | F64: =BS!J59 -> 121283 | G64: =BS!K59 -> 136822 | H64: =BS!L59 -> 184534 | I64: =BS!M59 -> 214736 | J64: =BS!N59 -> 170770 | ... O64: =BS!S59 -> 191956 | P64: =WC!O85 -> 160987.44 | Q64: =WC!P85 -> 165086.71 | R64: =WC!Q85 -> 172638.4 | S64: =WC!R85 -> 176900.66 | T64: =WC!S85 -> 183956.53 | U64: =WC!T85 -> 188520.72 | X64: 21 | Y64: =N64-M64 -> -7913 | Z64: =O64-N64 -> -6551 | AA64: =P64-O64 -> -30968.557 | AB64: =Q64-P64 -> 4099.271 | AC64: =R64-Q64 -> 7551.686 | AD64: =S64-R64 -> 4262.2586 | AE64: =T64-S64 -> 7055.8728 | AF64: =U64-T64 -> 4564.192
A65: 263 | B65: Long-term equipment, material and spare parts | C65: 0 | D65: 0 | E65: =BS!I60 -> 28307 | F65: =BS!J60 -> 18027 | G65: =BS!K60 -> 13862 | H65: =BS!L60 -> 49306 | I65: =BS!M60 -> 31036 | J65: =BS!N60 -> 29122 | K65: =BS!O60 -> 19673 | L65: =BS!P60 -> 19446 | ... O65: =BS!S60 -> 34050 | P65: =WC!O86 -> 15017.638 | Q65: =WC!P86 -> 15400.037 | R65: =WC!Q86 -> 16104.492 | S65: =WC!R86 -> 16502.095 | T65: =WC!S86 -> 17160.299 | U65: =WC!T86 -> 17586.067 | X65: 21 | Y65: =N65-M65 -> -2660 | Z65: =O65-N65 -> 5017 | AA65: =P65-O65 -> -19032.362 | AB65: =Q65-P65 -> 382.39857 | AC65: =R65-Q65 -> 704.45549 | AD65: =S65-R65 -> 397.60279 | AE65: =T65-S65 -> 658.20379 | AF65: =U65-T65 -> 425.76851
A66: 268 | B66: Other long-term assets | C66: =BS!G60 -> 23632 | D66: =BS!H60 -> 28374 | E66: 8 | F66: 0 | G66: 0 | H66: 0 | I66: 0 | J66: 0 | K66: 0 | L66: 0 | M66: 0 | N66: 0 | O66: 0 | P66: =WC!O87 -> 0 | Q66: =WC!P87 -> 0 | R66: =WC!Q87 -> 0 | S66: =WC!R87 -> 0 | T66: =WC!S87 -> 0 | U66: =WC!T87 -> 0 | X66: 21 | Y66: =N66-M66 -> 0 | Z66: =O66-N66 -> 0 | AA66: =P66-O66 -> 0 | AB66: =Q66-P66 -> 0 | AC66: =R66-Q66 -> 0 | AD66: =S66-R66 -> 0 | AE66: =T66-S66 -> 0 | AF66: =U66-T66 -> 0
A67: 269 | B67: Good will | C67: 0 | D67: 0 | E67: 0 | F67: 0 | G67: 0 | H67: 0 | I67: 0 | J67: 0 | K67: 0 | L67: 0 | M67: 0 | N67: 0 | O67: 0 | P67: =O67 -> 0 | Q67: =P67 -> 0 | R67: =Q67 -> 0 | S67: =R67 -> 0 | T67: =S67 -> 0 | U67: =T67 -> 0 | X67: 21 | Y67: =N67-M67 -> 0 | Z67: =O67-N67 -> 0 | AA67: =P67-O67 -> 0 | AB67: =Q67-P67 -> 0 | AC67: =R67-Q67 -> 0 | AD67: =S67-R67 -> 0 | AE67: =T67-S67 -> 0 | AF67: =U67-T67 -> 0
A68: 270 | B68: TOTAL ASSETS | C68: =BS!G62 -> 18814767 | D68: =BS!H62 -> 21674037 | E68: =BS!I62 -> 21571926 | F68: =BS!J62 -> 19192865 | G68: =BS!K62 -> 22013689 | H68: =BS!L62 -> 22366743 | I68: =BS!M62 -> 26962476 | J68: =BS!N62 -> 27374973 | ... O68: =BS!S62 -> 32597354 | P68: =SUM(P3,P29) -> 31392670 | Q68: =SUM(Q3,Q29) -> 31025233 | R68: =SUM(R3,R29) -> 31831627 | S68: =SUM(S3,S29) -> 32298620 | T68: =SUM(T3,T29) -> 33326358 | U68: =SUM(U3,U29) -> 34482459 | X68: x | Y68: =N68-M68 -> -617219 | Z68: =O68-N68 -> -842052 | AA68: =P68-O68 -> -1204684.2 | AB68: =Q68-P68 -> -367437.01 | AC68: =R68-Q68 -> 806394.15 | AD68: =S68-R68 -> 466992.93 | AE68: =T68-S68 -> 1027738.6 | AF68: =U68-T68 -> 1156100.9
A69: 300 | B69: LIABILITIES | C69: =BS!G64 -> 7713292 | D69: =BS!H64 -> 8690568 | E69: =BS!I64 -> 7507222 | F69: =BS!J64 -> 6759685 | G69: =BS!K64 -> 7593163 | H69: =BS!L64 -> 6254837 | I69: =BS!M64 -> 6886229 | J69: =BS!N64 -> 6159696 | ... O69: =BS!S64 -> 9597539 | P69: =SUM(P70,P85) -> 8782869.7 | Q69: =SUM(Q70,Q85) -> 8627404.8 | R69: =SUM(R70,R85) -> 9184072.1 | S69: =SUM(S70,S85) -> 9280130.3 | T69: =SUM(T70,T85) -> 9671543.4 | U69: =SUM(U70,U85) -> 9951327.1 | X69: x | Y69: =N69-M69 -> 430846 | Z69: =O69-N69 -> 595226 | AA69: =P69-O69 -> -814669.26 | AB69: =Q69-P69 -> -155464.97 | AC69: =R69-Q69 -> 556667.38 | AD69: =S69-R69 -> 96058.106 | AE69: =T69-S69 -> 391413.11 | AF69: =U69-T69 -> 279783.74
A70: 310 | B70: Current liabilities | C70: =BS!G65 -> 6146682 | D70: =BS!H65 -> 7559893 | E70: =BS!I65 -> 6759695 | F70: =BS!J65 -> 6473889 | G70: =BS!K65 -> 7401585 | H70: =BS!L65 -> 5925697 | I70: =BS!M65 -> 6087830 | J70: =BS!N65 -> 5173043 | ... O70: =BS!S65 -> 8880281 | P70: =SUM(P71:P84) -> 8068629.7 | Q70: =SUM(Q71:Q84) -> 7916180.8 | R70: =SUM(R71:R84) -> 8475864.1 | S70: =SUM(S71:S84) -> 8574938.3 | T70: =SUM(T71:T84) -> 8969367.4 | U70: =SUM(U71:U84) -> 9252167.1 | X70: x | Y70: =N70-M70 -> 432533 | Z70: =O70-N70 -> 223140 | AA70: =P70-O70 -> -811651.26 | AB70: =Q70-P70 -> -152448.97 | AC70: =R70-Q70 -> 559683.38 | AD70: =S70-R70 -> 99074.106 | AE70: =T70-S70 -> 394429.11 | AF70: =U70-T70 -> 282799.74
A71: 311 | B71: Trade accounts payable | C71: =BS!G68 -> 1854719 | D71: =BS!H68 -> 1792271 | E71: =BS!I68 -> 1558016 | F71: =BS!J68 -> 1876186 | G71: =BS!K68 -> 2020400 | H71: =BS!L68 -> 2027262 | I71: =BS!M68 -> 2427068 | J71: =BS!N68 -> 1652907 | ... O71: =BS!S68 -> 2403618 | P71: =WC!O26 -> 2314532.7 | Q71: =WC!P26 -> 2413960.9 | R71: =WC!Q26 -> 2565343.9 | S71: =WC!R26 -> 2586235.7 | T71: =WC!S26 -> 2704266.8 | U71: =WC!T26 -> 2776276.7 | V71: x | X71: 11 | Y71: =N71-M71 -> 165875 | Z71: =O71-N71 -> -238630 | AA71: =P71-O71 -> -89085.279 | AB71: =Q71-P71 -> 99428.213 | AC71: =R71-Q71 -> 151383 | AD71: =S71-R71 -> 20891.773 | AE71: =T71-S71 -> 118031.08 | AF71: =U71-T71 -> 72009.937
A72: 312 | B72: Advances from customers | C72: =BS!G69 -> 40059 | D72: =BS!H69 -> 77000 | E72: =BS!I69 -> 381636 | F72: =BS!J69 -> 490296 | G72: =BS!K69 -> 89251 | H72: =BS!L69 -> 110463 | I72: =BS!M69 -> 42587 | J72: =BS!N69 -> 64715 | ... O72: =BS!S69 -> 84401 | P72: =WC!O27 -> 84086.112 | Q72: =WC!P27 -> 86227.221 | R72: =WC!Q27 -> 91595.478 | S72: =WC!R27 -> 92884.17 | T72: =WC!S27 -> 96757.538 | U72: =WC!T27 -> 99388.569 | V72: x | X72: 11 | Y72: =N72-M72 -> 49710 | Z72: =O72-N72 -> -10110 | AA72: =P72-O72 -> -314.88843 | AB72: =Q72-P72 -> 2141.1096 | AC72: =R72-Q72 -> 5368.257 | AD72: =S72-R72 -> 1288.6918 | AE72: =T72-S72 -> 3873.3683 | AF72: =U72-T72 -> 2631.0307
A73: 313 | B73: Taxes and other payable to State Budget | C73: =BS!G70 -> 985612 | D73: =BS!H70 -> 2359357 | E73: =BS!I70 -> 857038 | F73: =BS!J70 -> 803769 | G73: =BS!K70 -> 1209757 | H73: =BS!L70 -> 1100614 | I73: =BS!M70 -> 855960 | J73: =BS!N70 -> 1257298 | ... O73: =BS!S70 -> 1625986 | P73: =WC!O28 -> 1408077.3 | Q73: =WC!P28 -> 1443931.5 | R73: =WC!Q28 -> 1613138.5 | S73: =WC!R28 -> 1582496.5 | T73: =WC!S28 -> 1657829.3 | U73: =WC!T28 -> 1715650.5 | V73: x | X73: 11 | Y73: =N73-M73 -> -37655 | Z73: =O73-N73 -> 305125 | AA73: =P73-O73 -> -217908.74 | AB73: =Q73-P73 -> 35854.289 | AC73: =R73-Q73 -> 169206.91 | AD73: =S73-R73 -> -30641.911 | AE73: =T73-S73 -> 75332.792 | AF73: =U73-T73 -> 57821.146
A74: 314 | B74: Payable to employees | C74: =BS!G71 -> 185668 | D74: =BS!H71 -> 263921 | E74: =BS!I71 -> 217026 | F74: =BS!J71 -> 265149 | G74: =BS!K71 -> 222226 | H74: =BS!L71 -> 308694 | I74: =BS!M71 -> 389619 | J74: =BS!N71 -> 360588 | ... O74: =BS!S71 -> 130883 | P74: =WC!O29 -> 151472.25 | Q74: =WC!P29 -> 135740.91 | R74: =WC!Q29 -> 150280.21 | S74: =WC!R29 -> 155296.73 | T74: =WC!S29 -> 157626.63 | U74: =WC!T29 -> 163713.62 | V74: x | X74: 11 | Y74: =N74-M74 -> -106741 | Z74: =O74-N74 -> 2198 | AA74: =P74-O74 -> 20589.254 | AB74: =Q74-P74 -> -15731.344 | AC74: =R74-Q74 -> 14539.301 | AD74: =S74-R74 -> 5016.5208 | AE74: =T74-S74 -> 2329.8962 | AF74: =U74-T74 -> 6086.9976
A75: 315 | B75: Accrued expenses | C75: =BS!G72 -> 455032 | D75: =BS!H72 -> 470125 | E75: =BS!I72 -> 358289 | F75: =BS!J72 -> 375962 | G75: =BS!K72 -> 196526 | H75: =BS!L72 -> 473169 | I75: =BS!M72 -> 433171 | J75: =BS!N72 -> 237321 | ... O75: =BS!S72 -> 580272 | P75: =WC!O30 -> 491284.75 | Q75: =WC!P30 -> 524351.03 | R75: =WC!Q30 -> 574830.4 | S75: =WC!R30 -> 563581.36 | T75: =WC!S30 -> 594287.4 | U75: =WC!T30 -> 612449.05 | V75: x | X75: 11 | Y75: =N75-M75 -> 29680 | Z75: =O75-N75 -> 64415 | AA75: =P75-O75 -> -88987.246 | AB75: =Q75-P75 -> 33066.274 | AC75: =R75-Q75 -> 50479.376 | AD75: =S75-R75 -> -11249.046 | AE75: =T75-S75 -> 30706.039 | AF75: =U75-T75 -> 18161.653
A76: 316 | B76: Intercompany payables | C76: =BS!G73 -> 0 | D76: =BS!H73 -> 0 | E76: =BS!I73 -> 0 | F76: =BS!J73 -> 0 | G76: =BS!K73 -> 0 | H76: =BS!L73 -> 0 | I76: =BS!M73 -> 0 | J76: =BS!N73 -> 0 | ... O76: =BS!S73 -> 0 | P76: =WC!O31 -> 0 | Q76: =WC!P31 -> 0 | R76: =WC!Q31 -> 0 | S76: =WC!R31 -> 0 | T76: =WC!S31 -> 0 | U76: =WC!T31 -> 0 | V76: x | X76: 0 | Y76: =N76-M76 -> 0 | Z76: =O76-N76 -> 0 | AA76: =P76-O76 -> 0 | AB76: =Q76-P76 -> 0 | AC76: =R76-Q76 -> 0 | AD76: =S76-R76 -> 0 | AE76: =T76-S76 -> 0 | AF76: =U76-T76 -> 0
A77: 317 | B77: Construction contract in progress payables | C77: =BS!G74 -> 0 | D77: =BS!H74 -> 0 | E77: =BS!I74 -> 0 | F77: =BS!J74 -> 0 | G77: =BS!K74 -> 0 | H77: =BS!L74 -> 0 | I77: =BS!M74 -> 0 | J77: =BS!N74 -> 0 | ... O77: =BS!S74 -> 0 | P77: =WC!O32 -> 0 | Q77: =WC!P32 -> 0 | R77: =WC!Q32 -> 0 | S77: =WC!R32 -> 0 | T77: =WC!S32 -> 0 | U77: =WC!T32 -> 0 | V77: x | X77: 0 | Y77: =N77-M77 -> 0 | Z77: =O77-N77 -> 0 | AA77: =P77-O77 -> 0 | AB77: =Q77-P77 -> 0 | AC77: =R77-Q77 -> 0 | AD77: =S77-R77 -> 0 | AE77: =T77-S77 -> 0 | AF77: =U77-T77 -> 0
A78: 318 | B78: Short-term unrealized revenue | C78: =BS!G75 -> 0 | D78: =BS!H75 -> 0 | E78: =BS!I75 -> 1721 | F78: =BS!J75 -> 800 | G78: =BS!K75 -> 606 | H78: =BS!L75 -> 1739 | I78: =BS!M75 -> 930 | J78: =BS!N75 -> 782 | ... O78: =BS!S75 -> 546 | P78: =WC!O33 -> 254.32443 | Q78: =WC!P33 -> 347.73382 | R78: =WC!Q33 -> 415.7785 | S78: =WC!R33 -> 359.37526 | T78: =WC!S33 -> 401.40894 | U78: =WC!T33 -> 416.12635 | V78: x | X78: 11 | Y78: =N78-M78 -> 228 | Z78: =O78-N78 -> 318 | AA78: =P78-O78 -> -291.67557 | AB78: =Q78-P78 -> 93.409393 | AC78: =R78-Q78 -> 68.044682 | AD78: =S78-R78 -> -56.403244 | AE78: =T78-S78 -> 42.033681 | AF78: =U78-T78 -> 14.717414
A79: 319 | B79: Other payables | C79: =BS!G76 -> 1901822 | D79: =BS!H76 -> 1028237 | E79: =BS!I76 -> 1042998 | F79: =BS!J76 -> 1288893 | G79: =BS!K76 -> 2630181 | H79: =BS!L76 -> 1079539 | I79: =BS!M76 -> 1079348 | J79: =BS!N76 -> 966920 | ... O79: =BS!S76 -> 3555404 | P79: =WC!O34 -> 3085056.7 | Q79: =WC!P34 -> 2742427.1 | R79: =WC!Q34 -> 2867876.1 | S79: =WC!R34 -> 2938680.9 | T79: =WC!S34 -> 3055893.3 | U79: =WC!T34 -> 3131713.9 | V79: x | X79: 11 | Y79: =N79-M79 -> 610998 | Z79: =O79-N79 -> 45710 | AA79: =P79-O79 -> -470347.31 | AB79: =Q79-P79 -> -342629.54 | AC79: =R79-Q79 -> 125448.91 | AD79: =S79-R79 -> 70804.811 | AE79: =T79-S79 -> 117212.44 | AF79: =U79-T79 -> 75820.542
A80: 320 | B80: Short-term borrowings | C80: =BS!G66 -> 466463 | D80: =BS!H66 -> 437368 | E80: =BS!I66 -> 1051665 | F80: =BS!J66 -> 1042310 | G80: =BS!K66 -> 722904 | H80: =BS!L66 -> 594243 | I80: =BS!M66 -> 560511 | J80: =BS!N66 -> 448792 | ... O80: =BS!S66 -> 267584 | P80: =Debt!O5 -> 293301.63 | Q80: =Debt!P5 -> 319701.63 | R80: =Debt!Q5 -> 348490.16 | S80: =Debt!R5 -> 379883.34 | T80: =Debt!S5 -> 414116.8 | U80: =Debt!T5 -> 451447.54 | X80: 33 | Y80: =N80-M80 -> -284745 | Z80: =O80-N80 -> 22200 | AA80: =P80-O80 -> 25717.633 | AB80: =Q80-P80 -> 26399.997 | AC80: =R80-Q80 -> 28788.534 | AD80: =S80-R80 -> 31393.173 | AE80: =T80-S80 -> 34233.467 | AF80: =U80-T80 -> 37330.736
A81: 321 | B81: Provision for ST liabilities | C81: =BS!G77 -> 5547 | D81: =BS!H77 -> 905144 | E81: =BS!I77 -> 992214 | F81: =BS!J77 -> 0 | G81: =BS!K77 -> 12991 | H81: =BS!L77 -> 7668 | I81: =BS!M77 -> 3711 | J81: =BS!N77 -> 200 | ... O81: =BS!S77 -> 269 | P81: =WC!O36 -> 199.65244 | Q81: =WC!P36 -> 236.90917 | R81: =WC!Q36 -> 254.28478 | S81: =WC!R36 -> 244.60443 | T81: =WC!S36 -> 263.10161 | U81: =WC!T36 -> 269.32654 | V81: x | X81: 3 | Y81: =N81-M81 -> 132 | Z81: =O81-N81 -> 18 | AA81: =P81-O81 -> -69.347557 | AB81: =Q81-P81 -> 37.256728 | AC81: =R81-Q81 -> 17.375613 | AD81: =S81-R81 -> -9.6803565 | AE81: =T81-S81 -> 18.497187 | AF81: =U81-T81 -> 6.2249268
A82: 322 | B82: Bonus and welfare funds | C82: =BS!G78 -> 251759 | D82: =BS!H78 -> 226469 | E82: =BS!I78 -> 299092 | F82: =BS!J78 -> 330525 | G82: =BS!K78 -> 296743 | H82: =BS!L78 -> 222305 | I82: =BS!M78 -> 294925 | J82: =BS!N78 -> 183521 | ... O82: =BS!S78 -> 231318 | P82: =Equity!P107 -> 240364.35 | Q82: =Equity!Q107 -> 249255.71 | R82: =Equity!R107 -> 263639.38 | S82: =Equity!S107 -> 275275.56 | T82: =Equity!T107 -> 287925.05 | U82: =Equity!U107 -> 300841.8 | V82: x | W82: C.C01 - Equity | X82: 0 | Y82: =N82-M82 -> 5049 | Z82: =O82-N82 -> 31899 | AA82: =P82-O82 -> 9046.3472 | AB82: =Q82-P82 -> 8891.3669 | AC82: =R82-Q82 -> 14383.665 | AD82: =S82-R82 -> 11636.177 | AE82: =T82-S82 -> 12649.49 | AF82: =U82-T82 -> 12916.759
A83: 323 | B83: Price stabilization fund | C83: =BS!G79 -> 0 | D83: =BS!H79 -> 0 | E83: =BS!I79 -> 0 | F83: =BS!J79 -> 0 | G83: =BS!K79 -> 0 | H83: =BS!L79 -> 0 | I83: =BS!M79 -> 0 | J83: =BS!N79 -> 0 | ... O83: =BS!S79 -> 0 | P83: =WC!O38 -> 0 | Q83: =WC!P38 -> 0 | R83: =WC!Q38 -> 0 | S83: =WC!R38 -> 0 | T83: =WC!S38 -> 0 | U83: =WC!T38 -> 0 | V83: x | X83: 0 | Y83: =N83-M83 -> 0 | Z83: =O83-N83 -> 0 | AA83: =P83-O83 -> 0 | AB83: =Q83-P83 -> 0 | AC83: =R83-Q83 -> 0 | AD83: =S83-R83 -> 0 | AE83: =T83-S83 -> 0 | AF83: =U83-T83 -> 0
A84: 234 | B84: Government bonds purchased for resale | C84: =BS!G80 -> 0 | D84: =BS!H80 -> 0 | E84: =BS!I80 -> 0 | F84: =BS!J80 -> 0 | G84: =BS!K80 -> 0 | H84: =BS!L80 -> 0 | I84: =BS!M80 -> 0 | J84: =BS!N80 -> 0 | ... O84: =BS!S80 -> 0 | P84: =WC!O39 -> 0 | Q84: =WC!P39 -> 0 | R84: =WC!Q39 -> 0 | S84: =WC!R39 -> 0 | T84: =WC!S39 -> 0 | U84: =WC!T39 -> 0 | V84: x | X84: 0 | Y84: =N84-M84 -> 0 | Z84: =O84-N84 -> 0 | AA84: =P84-O84 -> 0 | AB84: =Q84-P84 -> 0 | AC84: =R84-Q84 -> 0 | AD84: =S84-R84 -> 0 | AE84: =T84-S84 -> 0 | AF84: =U84-T84 -> 0
A85: 330 | B85: Long-term liabilities | C85: =BS!G81 -> 1566610 | D85: =BS!H81 -> 1130675 | E85: =BS!I81 -> 747527 | F85: =BS!J81 -> 285797 | G85: =BS!K81 -> 191578 | H85: =BS!L81 -> 329140 | I85: =BS!M81 -> 798399 | J85: =BS!N81 -> 986653 | ... O85: =BS!S81 -> 717257 | P85: =SUM(P86:P99) -> 714240 | Q85: =SUM(Q86:Q99) -> 711224 | R85: =SUM(R86:R99) -> 708208 | S85: =SUM(S86:S99) -> 705192 | T85: =SUM(T86:T99) -> 702176 | U85: =SUM(U86:U99) -> 699160 | X85: x | Y85: =N85-M85 -> -1685 | Z85: =O85-N85 -> 372084 | AA85: =P85-O85 -> -3017 | AB85: =Q85-P85 -> -3016 | AC85: =R85-Q85 -> -3016 | AD85: =S85-R85 -> -3016 | AE85: =T85-S85 -> -3016 | AF85: =U85-T85 -> -3016
A86: 331 | B86: Long-term trade payables | C86: =BS!G82 -> 0 | D86: =BS!H82 -> 0 | E86: =BS!I82 -> 0 | F86: =BS!J82 -> 0 | G86: =BS!K82 -> 0 | H86: =BS!L82 -> 0 | I86: =BS!M82 -> 100 | J86: =BS!N82 -> 167227 | ... O86: =BS!S82 -> 100 | P86: =O86 -> 100 | Q86: =P86 -> 100 | R86: =Q86 -> 100 | S86: =R86 -> 100 | T86: =S86 -> 100 | U86: =T86 -> 100 | X86: 0 | Y86: =N86-M86 -> 0 | Z86: =O86-N86 -> 0 | AA86: =P86-O86 -> 0 | AB86: =Q86-P86 -> 0 | AC86: =R86-Q86 -> 0 | AD86: =S86-R86 -> 0 | AE86: =T86-S86 -> 0 | AF86: =U86-T86 -> 0
A87: 332 | B87: Long-term advances from customers | C87: 0 | D87: 0 | E87: 0 | F87: 2 | G87: 2 | H87: 2 | I87: 2 | J87: 0 | K87: 0 | L87: 0 | M87: 0 | N87: 0 | O87: 0 | P87: =O87 -> 0 | Q87: =P87 -> 0 | R87: =Q87 -> 0 | S87: =R87 -> 0 | T87: =S87 -> 0 | U87: =T87 -> 0 | X87: 0 | Y87: =N87-M87 -> 0 | Z87: =O87-N87 -> 0 | AA87: =P87-O87 -> 0 | AB87: =Q87-P87 -> 0 | AC87: =R87-Q87 -> 0 | AD87: =S87-R87 -> 0 | AE87: =T87-S87 -> 0 | AF87: =U87-T87 -> 0
A88: 333 | B88: Long-term accrued expenses | C88: =BS!G83 -> 0 | D88: =BS!H83 -> 0 | E88: =BS!I83 -> 0 | F88: =BS!J83 -> 0 | G88: =BS!K83 -> 0 | H88: =BS!L83 -> 0 | I88: =BS!M83 -> 0 | J88: =BS!N83 -> 0 | ... O88: =BS!S83 -> 0 | P88: =O88 -> 0 | Q88: =P88 -> 0 | R88: =Q88 -> 0 | S88: =R88 -> 0 | T88: =S88 -> 0 | U88: =T88 -> 0 | X88: 0 | Y88: =N88-M88 -> 0 | Z88: =O88-N88 -> 0 | AA88: =P88-O88 -> 0 | AB88: =Q88-P88 -> 0 | AC88: =R88-Q88 -> 0 | AD88: =S88-R88 -> 0 | AE88: =T88-S88 -> 0 | AF88: =U88-T88 -> 0
A89: 334 | B89: Intra-company payables for operating capital received | C89: =BS!G84 -> 0 | D89: =BS!H84 -> 0 | E89: =BS!I84 -> 0 | F89: =BS!J84 -> 0 | G89: =BS!K84 -> 0 | H89: =BS!L84 -> 0 | I89: =BS!M84 -> 0 | J89: =BS!N84 -> 0 | ... O89: =BS!S84 -> 0 | P89: =O89 -> 0 | Q89: =P89 -> 0 | R89: =Q89 -> 0 | S89: =R89 -> 0 | T89: =S89 -> 0 | U89: =T89 -> 0 | X89: 0 | Y89: =N89-M89 -> 0 | Z89: =O89-N89 -> 0 | AA89: =P89-O89 -> 0 | AB89: =Q89-P89 -> 0 | AC89: =R89-Q89 -> 0 | AD89: =S89-R89 -> 0 | AE89: =T89-S89 -> 0 | AF89: =U89-T89 -> 0
A90: 335 | B90: Long-term intercompany payables | C90: =BS!G85 -> 0 | D90: =BS!H85 -> 0 | E90: =BS!I85 -> 0 | F90: =BS!J85 -> 0 | G90: =BS!K85 -> 0 | H90: =BS!L85 -> 0 | I90: =BS!M85 -> 0 | J90: =BS!N85 -> 0 | ... O90: =BS!S85 -> 0 | P90: =O90 -> 0 | Q90: =P90 -> 0 | R90: =Q90 -> 0 | S90: =R90 -> 0 | T90: =S90 -> 0 | U90: =T90 -> 0 | X90: 0 | Y90: =N90-M90 -> 0 | Z90: =O90-N90 -> 0 | AA90: =P90-O90 -> 0 | AB90: =Q90-P90 -> 0 | AC90: =R90-Q90 -> 0 | AD90: =S90-R90 -> 0 | AE90: =T90-S90 -> 0 | AF90: =U90-T90 -> 0
A91: 336 | B91: Unrealized revenue | C91: =BS!G92 -> 3378 | D91: =BS!H92 -> 0 | E91: =BS!I92 -> 800 | F91: =BS!J92 -> 0 | G91: =BS!K92 -> 0 | H91: =BS!L92 -> 0 | I91: =BS!M92 -> 0 | J91: =BS!N92 -> 0 | ... O91: =BS!S92 -> 0 | P91: =O91 -> 0 | Q91: =P91 -> 0 | R91: =Q91 -> 0 | S91: =R91 -> 0 | T91: =S91 -> 0 | U91: =T91 -> 0 | X91: 0 | Y91: =N91-M91 -> 0 | Z91: =O91-N91 -> 0 | AA91: =P91-O91 -> 0 | AB91: =Q91-P91 -> 0 | AC91: =R91-Q91 -> 0 | AD91: =S91-R91 -> 0 | AE91: =T91-S91 -> 0 | AF91: =U91-T91 -> 0
A92: 337 | B92: Other long-term payables | C92: =BS!G86 -> 138948 | D92: =BS!H86 -> 62000 | E92: =BS!I86 -> 65183 | F92: =BS!J86 -> 52798 | G92: =BS!K86 -> 53655 | H92: =BS!L86 -> 53172 | I92: =BS!M86 -> 54095 | J92: =BS!N86 -> 54554 | ... O92: =BS!S86 -> 77161 | P92: =O92 -> 77161 | Q92: =P92 -> 77161 | R92: =Q92 -> 77161 | S92: =R92 -> 77161 | T92: =S92 -> 77161 | U92: =T92 -> 77161 | V92: x | X92: 33 | Y92: =N92-M92 -> 1388 | Z92: =O92-N92 -> 20048 | AA92: =P92-O92 -> 0 | AB92: =Q92-P92 -> 0 | AC92: =R92-Q92 -> 0 | AD92: =S92-R92 -> 0 | AE92: =T92-S92 -> 0 | AF92: =U92-T92 -> 0
A93: 338 | B93: Long-term borrowings | C93: =BS!G87 -> 1203543 | D93: =BS!H87 -> 912244 | E93: =BS!I87 -> 610451 | F93: =BS!J87 -> 164412 | G93: =BS!K87 -> 1942 | H93: =BS!L87 -> 14618 | I93: =BS!M87 -> 494245 | J93: =BS!N87 -> 526264 | ... O93: =BS!S87 -> 167936 | P93: =Debt!O13 -> 164919 | Q93: =Debt!P13 -> 161903 | R93: =Debt!Q13 -> 158887 | S93: =Debt!R13 -> 155871 | T93: =Debt!S13 -> 152855 | U93: =Debt!T13 -> 149839 | X93: 33 | Y93: =N93-M93 -> -1384 | Z93: =O93-N93 -> -1508 | AA93: =P93-O93 -> -3017 | AB93: =Q93-P93 -> -3016 | AC93: =R93-Q93 -> -3016 | AD93: =S93-R93 -> -3016 | AE93: =T93-S93 -> -3016 | AF93: =U93-T93 -> -3016
A94: 339 | B94: Convertible bonds | C94: =BS!G88 -> 0 | D94: =BS!H88 -> 0 | E94: =BS!I88 -> 0 | F94: =BS!J88 -> 0 | G94: =BS!K88 -> 0 | H94: =BS!L88 -> 0 | I94: =BS!M88 -> 0 | J94: =BS!N88 -> 0 | ... O94: =BS!S88 -> 0 | P94: =O94 -> 0 | Q94: =P94 -> 0 | R94: =Q94 -> 0 | S94: =R94 -> 0 | T94: =S94 -> 0 | U94: =T94 -> 0 | X94: 0 | Y94: =N94-M94 -> 0 | Z94: =O94-N94 -> 0 | AA94: =P94-O94 -> 0 | AB94: =Q94-P94 -> 0 | AC94: =R94-Q94 -> 0 | AD94: =S94-R94 -> 0 | AE94: =T94-S94 -> 0 | AF94: =U94-T94 -> 0
A95: 340 | B95: Preferred shares | C95: 0 | D95: 0 | E95: 0 | F95: 0 | G95: 0 | H95: 0 | I95: 0 | J95: 0 | K95: 0 | L95: 0 | M95: 0 | N95: 0 | O95: 0 | P95: =O95 -> 0 | Q95: =P95 -> 0 | R95: =Q95 -> 0 | S95: =R95 -> 0 | T95: =S95 -> 0 | U95: =T95 -> 0 | X95: 0 | Y95: =N95-M95 -> 0 | Z95: =O95-N95 -> 0 | AA95: =P95-O95 -> 0 | AB95: =Q95-P95 -> 0 | AC95: =R95-Q95 -> 0 | AD95: =S95-R95 -> 0 | AE95: =T95-S95 -> 0 | AF95: =U95-T95 -> 0
A96: 341 | B96: Deferred income tax liabilities | C96: =BS!G89 -> 54710 | D96: =BS!H89 -> 43190 | E96: =BS!I89 -> 15183 | F96: =BS!J89 -> 13747 | G96: =BS!K89 -> 17217 | H96: =BS!L89 -> 31484 | I96: =BS!M89 -> 30544 | J96: =BS!N89 -> 36606 | ... O96: =BS!S89 -> 406364 | P96: =O96 -> 406364 | Q96: =P96 -> 406364 | R96: =Q96 -> 406364 | S96: =R96 -> 406364 | T96: =S96 -> 406364 | U96: =T96 -> 406364 | X96: 21 | Y96: =N96-M96 -> -1585 | Z96: =O96-N96 -> 357156 | AA96: =P96-O96 -> 0 | AB96: =Q96-P96 -> 0 | AC96: =R96-Q96 -> 0 | AD96: =S96-R96 -> 0 | AE96: =T96-S96 -> 0 | AF96: =U96-T96 -> 0
B97: Provision for severance allowances | C97: =BS!G90 -> 52790 | D97: =BS!H90 -> 0 | E97: =BS!I90 -> 0 | F97: =BS!J90 -> 0 | G97: =BS!K90 -> 0 | H97: =BS!L90 -> 0 | I97: =BS!M90 -> 0 | J97: =BS!N90 -> 0 | ... O97: =BS!S90 -> 0 | P97: =O97 -> 0 | Q97: =P97 -> 0 | R97: =Q97 -> 0 | S97: =R97 -> 0 | T97: =S97 -> 0 | U97: =T97 -> 0 | X97: 3 | Y97: =N97-M97 -> 0 | Z97: =O97-N97 -> 0 | AA97: =P97-O97 -> 0 | AB97: =Q97-P97 -> 0 | AC97: =R97-Q97 -> 0 | AD97: =S97-R97 -> 0 | AE97: =T97-S97 -> 0 | AF97: =U97-T97 -> 0
A98: 342 | B98: Provision for long-term liabilities | C98: =BS!G91 -> 55656 | D98: =BS!H91 -> 55656 | E98: =BS!I91 -> 629 | F98: =BS!J91 -> 568 | G98: =BS!K91 -> 64494 | H98: =BS!L91 -> 145868 | I98: =BS!M91 -> 135417 | J98: =BS!N91 -> 126213 | ... O98: =BS!S91 -> 65696 | P98: =O98 -> 65696 | Q98: =P98 -> 65696 | R98: =Q98 -> 65696 | S98: =R98 -> 65696 | T98: =S98 -> 65696 | U98: =T98 -> 65696 | X98: 3 | Y98: =N98-M98 -> -105 | Z98: =O98-N98 -> -3611 | AA98: =P98-O98 -> 0 | AB98: =Q98-P98 -> 0 | AC98: =R98-Q98 -> 0 | AD98: =S98-R98 -> 0 | AE98: =T98-S98 -> 0 | AF98: =U98-T98 -> 0
A99: 343 | B99: Technology-science development fund | C99: =BS!G93 -> 57586 | D99: =BS!H93 -> 57586 | E99: =BS!I93 -> 55280 | F99: =BS!J93 -> 54271 | G99: =BS!K93 -> 54271 | H99: =BS!L93 -> 83998 | I99: =BS!M93 -> 83998 | J99: =BS!N93 -> 75789 | ... O99: =BS!S93 -> 0 | P99: =O99 -> 0 | Q99: =P99 -> 0 | R99: =Q99 -> 0 | S99: =R99 -> 0 | T99: =S99 -> 0 | U99: =T99 -> 0 | X99: 0 | Y99: =N99-M99 -> 0 | Z99: =O99-N99 -> 0 | AA99: =P99-O99 -> 0 | AB99: =Q99-P99 -> 0 | AC99: =R99-Q99 -> 0 | AD99: =S99-R99 -> 0 | AE99: =T99-S99 -> 0 | AF99: =U99-T99 -> 0
A100: 400 | B100: OWNER'S EQUITY | C100: =BS!G94 -> 11101475 | D100: =BS!H94 -> 12983469 | E100: =BS!I94 -> 14064704 | F100: =BS!J94 -> 12433180 | G100: =BS!K94 -> 14420526 | H100: =BS!L94 -> 16111906 | I100: =BS!M94 -> 20076247 | J100: =BS!N94 -> 21215276 | ... O100: =BS!S94 -> 22999815 | P100: =SUM(P101,P119,P123) -> 22609802 | Q100: =SUM(Q101,Q119,Q123) -> 22397830 | R100: =SUM(R101,R119,R123) -> 22647557 | S100: =SUM(S101,S119,S123) -> 23018492 | T100: =SUM(T101,T119,T123) -> 23654817 | U100: =SUM(U101,U119,U123) -> 24531134 | X100: 0 | Y100: =N100-M100 -> -1048065 | Z100: =O100-N100 -> -1437278 | AA100: =P100-O100 -> -390012.98 | AB100: =Q100-P100 -> -211972.04 | AC100: =R100-Q100 -> 249726.77 | AD100: =S100-R100 -> 370934.82 | AE100: =T100-S100 -> 636325.54 | AF100: =U100-T100 -> 876317.2
...

Sheet 1IS
W1: Growth rate
C2: 2013 | D2: =C2+1 -> 2014 | E2: =D2+1 -> 2015 | F2: =E2+1 -> 2016 | G2: =F2+1 -> 2017 | H2: 2018 | I2: =H2+1 -> 2019 | J2: =I2+1 -> 2020 | K2: =J2+1 -> 2021 | L2: =K2+1 -> 2022 | M2: =L2+1 -> 2023 | N2: =M2+1 -> 2024 | O2: =N2+1 -> 2025 | P2: ="E"&(RIGHT(O2,4)+1) -> E2026 | Q2: ="E"&(RIGHT(P2,4)+1) -> E2027 | R2: ="E"&(RIGHT(Q2,4)+1) -> E2028 | S2: ="E"&(RIGHT(R2,4)+1) -> E2029 | T2: ="E"&(RIGHT(S2,4)+1) -> E2030 | U2: ="E"&(RIGHT(T2,4)+1) -> E2031 | W2: E2024 | X2: E2025 | Y2: E2026 | Z2: E2027 | AA2: E2028 | AB2: E2029 | AC2: E2030 | AD2: E2031
B3: Net sales | C3: =IS!G4 -> 24006260 | D3: =IS!H4 -> 25107165 | E3: =IS!I4 -> 27144302 | F3: =IS!J4 -> 30568678 | G3: =IS!K4 -> 34193391 | H3: =IS!L4 -> 35948553 | I3: =IS!M4 -> 37899060 | J3: =IS!N4 -> 27961324 | ... O3: =IS!S4 -> 25888192 | P3: =Rev!P10 -> 27013433 | Q3: =Rev!Q10 -> 27701284 | R3: =Rev!R10 -> 28968445 | S3: =Rev!S10 -> 29683645 | T3: =Rev!T10 -> 30867609 | U3: =Rev!U10 -> 31633473 | W3: =N3/M3-1 -> 0.046322609 | X3: =O3/N3-1 -> -0.18775561 | Y3: =P3/O3-1 -> 0.043465424 | Z3: =Q3/P3-1 -> 0.025463296 | AA3: =R3/Q3-1 -> 0.045743754 | AB3: =S3/R3-1 -> 0.024688937 | AC3: =T3/S3-1 -> 0.039886075 | AD3: =U3/T3-1 -> 0.024811253
B4: Cost of sales | C4: =-IS!G5 -> -18149503 | D4: =-IS!H5 -> -17636086 | E4: =-IS!I5 -> -19586558 | F4: =-IS!J5 -> -22301143 | G4: =-IS!K5 -> -25327872 | H4: =-IS!L5 -> -27864413 | I4: =-IS!M5 -> -28348431 | J4: =-IS!N5 -> -19460229 | ... O4: =-IS!S5 -> -16587631 | P4: =-Rev!P33 -> -17682700 | Q4: =-Rev!Q33 -> -18223910 | R4: =-Rev!R33 -> -18936439 | S4: =-Rev!S33 -> -19393083 | T4: =-Rev!T33 -> -20096200 | U4: =-Rev!U33 -> -20586396
B5: Gross Profit | C5: =IS!G6 -> 5856757 | D5: =IS!H6 -> 7471080 | E5: =IS!I6 -> 7557744 | F5: =IS!J6 -> 8267535 | G5: =IS!K6 -> 8865518 | H5: =IS!L6 -> 8084139 | I5: =IS!M6 -> 9550629 | J5: =IS!N6 -> 8501095 | ... O5: =IS!S6 -> 9300561 | P5: =P3+P4 -> 9330733.5 | Q5: =Q3+Q4 -> 9477374.2 | R5: =R3+R4 -> 10032006 | S5: =S3+S4 -> 10290562 | T5: =T3+T4 -> 10771409 | U5: =U3+U4 -> 11047078
B6: Financial income | C6: =IS!G7 -> 375322 | D6: =IS!H7 -> 367210 | E6: =IS!I7 -> 418647 | F6: =IS!J7 -> 751041 | G6: =IS!K7 -> 506108 | H6: =IS!L7 -> 630350 | I6: =IS!M7 -> 889853 | J6: =IS!N7 -> 974402 | ... O6: =IS!S7 -> 1006647 | P6: ='FI&FE'!O2 -> 977523.7 | Q6: ='FI&FE'!P2 -> 927502.7 | R6: ='FI&FE'!Q2 -> 922159.3 | S6: ='FI&FE'!R2 -> 919283.02 | T6: ='FI&FE'!S2 -> 916482.27 | U6: ='FI&FE'!T2 -> 939848.61
B7: Financial expenses | C7: =-IS!G8 -> -207140 | D7: =-IS!H8 -> -89058 | E7: =-IS!I8 -> -121795 | F7: =-IS!J8 -> -68664 | G7: =-IS!K8 -> 25806 | H7: =-IS!L8 -> -74635 | I7: =-IS!M8 -> -93010 | J7: =-IS!N8 -> -105449 | ... O7: =-IS!S8 -> -26257 | P7: =-'FI&FE'!O12 -> -29677.657 | Q7: =-'FI&FE'!P12 -> -26823.982 | R7: =-'FI&FE'!Q12 -> -29623.78 | S7: =-'FI&FE'!R12 -> -32320.092 | T7: =-'FI&FE'!S12 -> -34037.104 | U7: =-'FI&FE'!T12 -> -36700.251
B8: of which: interest expenses | C8: =-IS!G9 -> -149827 | D8: =-IS!H9 -> -107216 | E8: =-IS!I9 -> -76591 | F8: =-IS!J9 -> -82182 | G8: =-IS!K9 -> -42112 | H8: =-IS!L9 -> -35245 | I8: =-IS!M9 -> -37367 | J8: =-IS!N9 -> -63681 | ... O8: =-IS!S9 -> -34346 | P8: =-'FI&FE'!O13 -> -33228.324 | Q8: =-'FI&FE'!P13 -> -34924.037 | R8: =-'FI&FE'!Q13 -> -37866.271 | S8: =-'FI&FE'!R13 -> -39228.538 | T8: =-'FI&FE'!S13 -> -41647.58 | U8: =-'FI&FE'!T13 -> -44356.65
B9: Gain/(loss) from joint ventures (from 2015) | C9: =IS!G10 -> 307216 | D9: =IS!H10 -> 343821 | E9: =IS!I10 -> 371954 | F9: =IS!J10 -> 305650 | G9: =IS!K10 -> 411874 | H9: =IS!L10 -> 354965 | I9: =IS!M10 -> 378267 | J9: =IS!N10 -> 267406 | ... O9: =IS!S10 -> 278264 | P9: =AVERAGE(N9:O9) -> 237854.5 | Q9: =AVERAGE(N9:P9) -> 237854.5 | R9: =AVERAGE(P9:Q9) -> 237854.5 | S9: =AVERAGE(Q9:R9) -> 237854.5 | T9: =AVERAGE(R9:S9) -> 237854.5 | U9: =AVERAGE(S9:T9) -> 237854.5
B10: Selling expenses | C10: =-IS!G11 -> -2132049 | D10: =-IS!H11 -> -3177311 | E10: =-IS!I11 -> -2682882 | F10: =-IS!J11 -> -2781731 | G10: =-IS!K11 -> -2811112 | H10: =-IS!L11 -> -2731091 | I10: =-IS!M11 -> -3003291 | J10: =-IS!N11 -> -2859037 | ... O10: =-IS!S11 -> -4022369 | P10: =P3*P45 -> -4052015 | Q10: =Q3*Q45 -> -3878179.8 | R10: =R3*R45 -> -3910740.1 | S10: =S3*S45 -> -4007292.1 | T10: =T3*T45 -> -4167127.2 | U10: =U3*U45 -> -4175618.5
B11: General and admin expenses | C11: =-IS!G12 -> -619075 | D11: =-IS!H12 -> -1041694 | E11: =-IS!I12 -> -1110423 | F11: =-IS!J12 -> -781829 | G11: =-IS!K12 -> -935975 | H11: =-IS!L12 -> -912705 | I11: =-IS!M12 -> -1047842 | J11: =-IS!N12 -> -702005 | ... O11: =-IS!S12 -> -983559 | P11: =P46*P3 -> -864429.86 | Q11: =Q46*Q3 -> -969544.95 | R11: =R46*R3 -> -970442.91 | S11: =S46*S3 -> -1016664.8 | T11: =T46*T3 -> -1045640.3 | U11: =U46*U3 -> -1077515.2
B12: Operating profit/(loss) | C12: =IS!G13 -> 3581029 | D12: =IS!H13 -> 3874048 | E12: =IS!I13 -> 4433244 | F12: =IS!J13 -> 5692001 | G12: =IS!K13 -> 6062219 | H12: =IS!L13 -> 5351023 | I12: =IS!M13 -> 6674606 | J12: =IS!N13 -> 6076411 | ... O12: =IS!S13 -> 5553286 | P12: =P5+P6+P7+P9+P10+P11 -> 5599989.2 | Q12: =Q5+Q6+Q7+Q9+Q10+Q11 -> 5768182.7 | R12: =R5+R6+R7+R9+R10+R11 -> 6281212.7 | S12: =S5+S6+S7+S9+S10+S11 -> 6391422.8 | T12: =T5+T6+T7+T9+T10+T11 -> 6678941.1 | U12: =U5+U6+U7+U9+U10+U11 -> 6934946.8 | W12: =N12/M12-1 -> 0.050776918 | X12: =O12/N12-1 -> -0.021785424 | Y12: =P12/O12-1 -> 0.0084100145 | Z12: =Q12/P12-1 -> 0.030034607 | AA12: =R12/Q12-1 -> 0.088941358 | AB12: =S12/R12-1 -> 0.017545991 | AC12: =T12/S12-1 -> 0.044985019 | AD12: =U12/T12-1 -> 0.038330293
B13: Other incomes | C13: =IS!G14 -> 145914 | D13: =IS!H14 -> 196849 | E13: =IS!I14 -> 132650 | F13: =IS!J14 -> 128295 | G13: =IS!K14 -> 106139 | H13: =IS!L14 -> 81738 | I13: =IS!M14 -> 74504 | J13: =IS!N14 -> 55952 | ... O13: =IS!S14 -> 152603 | P13: =AVERAGE(N13:O13) -> 90458 | Q13: =AVERAGE(N13:P13) -> 90458 | R13: =AVERAGE(P13:Q13) -> 90458 | S13: =AVERAGE(Q13:R13) -> 90458 | T13: =AVERAGE(R13:S13) -> 90458 | U13: =AVERAGE(S13:T13) -> 90458
B14: Other expenses | C14: =-IS!G15 -> -148044 | D14: =-IS!H15 -> -153339 | E14: =-IS!I15 -> -95885 | F14: =-IS!J15 -> -112898 | G14: =-IS!K15 -> -91266 | H14: =-IS!L15 -> -42322 | I14: =-IS!M15 -> -62934 | J14: =-IS!N15 -> -20545 | ... O14: =-IS!S15 -> -53924 | P14: =AVERAGE(N14:O14) -> -55920 | Q14: =AVERAGE(N14:P14) -> -55920 | R14: =AVERAGE(P14:Q14) -> -55920 | S14: =AVERAGE(Q14:R14) -> -55920 | T14: =AVERAGE(R14:S14) -> -55920 | U14: =AVERAGE(S14:T14) -> -55920
B15: Net other income/(expenses) | C15: =IS!G16 -> -2130 | D15: =IS!H16 -> 43510 | E15: =IS!I16 -> 36765 | F15: =IS!J16 -> 15397 | G15: =IS!K16 -> 14873 | H15: =IS!L16 -> 39416 | I15: =IS!M16 -> 11570 | J15: =IS!N16 -> 35407 | ... O15: =IS!S16 -> 98679 | P15: =P13+P14 -> 34538 | Q15: =Q13+Q14 -> 34538 | R15: =R13+R14 -> 34538 | S15: =S13+S14 -> 34538 | T15: =T13+T14 -> 34538 | U15: =U13+U14 -> 34538
B16: Income from investments in other entities | C16: =IS!G10 -> 307216 | D16: =IS!H10 -> 343821 | E16: =IS!I10 -> 371954 | F16: =IS!J10 -> 305650 | G16: =IS!K10 -> 411874 | H16: =IS!L10 -> 354965 | I16: =IS!M10 -> 378267 | J16: =IS!N10 -> 267406 | ... O16: =IS!S10 -> 278264 | P16: 0 | Q16: 0 | R16: 0 | S16: 0 | T16: 0 | U16: 0
B17: Net accounting profit/(loss) before tax | C17: =IS!G17 -> 3578899 | D17: =IS!H17 -> 3917558 | E17: =IS!I17 -> 4470009 | F17: =IS!J17 -> 5707398 | G17: =IS!K17 -> 6077092 | H17: =IS!L17 -> 5390440 | I17: =IS!M17 -> 6686177 | J17: =IS!N17 -> 6111818 | ... O17: =IS!S17 -> 5651966 | P17: =P12+P15+P16 -> 5634527.2 | Q17: =Q12+Q15+Q16 -> 5802720.7 | R17: =R12+R15+R16 -> 6315750.7 | S17: =S12+S15+S16 -> 6425960.8 | T17: =T12+T15+T16 -> 6713479.1 | U17: =U12+U15+U16 -> 6969484.8
B18: Corporate income tax - current | C18: =-IS!G18 -> -1057338 | D18: =-IS!H18 -> -971520 | E18: =-IS!I18 -> -1085883 | F18: =-IS!J18 -> -254203 | G18: =-IS!K18 -> -1140540 | H18: =-IS!L18 -> -1021134 | I18: =-IS!M18 -> -1347172 | J18: =-IS!N18 -> -1124943 | ... O18: =-IS!S18 -> -1057138 | P18: =(P47*P17) -> -1075512.3 | Q18: =Q47*Q17 -> -1092556.6 | R18: =R47*R17 -> -1155869.3 | S18: =S47*S17 -> -1159192.3 | T18: =T47*T17 -> -1187590.6 | U18: =U47*U17 -> -1206423.1
B19: Corporate income tax - deferred | C19: =-IS!G19 -> -26167 | D19: =-IS!H19 -> 103055 | E19: =-IS!I19 -> 215969 | F19: =-IS!J19 -> -798607 | G19: =-IS!K19 -> 12048 | H19: =-IS!L19 -> 33445 | I19: =-IS!M19 -> 31143 | J19: =-IS!N19 -> -50030 | ... O19: =-IS!S19 -> -21702 | P19: 0 | Q19: 0 | R19: 0 | S19: 0 | T19: 0 | U19: 0
B20: Corporate income tax expenses | C20: =-IS!G20 -> -1083505 | D20: =-IS!H20 -> -868465 | E20: =-IS!I20 -> -869913 | F20: =-IS!J20 -> -1052809 | G20: =-IS!K20 -> -1128492 | H20: =-IS!L20 -> -987690 | I20: =-IS!M20 -> -1316029 | J20: =-IS!N20 -> -1174972 | ... O20: =-IS!S20 -> -1078841 | P20: =P18+P19 -> -1075512.3 | Q20: =Q18+Q19 -> -1092556.6 | R20: =R18+R19 -> -1155869.3 | S20: =S18+S19 -> -1159192.3 | T20: =T18+T19 -> -1187590.6 | U20: =U18+U19 -> -1206423.1
B21: Net profit/(loss) after tax | C21: =SUM(C17,C20) -> 2495394 | D21: =SUM(D17,D20) -> 3049093 | E21: =SUM(E17,E20) -> 3600096 | F21: =SUM(F17,F20) -> 4654589 | G21: =SUM(G17,G20) -> 4948600 | H21: =SUM(H17,H20) -> 4402750 | I21: =SUM(I17,I20) -> 5370148 | J21: =SUM(J17,J20) -> 4936846 | ... U21: =SUM(U17,U20) -> 5763061.8 | W21: =N21/M21-1 -> 0.056337959 | X21: =O21/N21-1 -> 0.017431577 | Y21: =P21/O21-1 -> -0.0030854368 | Z21: =Q21/P21-1 -> 0.03315391 | AA21: =R21/Q21-1 -> 0.095478057 | AB21: =S21/R21-1 -> 0.020715038 | AC21: =T21/S21-1 -> 0.049199045 | AD21: =U21/T21-1 -> 0.042920384
B22: Minority interests | C22: =IS!G22 -> 77699 | D22: =IS!H22 -> 109116 | E22: =IS!I22 -> 189800 | F22: =IS!J22 -> 176617 | G22: =IS!K22 -> 237114 | H22: =IS!L22 -> 225318 | I22: =IS!M22 -> 316784 | J22: =IS!N22 -> 213349 | ... O22: =IS!S22 -> 149585 | P22: =P21*P48 -> 159565.52 | Q22: =Q21*Q48 -> 164855.74 | R22: =R21*R48 -> 180595.85 | S22: =S21*S48 -> 184336.9 | T22: =T21*T48 -> 193406.1 | U22: =U21*U48 -> 201707.16
B23: Attributable to parent company | C23: =IS!G23 -> 2417695 | D23: =IS!H23 -> 2939977 | E23: =IS!I23 -> 3410296 | F23: =IS!J23 -> 4477972 | G23: =IS!K23 -> 4711485 | H23: =IS!L23 -> 4177432 | I23: =IS!M23 -> 5053364 | J23: =IS!N23 -> 4723497 | ... O23: =IS!S23 -> 4423540 | P23: =P21-P22 -> 4399449.4 | Q23: =Q21-Q22 -> 4545308.3 | R23: =R21-R22 -> 4979285.5 | S23: =S21-S22 -> 5082431.6 | T23: =T21-T22 -> 5332482.4 | U23: =U21-U22 -> 5561354.6
B24: EPS_basis (VND) | C24: 3350 | D24: 3780 | E24: 4860 | F24: 6190 | G24: 6920 | H24: 6140 | I24: 7480 | J24: 7150 | K24: 5560 | L24: 7980 | M24: 3132 | N24: 3291 | O24: 3347 | P24: =P30 -> 3330.7195 | Q24: =Q30 -> 3441.1459 | R24: =R30 -> 3769.6998 | S24: =S30 -> 3847.7892 | T24: =T30 -> 4037.0968 | U24: =U30 -> 4210.3705
B25: EPS_diluted (VND) | C25: 0 | D25: 0 | E25: 0 | F25: 6190 | G25: 6920 | H25: 0 | I25: 0 | J25: 0 | K25: 0 | L25: 0 | M25: 0 | N25: 0 | O25: 0
B26: Net profit growth | D26: =D21/C21-1 -> 0.22188841 | E26: =E21/D21-1 -> 0.18071046 | F26: =F21/E21-1 -> 0.29290691 | G26: =G21/F21-1 -> 0.063165835 | H26: =H21/G21-1 -> -0.11030392 | I26: =I21/H21-1 -> 0.21972585 | J26: =J21/I21-1 -> -0.080687162 | K26: =K21/J21-1 -> -0.20408597 | ... U26: =U21/T21-1 -> 0.042920384
B27: Trích quỹ khen thưởng, phúc lợi | K27: -170371 | L27: -121347 | M27: -116231 | N27: -125583 | O27: -150126 | P27: =-Equity!P105 -> -127593.91 | Q27: =-Equity!Q105 -> -131824.15 | R27: =-Equity!R105 -> -144410.46 | S27: =-Equity!S105 -> -147401.93 | T27: =-Equity!T105 -> -154653.96 | U27: =-Equity!U105 -> -161291.77
B28: Cổ tức cổ phiếu ưu đãi
B29: Cổ phiếu lưu hành | K29: 641281186 | L29: 641281186 | M29: 1282562372 | N29: 1282562372 | O29: 1282562372 | P29: =N29 -> 1282562372 | Q29: =P29 -> 1282562372 | R29: =Q29 -> 1282562372 | S29: =R29 -> 1282562372 | T29: =S29 -> 1282562372 | U29: =T29 -> 1282562372
B30: EPS_basis (VND) | K30: =(K23+K27)*10^6/K29 -> 5468.5543 | L30: =(L23+L27)*10^6/L29 -> 7956.7343 | M30: =(M23+M27)*10^6/M29 -> 3119.828 | N30: =(N23+N27)*10^6/N29 -> 3278.2265 | O30: =(O23+O27)*10^6/O29 -> 3331.9346 | P30: =(P23+P27)*10^6/P29 -> 3330.7195 | Q30: =(Q23+Q27)*10^6/Q29 -> 3441.1459 | R30: =(R23+R27)*10^6/R29 -> 3769.6998 | ... U30: =(U23+U27)*10^6/U29 -> 4210.3705
B31: EPS_diluted (VND)
B33: SGA margin | H33: =SUM(H10:H11)/H3 -> -0.10136141 | I33: =SUM(I10:I11)/I3 -> -0.1068927 | J33: =SUM(J10:J11)/J3 -> -0.12735599 | K33: =SUM(K10:K11)/K3 -> -0.15538502 | L33: =SUM(L10:L11)/L3 -> -0.15073962 | M33: =SUM(M10:M11)/M3 -> -0.17333168 | N33: =SUM(N10:N11)/N3 -> -0.15314091 | O33: =SUM(O10:O11)/O3 -> -0.19336723 | ... U33: =SUM(U10:U11)/U3 -> -0.1660625
B35: Number of outstanding share | H35: 641281186 | I35: 641281186 | J35: 641281186 | K35: 641281186 | L35: 641281186 | M35: 1282562372 | N35: 1282562372 | O35: 1282562372 | P35: 1282562372 | Q35: 1282562372 | R35: 1282562372 | S35: 1282562372 | T35: 1282562372 | U35: 1282562372
B36: BPS | H36: =('1BS'!H101-'1BS'!H118)*10^6/'1IS'!H35 -> 23462.987 | I36: =('1BS'!I101-'1BS'!I118)*10^6/'1IS'!I35 -> 29324.52 | J36: =('1BS'!J101-'1BS'!J118)*10^6/'1IS'!J35 -> 31094.363 | K36: =('1BS'!K101-'1BS'!K118)*10^6/'1IS'!K35 -> 33092.306 | L36: =('1BS'!L101-'1BS'!L118)*10^6/'1IS'!L35 -> 36084.474 | M36: =('1BS'!M101-'1BS'!M118)*10^6/'1IS'!M35 -> 18878.078 | N36: =('1BS'!N101-'1BS'!N118)*10^6/'1IS'!N35 -> 18152.817 | O36: =('1BS'!O101-'1BS'!O118)*10^6/'1IS'!O35 -> 16492.597 | ... U36: =('1BS'!U101-'1BS'!U118)*10^6/'1IS'!U35 -> 18129.418
B38: GPM | H38: =H5/H3 -> 0.22488079 | I38: =I5/I3 -> 0.25200174 | J38: =J5/J3 -> 0.30403049 | K38: =K5/K3 -> 0.28849011 | L38: =L5/L3 -> 0.3079185 | M38: =M5/M3 -> 0.29845552 | N38: =N5/N3 -> 0.29235928 | O38: =O5/O3 -> 0.35925881 | ... U38: =U5/U3 -> 0.34922114
B39: OPM | H39: =H12/H3 -> 0.14885225 | I39: =I12/I3 -> 0.17611534 | J39: =J12/J3 -> 0.21731485 | K39: =K12/K3 -> 0.18124968 | L39: =L12/L3 -> 0.19524982 | M39: =M12/M3 -> 0.17736013 | N39: =N12/N3 -> 0.17811517 | O39: =O12/O3 -> 0.21451038 | ... U39: =U12/U3 -> 0.21922812
B40: NPM | H40: =H21/H3 -> 0.12247364 | I40: =I21/I3 -> 0.14169607 | J40: =J21/J3 -> 0.17655981 | K40: =K21/K3 -> 0.14898547 | L40: =L21/L3 -> 0.15723105 | M40: =M21/M3 -> 0.13968687 | N40: =N21/N3 -> 0.14102395 | O40: =O21/O3 -> 0.17664907 | ... U40: =U21/U3 -> 0.18218239
B42: EBIT | H42: =H17-H8 -> 5425685 | I42: =I17-I8 -> 6723544 | J42: =J17-J8 -> 6175499 | K42: =K17-K8 -> 4905634 | L42: =L17-L8 -> 6858934 | M42: =M17-M8 -> 5420625 | N42: =N17-N8 -> 5674809 | O42: =O17-O8 -> 5686312 | ... U42: =U17-U8 -> 7013841.5
B43: EBITDA | H43: =H42+'1CF'!E8 -> 6060278 | I43: =I42+'1CF'!F8 -> 7370792 | J43: =J42+'1CF'!G8 -> 6768951 | K43: =K42+'1CF'!H8 -> 5463112 | L43: =L42+'1CF'!I8 -> 7420039 | M43: =M42+'1CF'!J8 -> 5990657 | N43: =N42+'1CF'!K8 -> 6223693 | O43: =O42+'1CF'!L8 -> 6416584 | ... U43: =U42+'1CF'!R8 -> 7117298.1 | Z43: Price | AA43: =Valuation!E21 -> 55678.945
B45: Selling expense | H45: =H10/H3 -> -0.07597221 | I45: =I10/I3 -> -0.079244472 | J45: =J10/J3 -> -0.1022497 | K45: =K10/K3 -> -0.13272172 | L45: =L10/L3 -> -0.12956509 | M45: =M10/M3 -> -0.14704619 | N45: =N10/N3 -> -0.12680422 | O45: =O10/O3 -> -0.15537466 | P45: -0.15 | Q45: -0.14 | R45: -0.135 | S45: -0.135 | T45: -0.135 | U45: -0.132
B46: General and admin expenses | H46: =H11/H3 -> -0.0253892 | I46: =I11/I3 -> -0.027648232 | J46: =J11/J3 -> -0.025106286 | K46: =K11/K3 -> -0.022663296 | L46: =L11/L3 -> -0.02117454 | M46: =M11/M3 -> -0.026285491 | N46: =N11/N3 -> -0.026336691 | O46: =O11/O3 -> -0.037992572 | P46: -0.032 | Q46: -0.035 | R46: =AVERAGE(P46:Q46) -> -0.0335 | S46: =AVERAGE(Q46:R46) -> -0.03425 | T46: =AVERAGE(R46:S46) -> -0.033875 | U46: =AVERAGE(S46:T46) -> -0.0340625
B47: Effective tax rate | H47: =H20/H17 -> -0.18322994 | I47: =I20/I17 -> -0.19682832 | J47: =J20/J17 -> -0.19224591 | K47: =K20/K17 -> -0.19098399 | L47: =L20/L17 -> -0.19279886 | M47: =M20/M17 -> -0.20768563 | N47: =N20/N17 -> -0.20409274 | O47: =O20/O17 -> -0.19087889 | P47: =AVERAGE(O47) -> -0.19087889 | Q47: =AVERAGE(N47:P47)+0.7% -> -0.18828351 | R47: =AVERAGE(O47:Q47)+0.7% -> -0.18301376 | S47: =AVERAGE(P47:R47)+0.7% -> -0.18039205 | T47: =AVERAGE(Q47:S47)+0.7% -> -0.17689644 | U47: =AVERAGE(R47:T47)+0.7% -> -0.17310075
B48: Minority interests | H48: =H22/H21 -> 0.051176651 | I48: =I22/I21 -> 0.058989808 | J48: =J22/J21 -> 0.043215648 | K48: =K22/K21 -> 0.064146967 | L48: =L22/L21 -> 0.050174025 | M48: =M22/M21 -> 0.0323023 | N48: =N22/N21 -> 0.036633655 | O48: =O22/O21 -> 0.03270958 | P48: 0.035 | Q48: 0.035 | R48: 0.035 | S48: 0.035 | T48: 0.035 | U48: 0.035
B50: COGS | H50: =H4/H3 -> -0.77511918 | I50: =I4/I3 -> -0.74799826 | J50: =J4/J3 -> -0.69596951 | K50: =K4/K3 -> -0.71150989 | L50: =L4/L3 -> -0.6920815 | M50: =M4/M3 -> -0.70154452 | N50: =N4/N3 -> -0.70764075 | O50: =O4/O3 -> -0.64074119 | ... U50: =U4/U3 -> -0.65077886
B53: ROE | J53: =J21/AVERAGE('1BS'!I100:J100) -> 0.23912153 | K53: =K21/AVERAGE('1BS'!J100:K100) -> 0.17937911 | L53: =L21/AVERAGE('1BS'!K100:L100) -> 0.23311325 | M53: =M21/AVERAGE('1BS'!L100:M100) -> 0.16994379 | N53: =N21/AVERAGE('1BS'!M100:N100) -> 0.18007097 | O53: =O21/AVERAGE('1BS'!N100:O100) -> 0.19280873 | P53: =P21/AVERAGE('1BS'!O100:P100) -> 0.19991463 | Q53: =Q21/AVERAGE('1BS'!P100:Q100) -> 0.20930513 | ... U53: =U21/AVERAGE('1BS'!T100:U100) -> 0.23920091
B54: PER | K54: =K57/K30 -> 10.807244 | L54: =L57/L30 -> 8.4997183 | M54: =M57/M30 -> 16.395135 | N54: =N57/N30 -> 15.441276 | O54: =O57/O30 -> 14.105919 | P54: =P57/P30 -> 16.716792 | Q54: =Q57/Q30 -> 16.18035 | R54: =R57/R30 -> 14.770127 | ... U54: =U57/U30 -> 13.224239
B55: PBR | K55: =K57/K36 -> 1.7859136 | L55: =L57/L36 -> 1.8742133 | M55: =M57/M36 -> 2.709492 | N55: =N57/N36 -> 2.7885479 | O55: =O57/O36 -> 2.8497635 | P55: =$AA$43/P36 -> 3.411007 | Q55: =$AA$43/Q36 -> 3.42335 | R55: =$AA$43/R36 -> 3.3675094 | S55: =$AA$43/S36 -> 3.2981346 | T55: =$AA$43/T36 -> 3.1964403 | U55: =$AA$43/U36 -> 3.0711932
B57: Price | K57: =59100 -> 59100 | L57: 67630 | M57: 51150 | N57: 50620 | O57: 47000 | P57: =$AA$43 -> 55678.945 | Q57: =$AA$43 -> 55678.945 | R57: =$AA$43 -> 55678.945 | S57: =$AA$43 -> 55678.945 | T57: =$AA$43 -> 55678.945 | U57: =$AA$43 -> 55678.945
B59: EV | K59: =K57*K35/10^6 -> 37899718 | L59: =L57*L35/10^6 -> 43369847 | M59: =M57*M35/10^6 -> 65603065 | N59: =N57*N35/10^6 -> 64923307 | O59: =O57*O35/10^6 -> 60280431 | P59: =P57*P35/10^6 -> 71411720 | Q59: =Q57*Q35/10^6 -> 71411720 | R59: =R57*R35/10^6 -> 71411720 | ... U59: =U57*U35/10^6 -> 71411720

Sheet 1CF
J2: Adjusted | T2: Adjustment | AC2: Raw
A3: Code for CF | B3: ITEMS | C3: Note | D3: 2017 | E3: =D3+1 -> 2018 | F3: =E3+1 -> 2019 | G3: =F3+1 -> 2020 | H3: =G3+1 -> 2021 | I3: =H3+1 -> 2022 | J3: =I3+1 -> 2023 | K3: =J3+1 -> 2024 | L3: =K3+1 -> 2025 | ... R3: =Q3+1 -> 2031 | T3: 2024 | U3: 2025 | V3: 2026 | W3: 2027 | X3: 2028 | Y3: 2029 | Z3: 2030 | AA3: 2031 | AC3: 2024 | AD3: 2025 | AE3: 2026 | AF3: 2027 | AG3: 2028 | AH3: 2029 | AI3: 2030 | AJ3: 2031
AM4: leave
B5: I. CASH FLOWS FROM OPERATING ACTIVITIES | AM5: leave
A6: 1 | B6: Profit/(loss) before tax | D6: =SUMIFS(CF!K:K,CF!$A:$A,'1CF'!$A$6) -> 6077092 | E6: =SUMIFS(CF!L:L,CF!$A:$A,'1CF'!$A$6) -> 5390440 | F6: =SUMIFS(CF!M:M,CF!$A:$A,'1CF'!$A$6) -> 6686177 | G6: =SUMIFS(CF!N:N,CF!$A:$A,'1CF'!$A$6) -> 6111818 | H6: =SUMIFS(CF!O:O,CF!$A:$A,'1CF'!$A$6) -> 4856894 | I6: =SUMIFS(CF!P:P,CF!$A:$A,'1CF'!$A$6) -> 6813417 | J6: =SUMIFS(CF!Q:Q,CF!$A:$A,'1CF'!$A$6) -> 5370410 | K6: =SUMIFS(CF!R:R,CF!$A:$A,'1CF'!$A$6) -> 5647359 | L6: =SUMIFS(CF!S:S,CF!$A:$A,'1CF'!$A$6) -> 5651966 | M6: =V6+AE6 -> 5634527.2 | N6: =W6+AF6 -> 5802720.7 | O6: =X6+AG6 -> 6315750.7 | P6: =Y6+AH6 -> 6425960.8 | Q6: =Z6+AI6 -> 6713479.1 | R6: =AA6+AJ6 -> 6969484.8 | AC6: ='1IS'!N17 -> 5647359 | AD6: ='1IS'!O17 -> 5651966 | AE6: ='1IS'!P17 -> 5634527.2 | AF6: ='1IS'!Q17 -> 5802720.7 | AG6: ='1IS'!R17 -> 6315750.7 | AH6: ='1IS'!S17 -> 6425960.8 | AI6: ='1IS'!T17 -> 6713479.1 | AJ6: ='1IS'!U17 -> 6969484.8 | AM6: leave
B7: Adjustments for: | AM7: leave
A8: 2 | B8: Depreciation and amortisation of fixed assets and investment properties | D8: =SUMIFS(CF!K:K,CF!$A:$A,'1CF'!$A$8) -> 625353 | E8: =SUMIFS(CF!L:L,CF!$A:$A,'1CF'!$A$8) -> 634593 | F8: =SUMIFS(CF!M:M,CF!$A:$A,'1CF'!$A$8) -> 647248 | G8: =SUMIFS(CF!N:N,CF!$A:$A,'1CF'!$A$8) -> 593452 | H8: =SUMIFS(CF!O:O,CF!$A:$A,'1CF'!$A$8) -> 557478 | I8: =SUMIFS(CF!P:P,CF!$A:$A,'1CF'!$A$8) -> 561105 | J8: =SUMIFS(CF!Q:Q,CF!$A:$A,'1CF'!$A$8) -> 570032 | K8: =SUMIFS(CF!R:R,CF!$A:$A,'1CF'!$A$8) -> 548884 | L8: =SUMIFS(CF!S:S,CF!$A:$A,'1CF'!$A$8) -> 730272 | M8: =V8+AE8 -> 800488.6 | N8: =W8+AF8 -> 812226.28 | O8: =X8+AG8 -> 799683.17 | P8: =Y8+AH8 -> 813377.07 | Q8: =Z8+AI8 -> 630981.22 | R8: =AA8+AJ8 -> 103456.63 | AC8: =-SUMIFS('1BS'!Y$3:Y$68,'1BS'!$X$3:$X$68,'1CF'!$A8)+SUMIFS('1BS'!Y$69:Y$124,'1BS'!$X$69:$X$124,'1CF'!$A8) -> 526483 | AD8: =-SUMIFS('1BS'!Z$3:Z$68,'1BS'!$X$3:$X$68,'1CF'!$A8)+SUMIFS('1BS'!Z$69:Z$124,'1BS'!$X$69:$X$124,'1CF'!$A8) -> 3550888 | AE8: =-SUMIFS('1BS'!AA$3:AA$68,'1BS'!$X$3:$X$68,'1CF'!$A8)+SUMIFS('1BS'!AA$69:AA$124,'1BS'!$X$69:$X$124,'1CF'!$A8) -> 800488.6 | AF8: =-SUMIFS('1BS'!AB$3:AB$68,'1BS'!$X$3:$X$68,'1CF'!$A8)+SUMIFS('1BS'!AB$69:AB$124,'1BS'!$X$69:$X$124,'1CF'!$A8) -> 812226.28 | AG8: =-SUMIFS('1BS'!AC$3:AC$68,'1BS'!$X$3:$X$68,'1CF'!$A8)+SUMIFS('1BS'!AC$69:AC$124,'1BS'!$X$69:$X$124,'1CF'!$A8) -> 799683.17 | AH8: =-SUMIFS('1BS'!AD$3:AD$68,'1BS'!$X$3:$X$68,'1CF'!$A8)+SUMIFS('1BS'!AD$69:AD$124,'1BS'!$X$69:$X$124,'1CF'!$A8) -> 813377.07 | AI8: =-SUMIFS('1BS'!AE$3:AE$68,'1BS'!$X$3:$X$68,'1CF'!$A8)+SUMIFS('1BS'!AE$69:AE$124,'1BS'!$X$69:$X$124,'1CF'!$A8) -> 630981.22 | AJ8: =-SUMIFS('1BS'!AF$3:AF$68,'1BS'!$X$3:$X$68,'1CF'!$A8)+SUMIFS('1BS'!AF$69:AF$124,'1BS'!$X$69:$X$124,'1CF'!$A8) -> 103456.63 | AM8: leave
A9: 3 | B9: Provisions | D9: =SUMIFS(CF!K:K,CF!$A:$A,'1CF'!$A$9) -> 81974 | E9: =SUMIFS(CF!L:L,CF!$A:$A,'1CF'!$A$9) -> 241181 | F9: =SUMIFS(CF!M:M,CF!$A:$A,'1CF'!$A$9) -> 358145 | G9: =SUMIFS(CF!N:N,CF!$A:$A,'1CF'!$A$9) -> -41309 | H9: =SUMIFS(CF!O:O,CF!$A:$A,'1CF'!$A$9) -> -63137 | I9: =SUMIFS(CF!P:P,CF!$A:$A,'1CF'!$A$9) -> -375 | J9: =SUMIFS(CF!Q:Q,CF!$A:$A,'1CF'!$A$9) -> 3418 | K9: =SUMIFS(CF!R:R,CF!$A:$A,'1CF'!$A$9) -> 4315 | L9: =SUMIFS(CF!S:S,CF!$A:$A,'1CF'!$A$9) -> 42467 | M9: =V9+AE9 -> -252929.35 | N9: =W9+AF9 -> -89715.018 | O9: =X9+AG9 -> 70440.723 | P9: =Y9+AH9 -> -13739.812 | Q9: =Z9+AI9 -> 20307.209 | R9: =AA9+AJ9 -> 9039.0122 | AC9: =-SUMIFS('1BS'!Y$3:Y$68,'1BS'!$X$3:$X$68,'1CF'!$A9)+SUMIFS('1BS'!Y$69:Y$124,'1BS'!$X$69:$X$124,'1CF'!$A9) -> -35129 | AD9: =-SUMIFS('1BS'!Z$3:Z$68,'1BS'!$X$3:$X$68,'1CF'!$A9)+SUMIFS('1BS'!Z$69:Z$124,'1BS'!$X$69:$X$124,'1CF'!$A9) -> 261007 | AE9: =-SUMIFS('1BS'!AA$3:AA$68,'1BS'!$X$3:$X$68,'1CF'!$A9)+SUMIFS('1BS'!AA$69:AA$124,'1BS'!$X$69:$X$124,'1CF'!$A9) -> -252929.35 | AF9: =-SUMIFS('1BS'!AB$3:AB$68,'1BS'!$X$3:$X$68,'1CF'!$A9)+SUMIFS('1BS'!AB$69:AB$124,'1BS'!$X$69:$X$124,'1CF'!$A9) -> -89715.018 | AG9: =-SUMIFS('1BS'!AC$3:AC$68,'1BS'!$X$3:$X$68,'1CF'!$A9)+SUMIFS('1BS'!AC$69:AC$124,'1BS'!$X$69:$X$124,'1CF'!$A9) -> 70440.723 | AH9: =-SUMIFS('1BS'!AD$3:AD$68,'1BS'!$X$3:$X$68,'1CF'!$A9)+SUMIFS('1BS'!AD$69:AD$124,'1BS'!$X$69:$X$124,'1CF'!$A9) -> -13739.812 | AI9: =-SUMIFS('1BS'!AE$3:AE$68,'1BS'!$X$3:$X$68,'1CF'!$A9)+SUMIFS('1BS'!AE$69:AE$124,'1BS'!$X$69:$X$124,'1CF'!$A9) -> 20307.209 | AJ9: =-SUMIFS('1BS'!AF$3:AF$68,'1BS'!$X$3:$X$68,'1CF'!$A9)+SUMIFS('1BS'!AF$69:AF$124,'1BS'!$X$69:$X$124,'1CF'!$A9) -> 9039.0122 | AM9: leave
A10: 4 | B10: Foreign exchange (gains)/losses arising from revaluation of monetary accounts | D10: =SUMIFS(CF!K:K,CF!$A:$A,'1CF'!$A$10) -> 106 | E10: =SUMIFS(CF!L:L,CF!$A:$A,'1CF'!$A$10) -> -72 | F10: =SUMIFS(CF!M:M,CF!$A:$A,'1CF'!$A$10) -> 790 | G10: =SUMIFS(CF!N:N,CF!$A:$A,'1CF'!$A$10) -> 10994 | H10: =SUMIFS(CF!O:O,CF!$A:$A,'1CF'!$A$10) -> -24130 | I10: =SUMIFS(CF!P:P,CF!$A:$A,'1CF'!$A$10) -> -6770 | J10: =SUMIFS(CF!Q:Q,CF!$A:$A,'1CF'!$A$10) -> 8344 | K10: =SUMIFS(CF!R:R,CF!$A:$A,'1CF'!$A$10) -> 581 | L10: =SUMIFS(CF!S:S,CF!$A:$A,'1CF'!$A$10) -> 24 | M10: =V10+AE10 -> 0 | N10: =W10+AF10 -> 0 | O10: =X10+AG10 -> 0 | P10: =Y10+AH10 -> 0 | Q10: =Z10+AI10 -> 0 | R10: =AA10+AJ10 -> 0 | AC10: =-SUMIFS('1BS'!Y$3:Y$68,'1BS'!$X$3:$X$68,'1CF'!$A10)+SUMIFS('1BS'!Y$69:Y$124,'1BS'!$X$69:$X$124,'1CF'!$A10) -> 0 | AD10: =-SUMIFS('1BS'!Z$3:Z$68,'1BS'!$X$3:$X$68,'1CF'!$A10)+SUMIFS('1BS'!Z$69:Z$124,'1BS'!$X$69:$X$124,'1CF'!$A10) -> 0 | AE10: =-SUMIFS('1BS'!AA$3:AA$68,'1BS'!$X$3:$X$68,'1CF'!$A10)+SUMIFS('1BS'!AA$69:AA$124,'1BS'!$X$69:$X$124,'1CF'!$A10) -> 0 | AF10: =-SUMIFS('1BS'!AB$3:AB$68,'1BS'!$X$3:$X$68,'1CF'!$A10)+SUMIFS('1BS'!AB$69:AB$124,'1BS'!$X$69:$X$124,'1CF'!$A10) -> 0 | AG10: =-SUMIFS('1BS'!AC$3:AC$68,'1BS'!$X$3:$X$68,'1CF'!$A10)+SUMIFS('1BS'!AC$69:AC$124,'1BS'!$X$69:$X$124,'1CF'!$A10) -> 0 | AH10: =-SUMIFS('1BS'!AD$3:AD$68,'1BS'!$X$3:$X$68,'1CF'!$A10)+SUMIFS('1BS'!AD$69:AD$124,'1BS'!$X$69:$X$124,'1CF'!$A10) -> 0 | AI10: =-SUMIFS('1BS'!AE$3:AE$68,'1BS'!$X$3:$X$68,'1CF'!$A10)+SUMIFS('1BS'!AE$69:AE$124,'1BS'!$X$69:$X$124,'1CF'!$A10) -> 0 | AJ10: =-SUMIFS('1BS'!AF$3:AF$68,'1BS'!$X$3:$X$68,'1CF'!$A10)+SUMIFS('1BS'!AF$69:AF$124,'1BS'!$X$69:$X$124,'1CF'!$A10) -> 0 | AM10: leave
A11: 5 | B11: (Profits)/losses from investing activities | D11: =SUMIFS(CF!K:K,CF!$A:$A,'1CF'!$A$11) -> -920688 | E11: =SUMIFS(CF!L:L,CF!$A:$A,'1CF'!$A$11) -> -598929 | F11: =SUMIFS(CF!M:M,CF!$A:$A,'1CF'!$A$11) -> -861838 | G11: =SUMIFS(CF!N:N,CF!$A:$A,'1CF'!$A$11) -> -1200918 | H11: =SUMIFS(CF!O:O,CF!$A:$A,'1CF'!$A$11) -> -1146221 | I11: =SUMIFS(CF!P:P,CF!$A:$A,'1CF'!$A$11) -> -1030694 | J11: =SUMIFS(CF!Q:Q,CF!$A:$A,'1CF'!$A$11) -> -1393861 | K11: =SUMIFS(CF!R:R,CF!$A:$A,'1CF'!$A$11) -> -1051087 | L11: =SUMIFS(CF!S:S,CF!$A:$A,'1CF'!$A$11) -> -1273875 | M11: =V11+AE11 -> -960583.2 | N11: =W11+AF11 -> -913313.45 | O11: =X11+AG11 -> -906594.42 | P11: =Y11+AH11 -> -904404.96 | Q11: =Z11+AI11 -> -901260.3 | R11: =AA11+AJ11 -> -924798.59 | T11: =-'FI&FE'!M3 -> -1044633 | U11: =-'FI&FE'!N3 -> -995208 | V11: =-'FI&FE'!O3 -> -960583.2 | W11: =-'FI&FE'!P3 -> -913313.45 | X11: =-'FI&FE'!Q3 -> -906594.42 | Y11: =-'FI&FE'!R3 -> -904404.96 | Z11: =-'FI&FE'!S3 -> -901260.3 | AA11: =-'FI&FE'!T3 -> -924798.59 | AC11: =-SUMIFS('1BS'!Y$3:Y$68,'1BS'!$X$3:$X$68,'1CF'!$A11)+SUMIFS('1BS'!Y$69:Y$124,'1BS'!$X$69:$X$124,'1CF'!$A11) -> 0 | AD11: =-SUMIFS('1BS'!Z$3:Z$68,'1BS'!$X$3:$X$68,'1CF'!$A11)+SUMIFS('1BS'!Z$69:Z$124,'1BS'!$X$69:$X$124,'1CF'!$A11) -> 0 | AE11: =-SUMIFS('1BS'!AA$3:AA$68,'1BS'!$X$3:$X$68,'1CF'!$A11)+SUMIFS('1BS'!AA$69:AA$124,'1BS'!$X$69:$X$124,'1CF'!$A11) -> 0 | AF11: =-SUMIFS('1BS'!AB$3:AB$68,'1BS'!$X$3:$X$68,'1CF'!$A11)+SUMIFS('1BS'!AB$69:AB$124,'1BS'!$X$69:$X$124,'1CF'!$A11) -> 0 | AG11: =-SUMIFS('1BS'!AC$3:AC$68,'1BS'!$X$3:$X$68,'1CF'!$A11)+SUMIFS('1BS'!AC$69:AC$124,'1BS'!$X$69:$X$124,'1CF'!$A11) -> 0 | AH11: =-SUMIFS('1BS'!AD$3:AD$68,'1BS'!$X$3:$X$68,'1CF'!$A11)+SUMIFS('1BS'!AD$69:AD$124,'1BS'!$X$69:$X$124,'1CF'!$A11) -> 0 | AI11: =-SUMIFS('1BS'!AE$3:AE$68,'1BS'!$X$3:$X$68,'1CF'!$A11)+SUMIFS('1BS'!AE$69:AE$124,'1BS'!$X$69:$X$124,'1CF'!$A11) -> 0 | AJ11: =-SUMIFS('1BS'!AF$3:AF$68,'1BS'!$X$3:$X$68,'1CF'!$A11)+SUMIFS('1BS'!AF$69:AF$124,'1BS'!$X$69:$X$124,'1CF'!$A11) -> 0 | AK11: Loại lãi tiền gửi/thanh lý TSCĐ | AM11: leave
A12: 6 | B12: Interest expense | D12: =SUMIFS(CF!K:K,CF!$A:$A,'1CF'!$A$12) -> 42112 | E12: =SUMIFS(CF!L:L,CF!$A:$A,'1CF'!$A$12) -> 35245 | F12: =SUMIFS(CF!M:M,CF!$A:$A,'1CF'!$A$12) -> 37367 | G12: =SUMIFS(CF!N:N,CF!$A:$A,'1CF'!$A$12) -> 63681 | H12: =SUMIFS(CF!O:O,CF!$A:$A,'1CF'!$A$12) -> 48740 | I12: =SUMIFS(CF!P:P,CF!$A:$A,'1CF'!$A$12) -> 45517 | J12: =SUMIFS(CF!Q:Q,CF!$A:$A,'1CF'!$A$12) -> 50215 | K12: =SUMIFS(CF!R:R,CF!$A:$A,'1CF'!$A$12) -> 27450 | L12: =SUMIFS(CF!S:S,CF!$A:$A,'1CF'!$A$12) -> 34346 | M12: =V12+AE12 -> 33228.324 | N12: =W12+AF12 -> 34924.037 | O12: =X12+AG12 -> 37866.271 | P12: =Y12+AH12 -> 39228.538 | Q12: =Z12+AI12 -> 41647.58 | R12: =AA12+AJ12 -> 44356.65 | T12: ='FI&FE'!M13 -> 27449 | U12: ='FI&FE'!N13 -> 34346 | V12: ='FI&FE'!O13 -> 33228.324 | W12: ='FI&FE'!P13 -> 34924.037 | X12: ='FI&FE'!Q13 -> 37866.271 | Y12: ='FI&FE'!R13 -> 39228.538 | Z12: ='FI&FE'!S13 -> 41647.58 | AA12: ='FI&FE'!T13 -> 44356.65 | AC12: =-SUMIFS('1BS'!Y$3:Y$68,'1BS'!$X$3:$X$68,'1CF'!$A12)+SUMIFS('1BS'!Y$69:Y$124,'1BS'!$X$69:$X$124,'1CF'!$A12) -> 0 | AD12: =-SUMIFS('1BS'!Z$3:Z$68,'1BS'!$X$3:$X$68,'1CF'!$A12)+SUMIFS('1BS'!Z$69:Z$124,'1BS'!$X$69:$X$124,'1CF'!$A12) -> 0 | AE12: =-SUMIFS('1BS'!AA$3:AA$68,'1BS'!$X$3:$X$68,'1CF'!$A12)+SUMIFS('1BS'!AA$69:AA$124,'1BS'!$X$69:$X$124,'1CF'!$A12) -> 0 | AF12: =-SUMIFS('1BS'!AB$3:AB$68,'1BS'!$X$3:$X$68,'1CF'!$A12)+SUMIFS('1BS'!AB$69:AB$124,'1BS'!$X$69:$X$124,'1CF'!$A12) -> 0 | AG12: =-SUMIFS('1BS'!AC$3:AC$68,'1BS'!$X$3:$X$68,'1CF'!$A12)+SUMIFS('1BS'!AC$69:AC$124,'1BS'!$X$69:$X$124,'1CF'!$A12) -> 0 | AH12: =-SUMIFS('1BS'!AD$3:AD$68,'1BS'!$X$3:$X$68,'1CF'!$A12)+SUMIFS('1BS'!AD$69:AD$124,'1BS'!$X$69:$X$124,'1CF'!$A12) -> 0 | AI12: =-SUMIFS('1BS'!AE$3:AE$68,'1BS'!$X$3:$X$68,'1CF'!$A12)+SUMIFS('1BS'!AE$69:AE$124,'1BS'!$X$69:$X$124,'1CF'!$A12) -> 0 | AJ12: =-SUMIFS('1BS'!AF$3:AF$68,'1BS'!$X$3:$X$68,'1CF'!$A12)+SUMIFS('1BS'!AF$69:AF$124,'1BS'!$X$69:$X$124,'1CF'!$A12) -> 0 | AK12: Cộng lại int exp | AM12: leave
A13: 7 | B13: Other adjustments | D13: =SUMIFS(CF!K:K,CF!$A:$A,'1CF'!$A$13) -> 0 | E13: =SUMIFS(CF!L:L,CF!$A:$A,'1CF'!$A$13) -> 0 | F13: =SUMIFS(CF!M:M,CF!$A:$A,'1CF'!$A$13) -> 0 | G13: =SUMIFS(CF!N:N,CF!$A:$A,'1CF'!$A$13) -> 0 | H13: =SUMIFS(CF!O:O,CF!$A:$A,'1CF'!$A$13) -> 0 | I13: =SUMIFS(CF!P:P,CF!$A:$A,'1CF'!$A$13) -> 0 | J13: =SUMIFS(CF!Q:Q,CF!$A:$A,'1CF'!$A$13) -> 0 | K13: =SUMIFS(CF!R:R,CF!$A:$A,'1CF'!$A$13) -> 0 | L13: =SUMIFS(CF!S:S,CF!$A:$A,'1CF'!$A$13) -> 0 | M13: =SUMIFS(CF!T:T,CF!$A:$A,'1CF'!$A$13) -> 0 | N13: =SUMIFS(CF!U:U,CF!$A:$A,'1CF'!$A$13) -> 0 | O13: =SUMIFS(CF!V:V,CF!$A:$A,'1CF'!$A$13) -> 0 | P13: =SUMIFS(CF!W:W,CF!$A:$A,'1CF'!$A$13) -> 0 | Q13: =SUMIFS(CF!X:X,CF!$A:$A,'1CF'!$A$13) -> 0 | R13: =SUMIFS(CF!Y:Y,CF!$A:$A,'1CF'!$A$13) -> 0 | AC13: =-SUMIFS('1BS'!Y$3:Y$68,'1BS'!$X$3:$X$68,'1CF'!$A13)+SUMIFS('1BS'!Y$69:Y$124,'1BS'!$X$69:$X$124,'1CF'!$A13) -> 0 | AD13: =-SUMIFS('1BS'!Z$3:Z$68,'1BS'!$X$3:$X$68,'1CF'!$A13)+SUMIFS('1BS'!Z$69:Z$124,'1BS'!$X$69:$X$124,'1CF'!$A13) -> 0 | AE13: =-SUMIFS('1BS'!AA$3:AA$68,'1BS'!$X$3:$X$68,'1CF'!$A13)+SUMIFS('1BS'!AA$69:AA$124,'1BS'!$X$69:$X$124,'1CF'!$A13) -> 0 | AF13: =-SUMIFS('1BS'!AB$3:AB$68,'1BS'!$X$3:$X$68,'1CF'!$A13)+SUMIFS('1BS'!AB$69:AB$124,'1BS'!$X$69:$X$124,'1CF'!$A13) -> 0 | AG13: =-SUMIFS('1BS'!AC$3:AC$68,'1BS'!$X$3:$X$68,'1CF'!$A13)+SUMIFS('1BS'!AC$69:AC$124,'1BS'!$X$69:$X$124,'1CF'!$A13) -> 0 | AH13: =-SUMIFS('1BS'!AD$3:AD$68,'1BS'!$X$3:$X$68,'1CF'!$A13)+SUMIFS('1BS'!AD$69:AD$124,'1BS'!$X$69:$X$124,'1CF'!$A13) -> 0 | AI13: =-SUMIFS('1BS'!AE$3:AE$68,'1BS'!$X$3:$X$68,'1CF'!$A13)+SUMIFS('1BS'!AE$69:AE$124,'1BS'!$X$69:$X$124,'1CF'!$A13) -> 0 | AJ13: =-SUMIFS('1BS'!AF$3:AF$68,'1BS'!$X$3:$X$68,'1CF'!$A13)+SUMIFS('1BS'!AF$69:AF$124,'1BS'!$X$69:$X$124,'1CF'!$A13) -> 0 | AM13: leave
AM14: leave
A15: 8 | B15: Operating profit/(loss) before changes in working capital | D15: =SUMIFS(CF!K:K,CF!$A:$A,'1CF'!$A$15) -> 5905949 | E15: =SUMIFS(CF!L:L,CF!$A:$A,'1CF'!$A$15) -> 5347492 | F15: =SUMIFS(CF!M:M,CF!$A:$A,'1CF'!$A$15) -> 6489622 | G15: =SUMIFS(CF!N:N,CF!$A:$A,'1CF'!$A$15) -> 5537718 | H15: =SUMIFS(CF!O:O,CF!$A:$A,'1CF'!$A$15) -> 4056683 | I15: =SUMIFS(CF!P:P,CF!$A:$A,'1CF'!$A$15) -> 6059081 | J15: =SUMIFS(CF!Q:Q,CF!$A:$A,'1CF'!$A$15) -> 4376504 | K15: =SUMIFS(CF!R:R,CF!$A:$A,'1CF'!$A$15) -> 4980056 | L15: =SUMIFS(CF!S:S,CF!$A:$A,'1CF'!$A$15) -> 5185201 | M15: =SUM(M8:M13,M6) -> 5254731.6 | N15: =SUM(N8:N13,N6) -> 5646842.5 | O15: =SUM(O8:O13,O6) -> 6317146.4 | P15: =SUM(P8:P13,P6) -> 6360421.6 | Q15: =SUM(Q8:Q13,Q6) -> 6505154.8 | R15: =SUM(R8:R13,R6) -> 6201538.5 | AC15: =SUM(AC8:AC13,AC6) -> 6138713 | AD15: =SUM(AD8:AD13,AD6) -> 9463861 | AE15: =SUM(AE8:AE13,AE6) -> 6182086.5 | AF15: =SUM(AF8:AF13,AF6) -> 6525232 | AG15: =SUM(AG8:AG13,AG6) -> 7185874.6 | AH15: =SUM(AH8:AH13,AH6) -> 7225598.1 | AI15: =SUM(AI8:AI13,AI6) -> 7364767.5 | AJ15: =SUM(AJ8:AJ13,AJ6) -> 7081980.5 | AM15: leave
A16: 9 | B16: (Increase)/decrease in receivables | D16: =SUMIFS(CF!K:K,CF!$A:$A,'1CF'!$A$16) -> 187691 | E16: =SUMIFS(CF!L:L,CF!$A:$A,'1CF'!$A$16) -> 119831 | F16: =SUMIFS(CF!M:M,CF!$A:$A,'1CF'!$A$16) -> 95622 | G16: =SUMIFS(CF!N:N,CF!$A:$A,'1CF'!$A$16) -> 70186 | H16: =SUMIFS(CF!O:O,CF!$A:$A,'1CF'!$A$16) -> -52722 | I16: =SUMIFS(CF!P:P,CF!$A:$A,'1CF'!$A$16) -> -318889 | J16: =SUMIFS(CF!Q:Q,CF!$A:$A,'1CF'!$A$16) -> -39584 | K16: =SUMIFS(CF!R:R,CF!$A:$A,'1CF'!$A$16) -> 13722 | L16: =SUMIFS(CF!S:S,CF!$A:$A,'1CF'!$A$16) -> -92591 | M16: =V16+AE16 -> 100691.16 | N16: =W16+AF16 -> 117698.3 | O16: =X16+AG16 -> -143015.51 | P16: =Y16+AH16 -> -26304.982 | Q16: =Z16+AI16 -> -41929.736 | R16: =AA16+AJ16 -> -51425.983 | AC16: =-SUMIFS('1BS'!Y$3:Y$68,'1BS'!$X$3:$X$68,'1CF'!$A16)+SUMIFS('1BS'!Y$69:Y$124,'1BS'!$X$69:$X$124,'1CF'!$A16) -> -629075 | AD16: =-SUMIFS('1BS'!Z$3:Z$68,'1BS'!$X$3:$X$68,'1CF'!$A16)+SUMIFS('1BS'!Z$69:Z$124,'1BS'!$X$69:$X$124,'1CF'!$A16) -> 662768 | AE16: =-SUMIFS('1BS'!AA$3:AA$68,'1BS'!$X$3:$X$68,'1CF'!$A16)+SUMIFS('1BS'!AA$69:AA$124,'1BS'!$X$69:$X$124,'1CF'!$A16) -> 100691.16 | AF16: =-SUMIFS('1BS'!AB$3:AB$68,'1BS'!$X$3:$X$68,'1CF'!$A16)+SUMIFS('1BS'!AB$69:AB$124,'1BS'!$X$69:$X$124,'1CF'!$A16) -> 117698.3 | AG16: =-SUMIFS('1BS'!AC$3:AC$68,'1BS'!$X$3:$X$68,'1CF'!$A16)+SUMIFS('1BS'!AC$69:AC$124,'1BS'!$X$69:$X$124,'1CF'!$A16) -> -143015.51 | AH16: =-SUMIFS('1BS'!AD$3:AD$68,'1BS'!$X$3:$X$68,'1CF'!$A16)+SUMIFS('1BS'!AD$69:AD$124,'1BS'!$X$69:$X$124,'1CF'!$A16) -> -26304.982 | AI16: =-SUMIFS('1BS'!AE$3:AE$68,'1BS'!$X$3:$X$68,'1CF'!$A16)+SUMIFS('1BS'!AE$69:AE$124,'1BS'!$X$69:$X$124,'1CF'!$A16) -> -41929.736 | AJ16: =-SUMIFS('1BS'!AF$3:AF$68,'1BS'!$X$3:$X$68,'1CF'!$A16)+SUMIFS('1BS'!AF$69:AF$124,'1BS'!$X$69:$X$124,'1CF'!$A16) -> -51425.983 | AM16: leave
A17: 10 | B17: (Increase)/decrease in inventories | D17: =SUMIFS(CF!K:K,CF!$A:$A,'1CF'!$A$17) -> 50520 | E17: =SUMIFS(CF!L:L,CF!$A:$A,'1CF'!$A$17) -> 36215 | F17: =SUMIFS(CF!M:M,CF!$A:$A,'1CF'!$A$17) -> -109295 | G17: =SUMIFS(CF!N:N,CF!$A:$A,'1CF'!$A$17) -> 573633 | H17: =SUMIFS(CF!O:O,CF!$A:$A,'1CF'!$A$17) -> -223957 | I17: =SUMIFS(CF!P:P,CF!$A:$A,'1CF'!$A$17) -> -524913 | J17: =SUMIFS(CF!Q:Q,CF!$A:$A,'1CF'!$A$17) -> -135490 | K17: =SUMIFS(CF!R:R,CF!$A:$A,'1CF'!$A$17) -> 345460 | L17: =SUMIFS(CF!S:S,CF!$A:$A,'1CF'!$A$17) -> 214517 | M17: =V17+AE17 -> 91455.261 | N17: =W17+AF17 -> -15908.465 | O17: =X17+AG17 -> -183268.69 | P17: =Y17+AH17 -> -5798.6514 | Q17: =Z17+AI17 -> -90574.954 | R17: =AA17+AJ17 -> -73507.039 | AC17: =-SUMIFS('1BS'!Y$3:Y$68,'1BS'!$X$3:$X$68,'1CF'!$A17)+SUMIFS('1BS'!Y$69:Y$124,'1BS'!$X$69:$X$124,'1CF'!$A17) -> 350232 | AD17: =-SUMIFS('1BS'!Z$3:Z$68,'1BS'!$X$3:$X$68,'1CF'!$A17)+SUMIFS('1BS'!Z$69:Z$124,'1BS'!$X$69:$X$124,'1CF'!$A17) -> -66997 | AE17: =-SUMIFS('1BS'!AA$3:AA$68,'1BS'!$X$3:$X$68,'1CF'!$A17)+SUMIFS('1BS'!AA$69:AA$124,'1BS'!$X$69:$X$124,'1CF'!$A17) -> 91455.261 | AF17: =-SUMIFS('1BS'!AB$3:AB$68,'1BS'!$X$3:$X$68,'1CF'!$A17)+SUMIFS('1BS'!AB$69:AB$124,'1BS'!$X$69:$X$124,'1CF'!$A17) -> -15908.465 | AG17: =-SUMIFS('1BS'!AC$3:AC$68,'1BS'!$X$3:$X$68,'1CF'!$A17)+SUMIFS('1BS'!AC$69:AC$124,'1BS'!$X$69:$X$124,'1CF'!$A17) -> -183268.69 | AH17: =-SUMIFS('1BS'!AD$3:AD$68,'1BS'!$X$3:$X$68,'1CF'!$A17)+SUMIFS('1BS'!AD$69:AD$124,'1BS'!$X$69:$X$124,'1CF'!$A17) -> -5798.6514 | AI17: =-SUMIFS('1BS'!AE$3:AE$68,'1BS'!$X$3:$X$68,'1CF'!$A17)+SUMIFS('1BS'!AE$69:AE$124,'1BS'!$X$69:$X$124,'1CF'!$A17) -> -90574.954 | AJ17: =-SUMIFS('1BS'!AF$3:AF$68,'1BS'!$X$3:$X$68,'1CF'!$A17)+SUMIFS('1BS'!AF$69:AF$124,'1BS'!$X$69:$X$124,'1CF'!$A17) -> -73507.039 | AM17: leave
A18: 11 | B18: Increase/(decrease) in payables (other than interest, corporate income tax) | D18: =SUMIFS(CF!K:K,CF!$A:$A,'1CF'!$A$18) -> -329360 | E18: =SUMIFS(CF!L:L,CF!$A:$A,'1CF'!$A$18) -> 324264 | F18: =SUMIFS(CF!M:M,CF!$A:$A,'1CF'!$A$18) -> 11238 | G18: =SUMIFS(CF!N:N,CF!$A:$A,'1CF'!$A$18) -> -660694 | H18: =SUMIFS(CF!O:O,CF!$A:$A,'1CF'!$A$18) -> 658280 | I18: =SUMIFS(CF!P:P,CF!$A:$A,'1CF'!$A$18) -> 739397 | J18: =SUMIFS(CF!Q:Q,CF!$A:$A,'1CF'!$A$18) -> -787120 | K18: =SUMIFS(CF!R:R,CF!$A:$A,'1CF'!$A$18) -> 208911 | L18: =SUMIFS(CF!S:S,CF!$A:$A,'1CF'!$A$18) -> -133234 | M18: =V18+AE18 -> -846345.89 | N18: =W18+AF18 -> -187777.59 | O18: =X18+AG18 -> 516493.8 | P18: =Y18+AH18 -> 56054.437 | Q18: =Z18+AI18 -> 347527.65 | R18: =AA18+AJ18 -> 232546.02 | AC18: =-SUMIFS('1BS'!Y$3:Y$68,'1BS'!$X$3:$X$68,'1CF'!$A18)+SUMIFS('1BS'!Y$69:Y$124,'1BS'!$X$69:$X$124,'1CF'!$A18) -> 712095 | AD18: =-SUMIFS('1BS'!Z$3:Z$68,'1BS'!$X$3:$X$68,'1CF'!$A18)+SUMIFS('1BS'!Z$69:Z$124,'1BS'!$X$69:$X$124,'1CF'!$A18) -> 169026 | AE18: =-SUMIFS('1BS'!AA$3:AA$68,'1BS'!$X$3:$X$68,'1CF'!$A18)+SUMIFS('1BS'!AA$69:AA$124,'1BS'!$X$69:$X$124,'1CF'!$A18) -> -846345.89 | AF18: =-SUMIFS('1BS'!AB$3:AB$68,'1BS'!$X$3:$X$68,'1CF'!$A18)+SUMIFS('1BS'!AB$69:AB$124,'1BS'!$X$69:$X$124,'1CF'!$A18) -> -187777.59 | AG18: =-SUMIFS('1BS'!AC$3:AC$68,'1BS'!$X$3:$X$68,'1CF'!$A18)+SUMIFS('1BS'!AC$69:AC$124,'1BS'!$X$69:$X$124,'1CF'!$A18) -> 516493.8 | AH18: =-SUMIFS('1BS'!AD$3:AD$68,'1BS'!$X$3:$X$68,'1CF'!$A18)+SUMIFS('1BS'!AD$69:AD$124,'1BS'!$X$69:$X$124,'1CF'!$A18) -> 56054.437 | AI18: =-SUMIFS('1BS'!AE$3:AE$68,'1BS'!$X$3:$X$68,'1CF'!$A18)+SUMIFS('1BS'!AE$69:AE$124,'1BS'!$X$69:$X$124,'1CF'!$A18) -> 347527.65 | AJ18: =-SUMIFS('1BS'!AF$3:AF$68,'1BS'!$X$3:$X$68,'1CF'!$A18)+SUMIFS('1BS'!AF$69:AF$124,'1BS'!$X$69:$X$124,'1CF'!$A18) -> 232546.02 | AM18: leave
A19: 12 | B19: (Increase)/decrease in prepaid expenses | D19: =SUMIFS(CF!K:K,CF!$A:$A,'1CF'!$A$19) -> -17854 | E19: =SUMIFS(CF!L:L,CF!$A:$A,'1CF'!$A$19) -> 203653 | F19: =SUMIFS(CF!M:M,CF!$A:$A,'1CF'!$A$19) -> 218117 | G19: =SUMIFS(CF!N:N,CF!$A:$A,'1CF'!$A$19) -> -44422 | H19: =SUMIFS(CF!O:O,CF!$A:$A,'1CF'!$A$19) -> 145399 | I19: =SUMIFS(CF!P:P,CF!$A:$A,'1CF'!$A$19) -> -94057 | J19: =SUMIFS(CF!Q:Q,CF!$A:$A,'1CF'!$A$19) -> -146695 | K19: =SUMIFS(CF!R:R,CF!$A:$A,'1CF'!$A$19) -> 123176 | L19: =SUMIFS(CF!S:S,CF!$A:$A,'1CF'!$A$19) -> -26981 | M19: =V19+AE19 -> -875.45063 | N19: =W19+AF19 -> 533.1164 | O19: =X19+AG19 -> -11140.384 | P19: =Y19+AH19 -> -1975.2509 | Q19: =Z19+AI19 -> -5654.4197 | R19: =AA19+AJ19 -> -4882.4192 | AC19: =-SUMIFS('1BS'!Y$3:Y$68,'1BS'!$X$3:$X$68,'1CF'!$A19)+SUMIFS('1BS'!Y$69:Y$124,'1BS'!$X$69:$X$124,'1CF'!$A19) -> 26572 | AD19: =-SUMIFS('1BS'!Z$3:Z$68,'1BS'!$X$3:$X$68,'1CF'!$A19)+SUMIFS('1BS'!Z$69:Z$124,'1BS'!$X$69:$X$124,'1CF'!$A19) -> 5839 | AE19: =-SUMIFS('1BS'!AA$3:AA$68,'1BS'!$X$3:$X$68,'1CF'!$A19)+SUMIFS('1BS'!AA$69:AA$124,'1BS'!$X$69:$X$124,'1CF'!$A19) -> -875.45063 | AF19: =-SUMIFS('1BS'!AB$3:AB$68,'1BS'!$X$3:$X$68,'1CF'!$A19)+SUMIFS('1BS'!AB$69:AB$124,'1BS'!$X$69:$X$124,'1CF'!$A19) -> 533.1164 | AG19: =-SUMIFS('1BS'!AC$3:AC$68,'1BS'!$X$3:$X$68,'1CF'!$A19)+SUMIFS('1BS'!AC$69:AC$124,'1BS'!$X$69:$X$124,'1CF'!$A19) -> -11140.384 | AH19: =-SUMIFS('1BS'!AD$3:AD$68,'1BS'!$X$3:$X$68,'1CF'!$A19)+SUMIFS('1BS'!AD$69:AD$124,'1BS'!$X$69:$X$124,'1CF'!$A19) -> -1975.2509 | AI19: =-SUMIFS('1BS'!AE$3:AE$68,'1BS'!$X$3:$X$68,'1CF'!$A19)+SUMIFS('1BS'!AE$69:AE$124,'1BS'!$X$69:$X$124,'1CF'!$A19) -> -5654.4197 | AJ19: =-SUMIFS('1BS'!AF$3:AF$68,'1BS'!$X$3:$X$68,'1CF'!$A19)+SUMIFS('1BS'!AF$69:AF$124,'1BS'!$X$69:$X$124,'1CF'!$A19) -> -4882.4192 | AM19: leave
A20: 13 | B20: (Increase)/decrease in held-for-trading securities | D20: =SUMIFS(CF!K:K,CF!$A:$A,'1CF'!$A$20) -> 0 | E20: =SUMIFS(CF!L:L,CF!$A:$A,'1CF'!$A$20) -> 0 | F20: =SUMIFS(CF!M:M,CF!$A:$A,'1CF'!$A$20) -> 0 | G20: =SUMIFS(CF!N:N,CF!$A:$A,'1CF'!$A$20) -> 0 | H20: =SUMIFS(CF!O:O,CF!$A:$A,'1CF'!$A$20) -> 0 | I20: =SUMIFS(CF!P:P,CF!$A:$A,'1CF'!$A$20) -> 0 | J20: =SUMIFS(CF!Q:Q,CF!$A:$A,'1CF'!$A$20) -> 0 | K20: =SUMIFS(CF!R:R,CF!$A:$A,'1CF'!$A$20) -> 0 | L20: =SUMIFS(CF!S:S,CF!$A:$A,'1CF'!$A$20) -> 0 | M20: =V20+AE20 -> 0 | N20: =W20+AF20 -> 0 | O20: =X20+AG20 -> 0 | P20: =Y20+AH20 -> 0 | Q20: =Z20+AI20 -> 0 | R20: =AA20+AJ20 -> 0 | AC20: =-SUMIFS('1BS'!Y$3:Y$68,'1BS'!$X$3:$X$68,'1CF'!$A20)+SUMIFS('1BS'!Y$69:Y$124,'1BS'!$X$69:$X$124,'1CF'!$A20) -> 0 | AD20: =-SUMIFS('1BS'!Z$3:Z$68,'1BS'!$X$3:$X$68,'1CF'!$A20)+SUMIFS('1BS'!Z$69:Z$124,'1BS'!$X$69:$X$124,'1CF'!$A20) -> 0 | AE20: =-SUMIFS('1BS'!AA$3:AA$68,'1BS'!$X$3:$X$68,'1CF'!$A20)+SUMIFS('1BS'!AA$69:AA$124,'1BS'!$X$69:$X$124,'1CF'!$A20) -> 0 | AF20: =-SUMIFS('1BS'!AB$3:AB$68,'1BS'!$X$3:$X$68,'1CF'!$A20)+SUMIFS('1BS'!AB$69:AB$124,'1BS'!$X$69:$X$124,'1CF'!$A20) -> 0 | AG20: =-SUMIFS('1BS'!AC$3:AC$68,'1BS'!$X$3:$X$68,'1CF'!$A20)+SUMIFS('1BS'!AC$69:AC$124,'1BS'!$X$69:$X$124,'1CF'!$A20) -> 0 | AH20: =-SUMIFS('1BS'!AD$3:AD$68,'1BS'!$X$3:$X$68,'1CF'!$A20)+SUMIFS('1BS'!AD$69:AD$124,'1BS'!$X$69:$X$124,'1CF'!$A20) -> 0 | AI20: =-SUMIFS('1BS'!AE$3:AE$68,'1BS'!$X$3:$X$68,'1CF'!$A20)+SUMIFS('1BS'!AE$69:AE$124,'1BS'!$X$69:$X$124,'1CF'!$A20) -> 0 | AJ20: =-SUMIFS('1BS'!AF$3:AF$68,'1BS'!$X$3:$X$68,'1CF'!$A20)+SUMIFS('1BS'!AF$69:AF$124,'1BS'!$X$69:$X$124,'1CF'!$A20) -> 0 | AM20: hide
A21: 14 | B21: Interest paid | D21: =SUMIFS(CF!K:K,CF!$A:$A,'1CF'!$A$21) -> -44424 | E21: =SUMIFS(CF!L:L,CF!$A:$A,'1CF'!$A$21) -> -35957 | F21: =SUMIFS(CF!M:M,CF!$A:$A,'1CF'!$A$21) -> -36836 | G21: =SUMIFS(CF!N:N,CF!$A:$A,'1CF'!$A$21) -> -72030 | H21: =SUMIFS(CF!O:O,CF!$A:$A,'1CF'!$A$21) -> -35347 | I21: =SUMIFS(CF!P:P,CF!$A:$A,'1CF'!$A$21) -> -48765 | J21: =SUMIFS(CF!Q:Q,CF!$A:$A,'1CF'!$A$21) -> -50352 | K21: =SUMIFS(CF!R:R,CF!$A:$A,'1CF'!$A$21) -> -27623 | L21: =SUMIFS(CF!S:S,CF!$A:$A,'1CF'!$A$21) -> -35216 | M21: =V21+AE21 -> -33228.324 | N21: =W21+AF21 -> -34924.037 | O21: =X21+AG21 -> -37866.271 | P21: =Y21+AH21 -> -39228.538 | Q21: =Z21+AI21 -> -41647.58 | R21: =AA21+AJ21 -> -44356.65 | T21: =-T12 -> -27449 | U21: =-U12 -> -34346 | V21: =-V12 -> -33228.324 | W21: =-W12 -> -34924.037 | X21: =-X12 -> -37866.271 | Y21: =-Y12 -> -39228.538 | Z21: =-Z12 -> -41647.58 | AA21: =-AA12 -> -44356.65 | AC21: =-SUMIFS('1BS'!Y$3:Y$68,'1BS'!$X$3:$X$68,'1CF'!$A21)+SUMIFS('1BS'!Y$69:Y$124,'1BS'!$X$69:$X$124,'1CF'!$A21) -> 0 | AD21: =-SUMIFS('1BS'!Z$3:Z$68,'1BS'!$X$3:$X$68,'1CF'!$A21)+SUMIFS('1BS'!Z$69:Z$124,'1BS'!$X$69:$X$124,'1CF'!$A21) -> 0 | AE21: =-SUMIFS('1BS'!AA$3:AA$68,'1BS'!$X$3:$X$68,'1CF'!$A21)+SUMIFS('1BS'!AA$69:AA$124,'1BS'!$X$69:$X$124,'1CF'!$A21) -> 0 | AF21: =-SUMIFS('1BS'!AB$3:AB$68,'1BS'!$X$3:$X$68,'1CF'!$A21)+SUMIFS('1BS'!AB$69:AB$124,'1BS'!$X$69:$X$124,'1CF'!$A21) -> 0 | AG21: =-SUMIFS('1BS'!AC$3:AC$68,'1BS'!$X$3:$X$68,'1CF'!$A21)+SUMIFS('1BS'!AC$69:AC$124,'1BS'!$X$69:$X$124,'1CF'!$A21) -> 0 | AH21: =-SUMIFS('1BS'!AD$3:AD$68,'1BS'!$X$3:$X$68,'1CF'!$A21)+SUMIFS('1BS'!AD$69:AD$124,'1BS'!$X$69:$X$124,'1CF'!$A21) -> 0 | AI21: =-SUMIFS('1BS'!AE$3:AE$68,'1BS'!$X$3:$X$68,'1CF'!$A21)+SUMIFS('1BS'!AE$69:AE$124,'1BS'!$X$69:$X$124,'1CF'!$A21) -> 0 | AJ21: =-SUMIFS('1BS'!AF$3:AF$68,'1BS'!$X$3:$X$68,'1CF'!$A21)+SUMIFS('1BS'!AF$69:AF$124,'1BS'!$X$69:$X$124,'1CF'!$A21) -> 0 | AM21: leave
A22: 15 | B22: Corporate income tax paid | D22: =SUMIFS(CF!K:K,CF!$A:$A,'1CF'!$A$22) -> -294736 | E22: =SUMIFS(CF!L:L,CF!$A:$A,'1CF'!$A$22) -> -1140987 | F22: =SUMIFS(CF!M:M,CF!$A:$A,'1CF'!$A$22) -> -1398560 | G22: =SUMIFS(CF!N:N,CF!$A:$A,'1CF'!$A$22) -> -1038634 | H22: =SUMIFS(CF!O:O,CF!$A:$A,'1CF'!$A$22) -> -919005 | I22: =SUMIFS(CF!P:P,CF!$A:$A,'1CF'!$A$22) -> -1329727 | J22: =SUMIFS(CF!Q:Q,CF!$A:$A,'1CF'!$A$22) -> -1099769 | K22: =SUMIFS(CF!R:R,CF!$A:$A,'1CF'!$A$22) -> -1156742 | L22: =SUMIFS(CF!S:S,CF!$A:$A,'1CF'!$A$22) -> -1068124 | M22: ='1IS'!P20 -> -1075512.3 | N22: ='1IS'!Q20 -> -1092556.6 | O22: ='1IS'!R20 -> -1155869.3 | P22: ='1IS'!S20 -> -1159192.3 | Q22: ='1IS'!T20 -> -1187590.6 | R22: ='1IS'!U20 -> -1206423.1 | AC22: =-SUMIFS('1BS'!Y$3:Y$68,'1BS'!$X$3:$X$68,'1CF'!$A22)+SUMIFS('1BS'!Y$69:Y$124,'1BS'!$X$69:$X$124,'1CF'!$A22) -> 0 | AD22: =-SUMIFS('1BS'!Z$3:Z$68,'1BS'!$X$3:$X$68,'1CF'!$A22)+SUMIFS('1BS'!Z$69:Z$124,'1BS'!$X$69:$X$124,'1CF'!$A22) -> 0 | AE22: =-SUMIFS('1BS'!AA$3:AA$68,'1BS'!$X$3:$X$68,'1CF'!$A22)+SUMIFS('1BS'!AA$69:AA$124,'1BS'!$X$69:$X$124,'1CF'!$A22) -> 0 | AF22: =-SUMIFS('1BS'!AB$3:AB$68,'1BS'!$X$3:$X$68,'1CF'!$A22)+SUMIFS('1BS'!AB$69:AB$124,'1BS'!$X$69:$X$124,'1CF'!$A22) -> 0 | AG22: =-SUMIFS('1BS'!AC$3:AC$68,'1BS'!$X$3:$X$68,'1CF'!$A22)+SUMIFS('1BS'!AC$69:AC$124,'1BS'!$X$69:$X$124,'1CF'!$A22) -> 0 | AH22: =-SUMIFS('1BS'!AD$3:AD$68,'1BS'!$X$3:$X$68,'1CF'!$A22)+SUMIFS('1BS'!AD$69:AD$124,'1BS'!$X$69:$X$124,'1CF'!$A22) -> 0 | AI22: =-SUMIFS('1BS'!AE$3:AE$68,'1BS'!$X$3:$X$68,'1CF'!$A22)+SUMIFS('1BS'!AE$69:AE$124,'1BS'!$X$69:$X$124,'1CF'!$A22) -> 0 | AJ22: =-SUMIFS('1BS'!AF$3:AF$68,'1BS'!$X$3:$X$68,'1CF'!$A22)+SUMIFS('1BS'!AF$69:AF$124,'1BS'!$X$69:$X$124,'1CF'!$A22) -> 0 | AK22: x | AM22: leave
A23: 16 | B23: Other cash inflows from operating activities | D23: =SUMIFS(CF!K:K,CF!$A:$A,'1CF'!$A$23) -> 0 | E23: =SUMIFS(CF!L:L,CF!$A:$A,'1CF'!$A$23) -> 0 | F23: =SUMIFS(CF!M:M,CF!$A:$A,'1CF'!$A$23) -> 0 | G23: =SUMIFS(CF!N:N,CF!$A:$A,'1CF'!$A$23) -> 0 | H23: =SUMIFS(CF!O:O,CF!$A:$A,'1CF'!$A$23) -> 0 | I23: =SUMIFS(CF!P:P,CF!$A:$A,'1CF'!$A$23) -> 0 | J23: =SUMIFS(CF!Q:Q,CF!$A:$A,'1CF'!$A$23) -> 0 | K23: =SUMIFS(CF!R:R,CF!$A:$A,'1CF'!$A$23) -> 0 | L23: =SUMIFS(CF!S:S,CF!$A:$A,'1CF'!$A$23) -> 0 | M23: =Equity!P106 -> -118547.56 | N23: =Equity!Q106 -> -122932.78 | O23: =Equity!R106 -> -130026.8 | P23: =Equity!S106 -> -135765.75 | Q23: =Equity!T106 -> -142004.47 | R23: =Equity!U106 -> -148375.01 | AC23: =-SUMIFS('1BS'!Y$3:Y$68,'1BS'!$X$3:$X$68,'1CF'!$A23)+SUMIFS('1BS'!Y$69:Y$124,'1BS'!$X$69:$X$124,'1CF'!$A23) -> 0 | AD23: =-SUMIFS('1BS'!Z$3:Z$68,'1BS'!$X$3:$X$68,'1CF'!$A23)+SUMIFS('1BS'!Z$69:Z$124,'1BS'!$X$69:$X$124,'1CF'!$A23) -> 0 | AE23: =-SUMIFS('1BS'!AA$3:AA$68,'1BS'!$X$3:$X$68,'1CF'!$A23)+SUMIFS('1BS'!AA$69:AA$124,'1BS'!$X$69:$X$124,'1CF'!$A23) -> 0 | AF23: =-SUMIFS('1BS'!AB$3:AB$68,'1BS'!$X$3:$X$68,'1CF'!$A23)+SUMIFS('1BS'!AB$69:AB$124,'1BS'!$X$69:$X$124,'1CF'!$A23) -> 0 | AG23: =-SUMIFS('1BS'!AC$3:AC$68,'1BS'!$X$3:$X$68,'1CF'!$A23)+SUMIFS('1BS'!AC$69:AC$124,'1BS'!$X$69:$X$124,'1CF'!$A23) -> 0 | AH23: =-SUMIFS('1BS'!AD$3:AD$68,'1BS'!$X$3:$X$68,'1CF'!$A23)+SUMIFS('1BS'!AD$69:AD$124,'1BS'!$X$69:$X$124,'1CF'!$A23) -> 0 | AI23: =-SUMIFS('1BS'!AE$3:AE$68,'1BS'!$X$3:$X$68,'1CF'!$A23)+SUMIFS('1BS'!AE$69:AE$124,'1BS'!$X$69:$X$124,'1CF'!$A23) -> 0 | AJ23: =-SUMIFS('1BS'!AF$3:AF$68,'1BS'!$X$3:$X$68,'1CF'!$A23)+SUMIFS('1BS'!AF$69:AF$124,'1BS'!$X$69:$X$124,'1CF'!$A23) -> 0 | AM23: leave
A24: 17 | B24: Other cash outflows from operating activities | D24: =SUMIFS(CF!K:K,CF!$A:$A,'1CF'!$A$24) -> -389966 | E24: =SUMIFS(CF!L:L,CF!$A:$A,'1CF'!$A$24) -> -339725 | F24: =SUMIFS(CF!M:M,CF!$A:$A,'1CF'!$A$24) -> -264897 | G24: =SUMIFS(CF!N:N,CF!$A:$A,'1CF'!$A$24) -> -237146 | H24: =SUMIFS(CF!O:O,CF!$A:$A,'1CF'!$A$24) -> -111480 | I24: =SUMIFS(CF!P:P,CF!$A:$A,'1CF'!$A$24) -> -103608 | J24: =SUMIFS(CF!Q:Q,CF!$A:$A,'1CF'!$A$24) -> -177429 | K24: =SUMIFS(CF!R:R,CF!$A:$A,'1CF'!$A$24) -> -124451 | L24: =SUMIFS(CF!S:S,CF!$A:$A,'1CF'!$A$24) -> -139496 | M24: -2 | N24: 0 | O24: 0 | P24: -1 | Q24: 0 | R24: 0 | AC24: =-SUMIFS('1BS'!Y$3:Y$68,'1BS'!$X$3:$X$68,'1CF'!$A24)+SUMIFS('1BS'!Y$69:Y$124,'1BS'!$X$69:$X$124,'1CF'!$A24) -> 0 | AD24: =-SUMIFS('1BS'!Z$3:Z$68,'1BS'!$X$3:$X$68,'1CF'!$A24)+SUMIFS('1BS'!Z$69:Z$124,'1BS'!$X$69:$X$124,'1CF'!$A24) -> 0 | AE24: =-SUMIFS('1BS'!AA$3:AA$68,'1BS'!$X$3:$X$68,'1CF'!$A24)+SUMIFS('1BS'!AA$69:AA$124,'1BS'!$X$69:$X$124,'1CF'!$A24) -> 0 | AF24: =-SUMIFS('1BS'!AB$3:AB$68,'1BS'!$X$3:$X$68,'1CF'!$A24)+SUMIFS('1BS'!AB$69:AB$124,'1BS'!$X$69:$X$124,'1CF'!$A24) -> 0 | AG24: =-SUMIFS('1BS'!AC$3:AC$68,'1BS'!$X$3:$X$68,'1CF'!$A24)+SUMIFS('1BS'!AC$69:AC$124,'1BS'!$X$69:$X$124,'1CF'!$A24) -> 0 | AH24: =-SUMIFS('1BS'!AD$3:AD$68,'1BS'!$X$3:$X$68,'1CF'!$A24)+SUMIFS('1BS'!AD$69:AD$124,'1BS'!$X$69:$X$124,'1CF'!$A24) -> 0 | AI24: =-SUMIFS('1BS'!AE$3:AE$68,'1BS'!$X$3:$X$68,'1CF'!$A24)+SUMIFS('1BS'!AE$69:AE$124,'1BS'!$X$69:$X$124,'1CF'!$A24) -> 0 | AJ24: =-SUMIFS('1BS'!AF$3:AF$68,'1BS'!$X$3:$X$68,'1CF'!$A24)+SUMIFS('1BS'!AF$69:AF$124,'1BS'!$X$69:$X$124,'1CF'!$A24) -> 0 | AM24: leave
AM25: leave
A26: 20 | B26: Net cash flows from/(used in) operating activities | D26: =CF!K25 -> 5067819 | E26: =CF!L25 -> 4514786 | F26: =CF!M25 -> 5005013 | G26: =CF!N25 -> 4128612 | H26: =CF!O25 -> 3517852 | I26: =CF!P25 -> 4378517 | J26: =CF!Q25 -> 1940064 | K26: =CF!R25 -> 4362510 | L26: =CF!S25 -> 3904076 | M26: =SUM(M15:M24) -> 3372366.5 | N26: =SUM(N15:N24) -> 4310974.5 | O26: =SUM(O15:O24) -> 5172453.3 | P26: =SUM(P15:P24) -> 5048209.6 | Q26: =SUM(Q15:Q24) -> 5343280.7 | R26: =SUM(R15:R24) -> 4905114.4 | AC26: =SUM(AC15:AC24) -> 6598537 | AD26: =SUM(AD15:AD24) -> 10234497 | AE26: =SUM(AE15:AE24) -> 5527011.5 | AF26: =SUM(AF15:AF24) -> 6439777.3 | AG26: =SUM(AG15:AG24) -> 7364943.8 | AH26: =SUM(AH15:AH24) -> 7247573.6 | AI26: =SUM(AI15:AI24) -> 7574136 | AJ26: =SUM(AJ15:AJ24) -> 7184711.1 | AM26: leave
AM27: leave
B28: II. CASH FLOWS FROM INVESTING ACTIVITIES | AM28: leave
A29: 21 | B29: Purchase, construction of fixed assets and other long-term assets | D29: =SUMIFS(CF!K:K,CF!$A:$A,'1CF'!$A$29) -> -151158 | E29: =SUMIFS(CF!L:L,CF!$A:$A,'1CF'!$A$29) -> -290439 | F29: =SUMIFS(CF!M:M,CF!$A:$A,'1CF'!$A$29) -> -268998 | G29: =SUMIFS(CF!N:N,CF!$A:$A,'1CF'!$A$29) -> -367442 | H29: =SUMIFS(CF!O:O,CF!$A:$A,'1CF'!$A$29) -> -329541 | I29: =SUMIFS(CF!P:P,CF!$A:$A,'1CF'!$A$29) -> -533164 | J29: =SUMIFS(CF!Q:Q,CF!$A:$A,'1CF'!$A$29) -> -283735 | K29: =SUMIFS(CF!R:R,CF!$A:$A,'1CF'!$A$29) -> -296018 | L29: =SUMIFS(CF!S:S,CF!$A:$A,'1CF'!$A$29) -> -241544 | M29: =V29+AE29 -> 49759.081 | N29: =W29+AF29 -> -12731.453 | O29: =X29+AG29 -> -72097.476 | P29: =Y29+AH29 -> -57898.51 | Q29: =Z29+AI29 -> -67436.359 | R29: =AA29+AJ29 -> -66420.303 | AC29: =-SUMIFS('1BS'!Y$3:Y$68,'1BS'!$X$3:$X$68,'1CF'!$A29)+SUMIFS('1BS'!Y$69:Y$124,'1BS'!$X$69:$X$124,'1CF'!$A29) -> -1285986 | AD29: =-SUMIFS('1BS'!Z$3:Z$68,'1BS'!$X$3:$X$68,'1CF'!$A29)+SUMIFS('1BS'!Z$69:Z$124,'1BS'!$X$69:$X$124,'1CF'!$A29) -> -5343714 | AE29: =-SUMIFS('1BS'!AA$3:AA$68,'1BS'!$X$3:$X$68,'1CF'!$A29)+SUMIFS('1BS'!AA$69:AA$124,'1BS'!$X$69:$X$124,'1CF'!$A29) -> 49759.081 | AF29: =-SUMIFS('1BS'!AB$3:AB$68,'1BS'!$X$3:$X$68,'1CF'!$A29)+SUMIFS('1BS'!AB$69:AB$124,'1BS'!$X$69:$X$124,'1CF'!$A29) -> -12731.453 | AG29: =-SUMIFS('1BS'!AC$3:AC$68,'1BS'!$X$3:$X$68,'1CF'!$A29)+SUMIFS('1BS'!AC$69:AC$124,'1BS'!$X$69:$X$124,'1CF'!$A29) -> -72097.476 | AH29: =-SUMIFS('1BS'!AD$3:AD$68,'1BS'!$X$3:$X$68,'1CF'!$A29)+SUMIFS('1BS'!AD$69:AD$124,'1BS'!$X$69:$X$124,'1CF'!$A29) -> -57898.51 | AI29: =-SUMIFS('1BS'!AE$3:AE$68,'1BS'!$X$3:$X$68,'1CF'!$A29)+SUMIFS('1BS'!AE$69:AE$124,'1BS'!$X$69:$X$124,'1CF'!$A29) -> -67436.359 | AJ29: =-SUMIFS('1BS'!AF$3:AF$68,'1BS'!$X$3:$X$68,'1CF'!$A29)+SUMIFS('1BS'!AF$69:AF$124,'1BS'!$X$69:$X$124,'1CF'!$A29) -> -66420.303 | AM29: leave
A30: 22 | B30: Proceeds from disposals of fixed assets and other long-term assets | D30: =SUMIFS(CF!K:K,CF!$A:$A,'1CF'!$A$30) -> 14863 | E30: =SUMIFS(CF!L:L,CF!$A:$A,'1CF'!$A$30) -> 2009 | F30: =SUMIFS(CF!M:M,CF!$A:$A,'1CF'!$A$30) -> 4839 | G30: =SUMIFS(CF!N:N,CF!$A:$A,'1CF'!$A$30) -> 1441 | H30: =SUMIFS(CF!O:O,CF!$A:$A,'1CF'!$A$30) -> 3485 | I30: =SUMIFS(CF!P:P,CF!$A:$A,'1CF'!$A$30) -> 4266 | J30: =SUMIFS(CF!Q:Q,CF!$A:$A,'1CF'!$A$30) -> 2485 | K30: =SUMIFS(CF!R:R,CF!$A:$A,'1CF'!$A$30) -> 3525 | L30: =SUMIFS(CF!S:S,CF!$A:$A,'1CF'!$A$30) -> 1300 | M30: =V30+AE30 -> 0 | N30: =W30+AF30 -> 0 | O30: =X30+AG30 -> 0 | P30: =Y30+AH30 -> 0 | Q30: =Z30+AI30 -> 0 | R30: =AA30+AJ30 -> 0 | AC30: =-SUMIFS('1BS'!Y$3:Y$68,'1BS'!$X$3:$X$68,'1CF'!$A30)+SUMIFS('1BS'!Y$69:Y$124,'1BS'!$X$69:$X$124,'1CF'!$A30) -> 0 | AD30: =-SUMIFS('1BS'!Z$3:Z$68,'1BS'!$X$3:$X$68,'1CF'!$A30)+SUMIFS('1BS'!Z$69:Z$124,'1BS'!$X$69:$X$124,'1CF'!$A30) -> 0 | AE30: =-SUMIFS('1BS'!AA$3:AA$68,'1BS'!$X$3:$X$68,'1CF'!$A30)+SUMIFS('1BS'!AA$69:AA$124,'1BS'!$X$69:$X$124,'1CF'!$A30) -> 0 | AF30: =-SUMIFS('1BS'!AB$3:AB$68,'1BS'!$X$3:$X$68,'1CF'!$A30)+SUMIFS('1BS'!AB$69:AB$124,'1BS'!$X$69:$X$124,'1CF'!$A30) -> 0 | AG30: =-SUMIFS('1BS'!AC$3:AC$68,'1BS'!$X$3:$X$68,'1CF'!$A30)+SUMIFS('1BS'!AC$69:AC$124,'1BS'!$X$69:$X$124,'1CF'!$A30) -> 0 | AH30: =-SUMIFS('1BS'!AD$3:AD$68,'1BS'!$X$3:$X$68,'1CF'!$A30)+SUMIFS('1BS'!AD$69:AD$124,'1BS'!$X$69:$X$124,'1CF'!$A30) -> 0 | AI30: =-SUMIFS('1BS'!AE$3:AE$68,'1BS'!$X$3:$X$68,'1CF'!$A30)+SUMIFS('1BS'!AE$69:AE$124,'1BS'!$X$69:$X$124,'1CF'!$A30) -> 0 | AJ30: =-SUMIFS('1BS'!AF$3:AF$68,'1BS'!$X$3:$X$68,'1CF'!$A30)+SUMIFS('1BS'!AF$69:AF$124,'1BS'!$X$69:$X$124,'1CF'!$A30) -> 0 | AM30: leave
A31: 23 | B31: Loans to other entities and payments for purchase of debt instruments of other entities | D31: =SUMIFS(CF!K:K,CF!$A:$A,'1CF'!$A$31) -> -7278047 | E31: =SUMIFS(CF!L:L,CF!$A:$A,'1CF'!$A$31) -> -10860587 | F31: =SUMIFS(CF!M:M,CF!$A:$A,'1CF'!$A$31) -> -14261677 | G31: =SUMIFS(CF!N:N,CF!$A:$A,'1CF'!$A$31) -> -16247323 | H31: =SUMIFS(CF!O:O,CF!$A:$A,'1CF'!$A$31) -> -18159840 | I31: =SUMIFS(CF!P:P,CF!$A:$A,'1CF'!$A$31) -> -22641270 | J31: =SUMIFS(CF!Q:Q,CF!$A:$A,'1CF'!$A$31) -> -17562408 | K31: =SUMIFS(CF!R:R,CF!$A:$A,'1CF'!$A$31) -> -20386135 | L31: =SUMIFS(CF!S:S,CF!$A:$A,'1CF'!$A$31) -> -16845775 | M31: =V31+AE31 -> 146720.03 | N31: =W31+AF31 -> 730207.4 | O31: =X31+AG31 -> 223674.78 | P31: =Y31+AH31 -> -45966.644 | Q31: =Z31+AI31 -> 61705.126 | R31: =AA31+AJ31 -> -344110.95 | AC31: =-SUMIFS('1BS'!Y$3:Y$68,'1BS'!$X$3:$X$68,'1CF'!$A31)+SUMIFS('1BS'!Y$69:Y$124,'1BS'!$X$69:$X$124,'1CF'!$A31) -> 1174813 | AD31: =-SUMIFS('1BS'!Z$3:Z$68,'1BS'!$X$3:$X$68,'1CF'!$A31)+SUMIFS('1BS'!Z$69:Z$124,'1BS'!$X$69:$X$124,'1CF'!$A31) -> 1580750 | AE31: =-SUMIFS('1BS'!AA$3:AA$68,'1BS'!$X$3:$X$68,'1CF'!$A31)+SUMIFS('1BS'!AA$69:AA$124,'1BS'!$X$69:$X$124,'1CF'!$A31) -> 146720.03 | AF31: =-SUMIFS('1BS'!AB$3:AB$68,'1BS'!$X$3:$X$68,'1CF'!$A31)+SUMIFS('1BS'!AB$69:AB$124,'1BS'!$X$69:$X$124,'1CF'!$A31) -> 730207.4 | AG31: =-SUMIFS('1BS'!AC$3:AC$68,'1BS'!$X$3:$X$68,'1CF'!$A31)+SUMIFS('1BS'!AC$69:AC$124,'1BS'!$X$69:$X$124,'1CF'!$A31) -> 223674.78 | AH31: =-SUMIFS('1BS'!AD$3:AD$68,'1BS'!$X$3:$X$68,'1CF'!$A31)+SUMIFS('1BS'!AD$69:AD$124,'1BS'!$X$69:$X$124,'1CF'!$A31) -> -45966.644 | AI31: =-SUMIFS('1BS'!AE$3:AE$68,'1BS'!$X$3:$X$68,'1CF'!$A31)+SUMIFS('1BS'!AE$69:AE$124,'1BS'!$X$69:$X$124,'1CF'!$A31) -> 61705.126 | AJ31: =-SUMIFS('1BS'!AF$3:AF$68,'1BS'!$X$3:$X$68,'1CF'!$A31)+SUMIFS('1BS'!AF$69:AF$124,'1BS'!$X$69:$X$124,'1CF'!$A31) -> -344110.95 | AM31: leave
A32: 24 | B32: Collections from borrowers and proceeds from sale of debt instruments of other entities | D32: =SUMIFS(CF!K:K,CF!$A:$A,'1CF'!$A$32) -> 3893567 | E32: =SUMIFS(CF!L:L,CF!$A:$A,'1CF'!$A$32) -> 9875200 | F32: =SUMIFS(CF!M:M,CF!$A:$A,'1CF'!$A$32) -> 9379639 | G32: =SUMIFS(CF!N:N,CF!$A:$A,'1CF'!$A$32) -> 14066130 | H32: =SUMIFS(CF!O:O,CF!$A:$A,'1CF'!$A$32) -> 15706420 | I32: =SUMIFS(CF!P:P,CF!$A:$A,'1CF'!$A$32) -> 20288539 | J32: =SUMIFS(CF!Q:Q,CF!$A:$A,'1CF'!$A$32) -> 19195705 | K32: =SUMIFS(CF!R:R,CF!$A:$A,'1CF'!$A$32) -> 20264668 | L32: =SUMIFS(CF!S:S,CF!$A:$A,'1CF'!$A$32) -> 17920926 | N32: =W32+AF32 -> 0 | O32: =X32+AG32 -> 0 | P32: =Y32+AH32 -> 0 | Q32: =Z32+AI32 -> 0 | R32: =AA32+AJ32 -> 0 | AC32: =-SUMIFS('1BS'!Y$3:Y$68,'1BS'!$X$3:$X$68,'1CF'!$A32)+SUMIFS('1BS'!Y$69:Y$124,'1BS'!$X$69:$X$124,'1CF'!$A32) -> 0 | AD32: =-SUMIFS('1BS'!Z$3:Z$68,'1BS'!$X$3:$X$68,'1CF'!$A32)+SUMIFS('1BS'!Z$69:Z$124,'1BS'!$X$69:$X$124,'1CF'!$A32) -> 0 | AE32: =-SUMIFS('1BS'!AA$3:AA$68,'1BS'!$X$3:$X$68,'1CF'!$A32)+SUMIFS('1BS'!AA$69:AA$124,'1BS'!$X$69:$X$124,'1CF'!$A32) -> 0 | AF32: =-SUMIFS('1BS'!AB$3:AB$68,'1BS'!$X$3:$X$68,'1CF'!$A32)+SUMIFS('1BS'!AB$69:AB$124,'1BS'!$X$69:$X$124,'1CF'!$A32) -> 0 | AG32: =-SUMIFS('1BS'!AC$3:AC$68,'1BS'!$X$3:$X$68,'1CF'!$A32)+SUMIFS('1BS'!AC$69:AC$124,'1BS'!$X$69:$X$124,'1CF'!$A32) -> 0 | AH32: =-SUMIFS('1BS'!AD$3:AD$68,'1BS'!$X$3:$X$68,'1CF'!$A32)+SUMIFS('1BS'!AD$69:AD$124,'1BS'!$X$69:$X$124,'1CF'!$A32) -> 0 | AI32: =-SUMIFS('1BS'!AE$3:AE$68,'1BS'!$X$3:$X$68,'1CF'!$A32)+SUMIFS('1BS'!AE$69:AE$124,'1BS'!$X$69:$X$124,'1CF'!$A32) -> 0 | AJ32: =-SUMIFS('1BS'!AF$3:AF$68,'1BS'!$X$3:$X$68,'1CF'!$A32)+SUMIFS('1BS'!AF$69:AF$124,'1BS'!$X$69:$X$124,'1CF'!$A32) -> 0 | AM32: leave
A33: 25 | B33: Payments for investments in other entities | D33: =SUMIFS(CF!K:K,CF!$A:$A,'1CF'!$A$33) -> -43881 | E33: =SUMIFS(CF!L:L,CF!$A:$A,'1CF'!$A$33) -> 0 | F33: =SUMIFS(CF!M:M,CF!$A:$A,'1CF'!$A$33) -> 0 | G33: =SUMIFS(CF!N:N,CF!$A:$A,'1CF'!$A$33) -> 0 | H33: =SUMIFS(CF!O:O,CF!$A:$A,'1CF'!$A$33) -> 0 | I33: =SUMIFS(CF!P:P,CF!$A:$A,'1CF'!$A$33) -> 0 | J33: =SUMIFS(CF!Q:Q,CF!$A:$A,'1CF'!$A$33) -> 0 | K33: =SUMIFS(CF!R:R,CF!$A:$A,'1CF'!$A$33) -> -954279 | L33: =SUMIFS(CF!S:S,CF!$A:$A,'1CF'!$A$33) -> 125894 | M33: =V33+AE33 -> 0 | N33: =W33+AF33 -> 0 | O33: =X33+AG33 -> 0 | P33: =Y33+AH33 -> 0 | Q33: =Z33+AI33 -> 0 | R33: =AA33+AJ33 -> 0 | AC33: =-SUMIFS('1BS'!Y$3:Y$68,'1BS'!$X$3:$X$68,'1CF'!$A33)+SUMIFS('1BS'!Y$69:Y$124,'1BS'!$X$69:$X$124,'1CF'!$A33) -> -74655 | AD33: =-SUMIFS('1BS'!Z$3:Z$68,'1BS'!$X$3:$X$68,'1CF'!$A33)+SUMIFS('1BS'!Z$69:Z$124,'1BS'!$X$69:$X$124,'1CF'!$A33) -> 84456 | AE33: =-SUMIFS('1BS'!AA$3:AA$68,'1BS'!$X$3:$X$68,'1CF'!$A33)+SUMIFS('1BS'!AA$69:AA$124,'1BS'!$X$69:$X$124,'1CF'!$A33) -> 0 | AF33: =-SUMIFS('1BS'!AB$3:AB$68,'1BS'!$X$3:$X$68,'1CF'!$A33)+SUMIFS('1BS'!AB$69:AB$124,'1BS'!$X$69:$X$124,'1CF'!$A33) -> 0 | AG33: =-SUMIFS('1BS'!AC$3:AC$68,'1BS'!$X$3:$X$68,'1CF'!$A33)+SUMIFS('1BS'!AC$69:AC$124,'1BS'!$X$69:$X$124,'1CF'!$A33) -> 0 | AH33: =-SUMIFS('1BS'!AD$3:AD$68,'1BS'!$X$3:$X$68,'1CF'!$A33)+SUMIFS('1BS'!AD$69:AD$124,'1BS'!$X$69:$X$124,'1CF'!$A33) -> 0 | AI33: =-SUMIFS('1BS'!AE$3:AE$68,'1BS'!$X$3:$X$68,'1CF'!$A33)+SUMIFS('1BS'!AE$69:AE$124,'1BS'!$X$69:$X$124,'1CF'!$A33) -> 0 | AJ33: =-SUMIFS('1BS'!AF$3:AF$68,'1BS'!$X$3:$X$68,'1CF'!$A33)+SUMIFS('1BS'!AF$69:AF$124,'1BS'!$X$69:$X$124,'1CF'!$A33) -> 0 | AM33: hide
A34: 26 | B34: Proceeds from sale of investments in other entities | D34: =SUMIFS(CF!K:K,CF!$A:$A,'1CF'!$A$34) -> 66048 | E34: =SUMIFS(CF!L:L,CF!$A:$A,'1CF'!$A$34) -> 28340 | F34: =SUMIFS(CF!M:M,CF!$A:$A,'1CF'!$A$34) -> 82063 | G34: =SUMIFS(CF!N:N,CF!$A:$A,'1CF'!$A$34) -> 0 | H34: =SUMIFS(CF!O:O,CF!$A:$A,'1CF'!$A$34) -> 444561 | I34: =SUMIFS(CF!P:P,CF!$A:$A,'1CF'!$A$34) -> 0 | J34: =SUMIFS(CF!Q:Q,CF!$A:$A,'1CF'!$A$34) -> 0 | K34: =SUMIFS(CF!R:R,CF!$A:$A,'1CF'!$A$34) -> 0 | L34: =SUMIFS(CF!S:S,CF!$A:$A,'1CF'!$A$34) -> 0 | M34: =V34+AE34 -> 0 | N34: =W34+AF34 -> 0 | O34: =X34+AG34 -> 0 | P34: =Y34+AH34 -> 0 | Q34: =Z34+AI34 -> 0 | R34: =AA34+AJ34 -> 0 | AC34: =-SUMIFS('1BS'!Y$3:Y$68,'1BS'!$X$3:$X$68,'1CF'!$A34)+SUMIFS('1BS'!Y$69:Y$124,'1BS'!$X$69:$X$124,'1CF'!$A34) -> 0 | AD34: =-SUMIFS('1BS'!Z$3:Z$68,'1BS'!$X$3:$X$68,'1CF'!$A34)+SUMIFS('1BS'!Z$69:Z$124,'1BS'!$X$69:$X$124,'1CF'!$A34) -> 0 | AE34: =-SUMIFS('1BS'!AA$3:AA$68,'1BS'!$X$3:$X$68,'1CF'!$A34)+SUMIFS('1BS'!AA$69:AA$124,'1BS'!$X$69:$X$124,'1CF'!$A34) -> 0 | AF34: =-SUMIFS('1BS'!AB$3:AB$68,'1BS'!$X$3:$X$68,'1CF'!$A34)+SUMIFS('1BS'!AB$69:AB$124,'1BS'!$X$69:$X$124,'1CF'!$A34) -> 0 | AG34: =-SUMIFS('1BS'!AC$3:AC$68,'1BS'!$X$3:$X$68,'1CF'!$A34)+SUMIFS('1BS'!AC$69:AC$124,'1BS'!$X$69:$X$124,'1CF'!$A34) -> 0 | AH34: =-SUMIFS('1BS'!AD$3:AD$68,'1BS'!$X$3:$X$68,'1CF'!$A34)+SUMIFS('1BS'!AD$69:AD$124,'1BS'!$X$69:$X$124,'1CF'!$A34) -> 0 | AI34: =-SUMIFS('1BS'!AE$3:AE$68,'1BS'!$X$3:$X$68,'1CF'!$A34)+SUMIFS('1BS'!AE$69:AE$124,'1BS'!$X$69:$X$124,'1CF'!$A34) -> 0 | AJ34: =-SUMIFS('1BS'!AF$3:AF$68,'1BS'!$X$3:$X$68,'1CF'!$A34)+SUMIFS('1BS'!AF$69:AF$124,'1BS'!$X$69:$X$124,'1CF'!$A34) -> 0 | AM34: leave
A35: 27 | B35: Interest and dividends received | D35: =SUMIFS(CF!K:K,CF!$A:$A,'1CF'!$A$35) -> 678089 | E35: =SUMIFS(CF!L:L,CF!$A:$A,'1CF'!$A$35) -> 934229 | F35: =SUMIFS(CF!M:M,CF!$A:$A,'1CF'!$A$35) -> 955091 | G35: =SUMIFS(CF!N:N,CF!$A:$A,'1CF'!$A$35) -> 1023969 | H35: =SUMIFS(CF!O:O,CF!$A:$A,'1CF'!$A$35) -> 1111566 | I35: =SUMIFS(CF!P:P,CF!$A:$A,'1CF'!$A$35) -> 1013860 | J35: =SUMIFS(CF!Q:Q,CF!$A:$A,'1CF'!$A$35) -> 1363536 | K35: =SUMIFS(CF!R:R,CF!$A:$A,'1CF'!$A$35) -> 1387124 | L35: =SUMIFS(CF!S:S,CF!$A:$A,'1CF'!$A$35) -> 1462274 | M35: =V35+AE35 -> 960583.2 | N35: =W35+AF35 -> 913313.45 | O35: =X35+AG35 -> 906594.42 | P35: =Y35+AH35 -> 904404.96 | Q35: =Z35+AI35 -> 901260.3 | R35: =AA35+AJ35 -> 924798.59 | T35: =-T11 -> 1044633 | U35: =-U11 -> 995208 | V35: =-V11 -> 960583.2 | W35: =-W11 -> 913313.45 | X35: =-X11 -> 906594.42 | Y35: =-Y11 -> 904404.96 | Z35: =-Z11 -> 901260.3 | AA35: =-AA11 -> 924798.59 | AC35: =-SUMIFS('1BS'!Y$3:Y$68,'1BS'!$X$3:$X$68,'1CF'!$A35)+SUMIFS('1BS'!Y$69:Y$124,'1BS'!$X$69:$X$124,'1CF'!$A35) -> 0 | AD35: =-SUMIFS('1BS'!Z$3:Z$68,'1BS'!$X$3:$X$68,'1CF'!$A35)+SUMIFS('1BS'!Z$69:Z$124,'1BS'!$X$69:$X$124,'1CF'!$A35) -> 0 | AE35: =-SUMIFS('1BS'!AA$3:AA$68,'1BS'!$X$3:$X$68,'1CF'!$A35)+SUMIFS('1BS'!AA$69:AA$124,'1BS'!$X$69:$X$124,'1CF'!$A35) -> 0 | AF35: =-SUMIFS('1BS'!AB$3:AB$68,'1BS'!$X$3:$X$68,'1CF'!$A35)+SUMIFS('1BS'!AB$69:AB$124,'1BS'!$X$69:$X$124,'1CF'!$A35) -> 0 | AG35: =-SUMIFS('1BS'!AC$3:AC$68,'1BS'!$X$3:$X$68,'1CF'!$A35)+SUMIFS('1BS'!AC$69:AC$124,'1BS'!$X$69:$X$124,'1CF'!$A35) -> 0 | AH35: =-SUMIFS('1BS'!AD$3:AD$68,'1BS'!$X$3:$X$68,'1CF'!$A35)+SUMIFS('1BS'!AD$69:AD$124,'1BS'!$X$69:$X$124,'1CF'!$A35) -> 0 | AI35: =-SUMIFS('1BS'!AE$3:AE$68,'1BS'!$X$3:$X$68,'1CF'!$A35)+SUMIFS('1BS'!AE$69:AE$124,'1BS'!$X$69:$X$124,'1CF'!$A35) -> 0 | AJ35: =-SUMIFS('1BS'!AF$3:AF$68,'1BS'!$X$3:$X$68,'1CF'!$A35)+SUMIFS('1BS'!AF$69:AF$124,'1BS'!$X$69:$X$124,'1CF'!$A35) -> 0 | AM35: leave
AM36: leave
A37: 30 | B37: Net cash flows from/(used in) investing activities | D37: =CF!K38 -> -2820518 | E37: =CF!L38 -> -311248 | F37: =CF!M38 -> -4109044 | G37: =CF!N38 -> -1523225 | H37: =CF!O38 -> -1223348 | I37: =CF!P38 -> -1867768 | J37: =CF!Q38 -> 2715583 | K37: =CF!R38 -> 18884 | L37: =CF!S38 -> 2423075 | M37: =SUM(M29:M35) -> 1157062.3 | N37: =SUM(N29:N35) -> 1630789.4 | O37: =SUM(O29:O35) -> 1058171.7 | P37: =SUM(P29:P35) -> 800539.81 | Q37: =SUM(Q29:Q35) -> 895529.07 | R37: =SUM(R29:R35) -> 514267.34 | AC37: =SUM(AC29:AC35) -> -185828 | AD37: =SUM(AD29:AD35) -> -3678508 | AE37: =SUM(AE29:AE35) -> 196479.11 | AF37: =SUM(AF29:AF35) -> 717475.95 | AG37: =SUM(AG29:AG35) -> 151577.3 | AH37: =SUM(AH29:AH35) -> -103865.15 | AI37: =SUM(AI29:AI35) -> -5731.2332 | AJ37: =SUM(AJ29:AJ35) -> -410531.25 | AM37: leave
AM38: leave
AM39: leave
B40: III. CASH FLOWS FROM FINANCING ACTIVITIES | AM40: leave
A41: 31 | B41: Capital contribution and issuance of shares | D41: =SUMIFS(CF!K:K,CF!$A:$A,'1CF'!$A$41) -> 67208 | E41: =SUMIFS(CF!L:L,CF!$A:$A,'1CF'!$A$41) -> 0 | F41: =SUMIFS(CF!M:M,CF!$A:$A,'1CF'!$A$41) -> 0 | G41: =SUMIFS(CF!N:N,CF!$A:$A,'1CF'!$A$41) -> 0 | H41: =SUMIFS(CF!O:O,CF!$A:$A,'1CF'!$A$41) -> 0 | I41: =SUMIFS(CF!P:P,CF!$A:$A,'1CF'!$A$41) -> 0 | J41: =SUMIFS(CF!Q:Q,CF!$A:$A,'1CF'!$A$41) -> 0 | K41: =SUMIFS(CF!R:R,CF!$A:$A,'1CF'!$A$41) -> 0 | L41: =SUMIFS(CF!S:S,CF!$A:$A,'1CF'!$A$41) -> 0 | M41: =V41+AE41 -> 0 | N41: =W41+AF41 -> 0 | O41: =X41+AG41 -> 0 | P41: =Y41+AH41 -> 0 | Q41: =Z41+AI41 -> 0 | R41: =AB41+AJ41 -> 0 | AC41: =-SUMIFS('1BS'!Y$3:Y$68,'1BS'!$X$3:$X$68,'1CF'!$A41)+SUMIFS('1BS'!Y$69:Y$124,'1BS'!$X$69:$X$124,'1CF'!$A41) -> 0 | AD41: =-SUMIFS('1BS'!Z$3:Z$68,'1BS'!$X$3:$X$68,'1CF'!$A41)+SUMIFS('1BS'!Z$69:Z$124,'1BS'!$X$69:$X$124,'1CF'!$A41) -> 0 | AE41: =-SUMIFS('1BS'!AA$3:AA$68,'1BS'!$X$3:$X$68,'1CF'!$A41)+SUMIFS('1BS'!AA$69:AA$124,'1BS'!$X$69:$X$124,'1CF'!$A41) -> 0 | AF41: =-SUMIFS('1BS'!AB$3:AB$68,'1BS'!$X$3:$X$68,'1CF'!$A41)+SUMIFS('1BS'!AB$69:AB$124,'1BS'!$X$69:$X$124,'1CF'!$A41) -> 0 | AG41: =-SUMIFS('1BS'!AC$3:AC$68,'1BS'!$X$3:$X$68,'1CF'!$A41)+SUMIFS('1BS'!AC$69:AC$124,'1BS'!$X$69:$X$124,'1CF'!$A41) -> 0 | AH41: =-SUMIFS('1BS'!AD$3:AD$68,'1BS'!$X$3:$X$68,'1CF'!$A41)+SUMIFS('1BS'!AD$69:AD$124,'1BS'!$X$69:$X$124,'1CF'!$A41) -> 0 | AI41: =-SUMIFS('1BS'!AE$3:AE$68,'1BS'!$X$3:$X$68,'1CF'!$A41)+SUMIFS('1BS'!AE$69:AE$124,'1BS'!$X$69:$X$124,'1CF'!$A41) -> 0 | AJ41: =-SUMIFS('1BS'!AF$3:AF$68,'1BS'!$X$3:$X$68,'1CF'!$A41)+SUMIFS('1BS'!AF$69:AF$124,'1BS'!$X$69:$X$124,'1CF'!$A41) -> 0 | AM41: leave
A42: 32 | B42: Capital redemption | D42: =SUMIFS(CF!K:K,CF!$A:$A,'1CF'!$A$42) -> 0 | E42: =SUMIFS(CF!L:L,CF!$A:$A,'1CF'!$A$42) -> 0 | F42: =SUMIFS(CF!M:M,CF!$A:$A,'1CF'!$A$42) -> 0 | G42: =SUMIFS(CF!N:N,CF!$A:$A,'1CF'!$A$42) -> 0 | H42: =SUMIFS(CF!O:O,CF!$A:$A,'1CF'!$A$42) -> 0 | I42: =SUMIFS(CF!P:P,CF!$A:$A,'1CF'!$A$42) -> 0 | J42: =SUMIFS(CF!Q:Q,CF!$A:$A,'1CF'!$A$42) -> 0 | K42: =SUMIFS(CF!R:R,CF!$A:$A,'1CF'!$A$42) -> 0 | L42: =SUMIFS(CF!S:S,CF!$A:$A,'1CF'!$A$42) -> 0 | M42: =V42+AE42 -> 0 | N42: =W42+AF42 -> 0 | O42: =X42+AG42 -> 0 | P42: =Y42+AH42 -> 0 | Q42: =Z42+AI42 -> 0 | R42: =AB42+AJ42 -> 0 | AC42: =-SUMIFS('1BS'!Y$3:Y$68,'1BS'!$X$3:$X$68,'1CF'!$A42)+SUMIFS('1BS'!Y$69:Y$124,'1BS'!$X$69:$X$124,'1CF'!$A42) -> 0 | AD42: =-SUMIFS('1BS'!Z$3:Z$68,'1BS'!$X$3:$X$68,'1CF'!$A42)+SUMIFS('1BS'!Z$69:Z$124,'1BS'!$X$69:$X$124,'1CF'!$A42) -> 0 | AE42: =-SUMIFS('1BS'!AA$3:AA$68,'1BS'!$X$3:$X$68,'1CF'!$A42)+SUMIFS('1BS'!AA$69:AA$124,'1BS'!$X$69:$X$124,'1CF'!$A42) -> 0 | AF42: =-SUMIFS('1BS'!AB$3:AB$68,'1BS'!$X$3:$X$68,'1CF'!$A42)+SUMIFS('1BS'!AB$69:AB$124,'1BS'!$X$69:$X$124,'1CF'!$A42) -> 0 | AG42: =-SUMIFS('1BS'!AC$3:AC$68,'1BS'!$X$3:$X$68,'1CF'!$A42)+SUMIFS('1BS'!AC$69:AC$124,'1BS'!$X$69:$X$124,'1CF'!$A42) -> 0 | AH42: =-SUMIFS('1BS'!AD$3:AD$68,'1BS'!$X$3:$X$68,'1CF'!$A42)+SUMIFS('1BS'!AD$69:AD$124,'1BS'!$X$69:$X$124,'1CF'!$A42) -> 0 | AI42: =-SUMIFS('1BS'!AE$3:AE$68,'1BS'!$X$3:$X$68,'1CF'!$A42)+SUMIFS('1BS'!AE$69:AE$124,'1BS'!$X$69:$X$124,'1CF'!$A42) -> 0 | AJ42: =-SUMIFS('1BS'!AF$3:AF$68,'1BS'!$X$3:$X$68,'1CF'!$A42)+SUMIFS('1BS'!AF$69:AF$124,'1BS'!$X$69:$X$124,'1CF'!$A42) -> 0 | AM42: leave
A43: 33 | B43: Drawdown of borrowings | D43: =SUMIFS(CF!K:K,CF!$A:$A,'1CF'!$A$43) -> 3541517 | E43: =SUMIFS(CF!L:L,CF!$A:$A,'1CF'!$A$43) -> 3255664 | F43: =SUMIFS(CF!M:M,CF!$A:$A,'1CF'!$A$43) -> 3235968 | G43: =SUMIFS(CF!N:N,CF!$A:$A,'1CF'!$A$43) -> 3061076 | H43: =SUMIFS(CF!O:O,CF!$A:$A,'1CF'!$A$43) -> 2984179 | I43: =SUMIFS(CF!P:P,CF!$A:$A,'1CF'!$A$43) -> 3279891 | J43: =SUMIFS(CF!Q:Q,CF!$A:$A,'1CF'!$A$43) -> 4130545 | K43: =SUMIFS(CF!R:R,CF!$A:$A,'1CF'!$A$43) -> 2934074 | L43: =SUMIFS(CF!S:S,CF!$A:$A,'1CF'!$A$43) -> 2791553 | M43: =V43+AE43 -> 22700.633 | N43: =W43+AF43 -> 23383.997 | O43: =X43+AG43 -> 25772.534 | P43: =Y43+AH43 -> 28377.173 | Q43: =Z43+AI43 -> 31217.467 | R43: =AB43+AJ43 -> 34314.736 | AC43: =-SUMIFS('1BS'!Y$3:Y$68,'1BS'!$X$3:$X$68,'1CF'!$A43)+SUMIFS('1BS'!Y$69:Y$124,'1BS'!$X$69:$X$124,'1CF'!$A43) -> -284741 | AD43: =-SUMIFS('1BS'!Z$3:Z$68,'1BS'!$X$3:$X$68,'1CF'!$A43)+SUMIFS('1BS'!Z$69:Z$124,'1BS'!$X$69:$X$124,'1CF'!$A43) -> 40740 | AE43: =-SUMIFS('1BS'!AA$3:AA$68,'1BS'!$X$3:$X$68,'1CF'!$A43)+SUMIFS('1BS'!AA$69:AA$124,'1BS'!$X$69:$X$124,'1CF'!$A43) -> 22700.633 | AF43: =-SUMIFS('1BS'!AB$3:AB$68,'1BS'!$X$3:$X$68,'1CF'!$A43)+SUMIFS('1BS'!AB$69:AB$124,'1BS'!$X$69:$X$124,'1CF'!$A43) -> 23383.997 | AG43: =-SUMIFS('1BS'!AC$3:AC$68,'1BS'!$X$3:$X$68,'1CF'!$A43)+SUMIFS('1BS'!AC$69:AC$124,'1BS'!$X$69:$X$124,'1CF'!$A43) -> 25772.534 | AH43: =-SUMIFS('1BS'!AD$3:AD$68,'1BS'!$X$3:$X$68,'1CF'!$A43)+SUMIFS('1BS'!AD$69:AD$124,'1BS'!$X$69:$X$124,'1CF'!$A43) -> 28377.173 | AI43: =-SUMIFS('1BS'!AE$3:AE$68,'1BS'!$X$3:$X$68,'1CF'!$A43)+SUMIFS('1BS'!AE$69:AE$124,'1BS'!$X$69:$X$124,'1CF'!$A43) -> 31217.467 | AJ43: =-SUMIFS('1BS'!AF$3:AF$68,'1BS'!$X$3:$X$68,'1CF'!$A43)+SUMIFS('1BS'!AF$69:AF$124,'1BS'!$X$69:$X$124,'1CF'!$A43) -> 34314.736 | AK43: Net-off dòng thu và chi nợ ngắn hạn | AM43: leave
A44: 34 | B44: Repayment of borrowings | D44: =SUMIFS(CF!K:K,CF!$A:$A,'1CF'!$A$44) -> -4023394 | E44: =SUMIFS(CF!L:L,CF!$A:$A,'1CF'!$A$44) -> -3371649 | F44: =SUMIFS(CF!M:M,CF!$A:$A,'1CF'!$A$44) -> -3346480 | G44: =SUMIFS(CF!N:N,CF!$A:$A,'1CF'!$A$44) -> -3309442 | H44: =SUMIFS(CF!O:O,CF!$A:$A,'1CF'!$A$44) -> -3301894 | I44: =SUMIFS(CF!P:P,CF!$A:$A,'1CF'!$A$44) -> -2908733 | J44: =SUMIFS(CF!Q:Q,CF!$A:$A,'1CF'!$A$44) -> -4461478 | K44: =SUMIFS(CF!R:R,CF!$A:$A,'1CF'!$A$44) -> -3218974 | L44: =SUMIFS(CF!S:S,CF!$A:$A,'1CF'!$A$44) -> -3066634 | M44: =V44+AE44 -> 0 | N44: =W44+AF44 -> 0 | O44: =X44+AG44 -> 0 | P44: =Y44+AH44 -> 0 | Q44: =Z44+AI44 -> 0 | R44: =AB44+AJ44 -> 0 | AC44: =-SUMIFS('1BS'!Y$3:Y$68,'1BS'!$X$3:$X$68,'1CF'!$A44)+SUMIFS('1BS'!Y$69:Y$124,'1BS'!$X$69:$X$124,'1CF'!$A44) -> 0 | AD44: =-SUMIFS('1BS'!Z$3:Z$68,'1BS'!$X$3:$X$68,'1CF'!$A44)+SUMIFS('1BS'!Z$69:Z$124,'1BS'!$X$69:$X$124,'1CF'!$A44) -> 0 | AE44: =-SUMIFS('1BS'!AA$3:AA$68,'1BS'!$X$3:$X$68,'1CF'!$A44)+SUMIFS('1BS'!AA$69:AA$124,'1BS'!$X$69:$X$124,'1CF'!$A44) -> 0 | AF44: =-SUMIFS('1BS'!AB$3:AB$68,'1BS'!$X$3:$X$68,'1CF'!$A44)+SUMIFS('1BS'!AB$69:AB$124,'1BS'!$X$69:$X$124,'1CF'!$A44) -> 0 | AG44: =-SUMIFS('1BS'!AC$3:AC$68,'1BS'!$X$3:$X$68,'1CF'!$A44)+SUMIFS('1BS'!AC$69:AC$124,'1BS'!$X$69:$X$124,'1CF'!$A44) -> 0 | AH44: =-SUMIFS('1BS'!AD$3:AD$68,'1BS'!$X$3:$X$68,'1CF'!$A44)+SUMIFS('1BS'!AD$69:AD$124,'1BS'!$X$69:$X$124,'1CF'!$A44) -> 0 | AI44: =-SUMIFS('1BS'!AE$3:AE$68,'1BS'!$X$3:$X$68,'1CF'!$A44)+SUMIFS('1BS'!AE$69:AE$124,'1BS'!$X$69:$X$124,'1CF'!$A44) -> 0 | AJ44: =-SUMIFS('1BS'!AF$3:AF$68,'1BS'!$X$3:$X$68,'1CF'!$A44)+SUMIFS('1BS'!AF$69:AF$124,'1BS'!$X$69:$X$124,'1CF'!$A44) -> 0 | AM44: leave
A45: 35 | B45: Payment of principal of finance lease liabilities | D45: =SUMIFS(CF!K:K,CF!$A:$A,'1CF'!$A$45) -> 0 | E45: =SUMIFS(CF!L:L,CF!$A:$A,'1CF'!$A$45) -> 0 | F45: =SUMIFS(CF!M:M,CF!$A:$A,'1CF'!$A$45) -> 0 | G45: =SUMIFS(CF!N:N,CF!$A:$A,'1CF'!$A$45) -> -12727 | H45: =SUMIFS(CF!O:O,CF!$A:$A,'1CF'!$A$45) -> 0 | I45: =SUMIFS(CF!P:P,CF!$A:$A,'1CF'!$A$45) -> 0 | J45: =SUMIFS(CF!Q:Q,CF!$A:$A,'1CF'!$A$45) -> 0 | K45: =SUMIFS(CF!R:R,CF!$A:$A,'1CF'!$A$45) -> 0 | L45: =SUMIFS(CF!S:S,CF!$A:$A,'1CF'!$A$45) -> 0 | M45: =V45+AE45 -> 0 | N45: =W45+AF45 -> 0 | O45: =X45+AG45 -> 0 | P45: =Y45+AH45 -> 0 | Q45: =Z45+AI45 -> 0 | R45: =AB45+AJ45 -> 0 | AC45: =-SUMIFS('1BS'!Y$3:Y$68,'1BS'!$X$3:$X$68,'1CF'!$A45)+SUMIFS('1BS'!Y$69:Y$124,'1BS'!$X$69:$X$124,'1CF'!$A45) -> 0 | AD45: =-SUMIFS('1BS'!Z$3:Z$68,'1BS'!$X$3:$X$68,'1CF'!$A45)+SUMIFS('1BS'!Z$69:Z$124,'1BS'!$X$69:$X$124,'1CF'!$A45) -> 0 | AE45: =-SUMIFS('1BS'!AA$3:AA$68,'1BS'!$X$3:$X$68,'1CF'!$A45)+SUMIFS('1BS'!AA$69:AA$124,'1BS'!$X$69:$X$124,'1CF'!$A45) -> 0 | AF45: =-SUMIFS('1BS'!AB$3:AB$68,'1BS'!$X$3:$X$68,'1CF'!$A45)+SUMIFS('1BS'!AB$69:AB$124,'1BS'!$X$69:$X$124,'1CF'!$A45) -> 0 | AG45: =-SUMIFS('1BS'!AC$3:AC$68,'1BS'!$X$3:$X$68,'1CF'!$A45)+SUMIFS('1BS'!AC$69:AC$124,'1BS'!$X$69:$X$124,'1CF'!$A45) -> 0 | AH45: =-SUMIFS('1BS'!AD$3:AD$68,'1BS'!$X$3:$X$68,'1CF'!$A45)+SUMIFS('1BS'!AD$69:AD$124,'1BS'!$X$69:$X$124,'1CF'!$A45) -> 0 | AI45: =-SUMIFS('1BS'!AE$3:AE$68,'1BS'!$X$3:$X$68,'1CF'!$A45)+SUMIFS('1BS'!AE$69:AE$124,'1BS'!$X$69:$X$124,'1CF'!$A45) -> 0 | AJ45: =-SUMIFS('1BS'!AF$3:AF$68,'1BS'!$X$3:$X$68,'1CF'!$A45)+SUMIFS('1BS'!AF$69:AF$124,'1BS'!$X$69:$X$124,'1CF'!$A45) -> 0 | AM45: leave
A46: 36 | B46: Dividends paid | D46: =SUMIFS(CF!K:K,CF!$A:$A,'1CF'!$A$46) -> -1008865 | E46: =SUMIFS(CF!L:L,CF!$A:$A,'1CF'!$A$46) -> -3888749 | F46: =SUMIFS(CF!M:M,CF!$A:$A,'1CF'!$A$46) -> -1136965 | G46: =SUMIFS(CF!N:N,CF!$A:$A,'1CF'!$A$46) -> -3734027 | H46: =SUMIFS(CF!O:O,CF!$A:$A,'1CF'!$A$46) -> -1096307 | I46: =SUMIFS(CF!P:P,CF!$A:$A,'1CF'!$A$46) -> -2418865 | J46: =SUMIFS(CF!Q:Q,CF!$A:$A,'1CF'!$A$46) -> -3354093 | K46: =SUMIFS(CF!R:R,CF!$A:$A,'1CF'!$A$46) -> -4658550 | L46: =SUMIFS(CF!S:S,CF!$A:$A,'1CF'!$A$46) -> -6512668 | M46: =Equity!P25+Equity!P131 -> -4821434 | N46: =Equity!Q25+Equity!Q131 -> -4790312 | O46: =Equity!R25+Equity!R131 -> -4765744.2 | P46: =Equity!S25+Equity!S131 -> -4748431.8 | Q46: =Equity!T25+Equity!T131 -> -4734909 | R46: =Equity!U25+Equity!U131 -> -4725452.8 | AC46: =-SUMIFS('1BS'!Y$3:Y$68,'1BS'!$X$3:$X$68,'1CF'!$A46)+SUMIFS('1BS'!Y$69:Y$124,'1BS'!$X$69:$X$124,'1CF'!$A46) -> 0 | AD46: =-SUMIFS('1BS'!Z$3:Z$68,'1BS'!$X$3:$X$68,'1CF'!$A46)+SUMIFS('1BS'!Z$69:Z$124,'1BS'!$X$69:$X$124,'1CF'!$A46) -> 0 | AE46: =-SUMIFS('1BS'!AA$3:AA$68,'1BS'!$X$3:$X$68,'1CF'!$A46)+SUMIFS('1BS'!AA$69:AA$124,'1BS'!$X$69:$X$124,'1CF'!$A46) -> 0 | AF46: =-SUMIFS('1BS'!AB$3:AB$68,'1BS'!$X$3:$X$68,'1CF'!$A46)+SUMIFS('1BS'!AB$69:AB$124,'1BS'!$X$69:$X$124,'1CF'!$A46) -> 0 | AG46: =-SUMIFS('1BS'!AC$3:AC$68,'1BS'!$X$3:$X$68,'1CF'!$A46)+SUMIFS('1BS'!AC$69:AC$124,'1BS'!$X$69:$X$124,'1CF'!$A46) -> 0 | AH46: =-SUMIFS('1BS'!AD$3:AD$68,'1BS'!$X$3:$X$68,'1CF'!$A46)+SUMIFS('1BS'!AD$69:AD$124,'1BS'!$X$69:$X$124,'1CF'!$A46) -> 0 | AI46: =-SUMIFS('1BS'!AE$3:AE$68,'1BS'!$X$3:$X$68,'1CF'!$A46)+SUMIFS('1BS'!AE$69:AE$124,'1BS'!$X$69:$X$124,'1CF'!$A46) -> 0 | AJ46: =-SUMIFS('1BS'!AF$3:AF$68,'1BS'!$X$3:$X$68,'1CF'!$A46)+SUMIFS('1BS'!AF$69:AF$124,'1BS'!$X$69:$X$124,'1CF'!$A46) -> 0 | AM46: leave
AM47: leave
A48: 40 | B48: Net cash flows from/(used in) financing activities | D48: =CF!K50 -> -1423533 | E48: =CF!L50 -> -4004734 | F48: =CF!M50 -> -1247477 | G48: =CF!N50 -> -3995121 | H48: =CF!O50 -> -1414022 | I48: =CF!P50 -> -2047707 | J48: =CF!Q50 -> -3685025 | K48: =CF!R50 -> -4943450 | L48: =CF!S50 -> -6787750 | M48: =SUM(M41:M46) -> -4798733.3 | N48: =SUM(N41:N46) -> -4766928 | O48: =SUM(O41:O46) -> -4739971.6 | P48: =SUM(P41:P46) -> -4720054.6 | Q48: =SUM(Q41:Q46) -> -4703691.5 | R48: =SUM(R41:R46) -> -4691138.1 | AC48: =SUM(AC41:AC46) -> -284741 | AD48: =SUM(AD41:AD46) -> 40740 | AE48: =SUM(AE41:AE46) -> 22700.633 | AF48: =SUM(AF41:AF46) -> 23383.997 | AG48: =SUM(AG41:AG46) -> 25772.534 | AH48: =SUM(AH41:AH46) -> 28377.173 | AI48: =SUM(AI41:AI46) -> 31217.467 | AJ48: =SUM(AJ41:AJ46) -> 34314.736 | AM48: leave
AM49: leave
AM50: leave
A51: 50 | B51: Net increase/(decrease) in cash [and cash equivalents] | D51: =CF!K51 -> 823768 | E51: =CF!L51 -> 198804 | F51: =CF!M51 -> -351509 | G51: =CF!N51 -> -1389734 | H51: =CF!O51 -> 880482 | I51: =CF!P51 -> 463042 | J51: =CF!Q51 -> 970623 | K51: =CF!R51 -> -562056 | L51: =CF!S51 -> -460598 | M51: =SUM(M26,M37,M48) -> -269304.56 | N51: =SUM(N26,N37,N48) -> 1174835.9 | O51: =SUM(O26,O37,O48) -> 1490653.4 | P51: =SUM(P26,P37,P48) -> 1128694.8 | Q51: =SUM(Q26,Q37,Q48) -> 1535118.2 | R51: =SUM(R26,R37,R48) -> 728243.66 | AC51: =SUM(AC26,AC37,AC48) -> 6127968 | AD51: =SUM(AD26,AD37,AD48) -> 6596729 | AE51: =SUM(AE26,AE37,AE48) -> 5746191.3 | AF51: =SUM(AF26,AF37,AF48) -> 7180637.3 | AG51: =SUM(AG26,AG37,AG48) -> 7542293.6 | AH51: =SUM(AH26,AH37,AH48) -> 7172085.6 | AI51: =SUM(AI26,AI37,AI48) -> 7599622.3 | AJ51: =SUM(AJ26,AJ37,AJ48) -> 6808494.5 | AM51: leave
A53: 60 | B53: Cash [and cash equivalents] at beginning of period | D53: =CF!K52 -> 3444825 | E53: =CF!L52 -> 4268599 | F53: =CF!M52 -> 4467392 | G53: =CF!N52 -> 4115885 | H53: =CF!O52 -> 2726137 | I53: =CF!P52 -> 3606454 | J53: =CF!Q52 -> 4069464 | K53: =CF!R52 -> 5039908 | L53: =CF!S52 -> 4477502 | M53: =L57 -> 4016882 | N53: =M57 -> 3747577.4 | O53: =N57 -> 4922413.3 | P53: =O57 -> 6413066.7 | Q53: =P57 -> 7541761.5 | R53: =Q57 -> 9076879.8 | AC53: =I57 -> 4069464 | AD53: =AC57 -> 10197432 | AE53: =AD57 -> 16794161 | AF53: =AE57 -> 22540352 | AG53: =AF57 -> 29720990 | AH53: =AG57 -> 37263283 | AI53: =AH57 -> 44435369 | AJ53: =AI57 -> 52034991 | AM53: leave
A55: 61 | B55: Impact of exchange rate fluctuation | D55: =SUMIFS(CF!K:K,CF!$A:$A,'1CF'!$A$55) -> 6 | E55: =SUMIFS(CF!L:L,CF!$A:$A,'1CF'!$A$55) -> -11 | F55: =SUMIFS(CF!M:M,CF!$A:$A,'1CF'!$A$55) -> 2 | G55: =SUMIFS(CF!N:N,CF!$A:$A,'1CF'!$A$55) -> -14 | H55: =SUMIFS(CF!O:O,CF!$A:$A,'1CF'!$A$55) -> -164 | I55: =SUMIFS(CF!P:P,CF!$A:$A,'1CF'!$A$55) -> -32 | J55: =SUMIFS(CF!Q:Q,CF!$A:$A,'1CF'!$A$55) -> -179 | K55: =SUMIFS(CF!R:R,CF!$A:$A,'1CF'!$A$55) -> -350 | L55: =SUMIFS(CF!S:S,CF!$A:$A,'1CF'!$A$55) -> -22 | M55: 0 | N55: 0 | O55: 0 | P55: 0 | Q55: 0 | R55: 0 | AC55: =-SUMIFS('1BS'!Y$3:Y$68,'1BS'!$X$3:$X$68,'1CF'!$A55)+SUMIFS('1BS'!Y$69:Y$124,'1BS'!$X$69:$X$124,'1CF'!$A55) -> 0 | AD55: =-SUMIFS('1BS'!Z$3:Z$68,'1BS'!$X$3:$X$68,'1CF'!$A55)+SUMIFS('1BS'!Z$69:Z$124,'1BS'!$X$69:$X$124,'1CF'!$A55) -> 0 | AE55: =-SUMIFS('1BS'!AA$3:AA$68,'1BS'!$X$3:$X$68,'1CF'!$A55)+SUMIFS('1BS'!AA$69:AA$124,'1BS'!$X$69:$X$124,'1CF'!$A55) -> 0 | AF55: =-SUMIFS('1BS'!AB$3:AB$68,'1BS'!$X$3:$X$68,'1CF'!$A55)+SUMIFS('1BS'!AB$69:AB$124,'1BS'!$X$69:$X$124,'1CF'!$A55) -> 0 | AG55: =-SUMIFS('1BS'!AC$3:AC$68,'1BS'!$X$3:$X$68,'1CF'!$A55)+SUMIFS('1BS'!AC$69:AC$124,'1BS'!$X$69:$X$124,'1CF'!$A55) -> 0 | AH55: =-SUMIFS('1BS'!AD$3:AD$68,'1BS'!$X$3:$X$68,'1CF'!$A55)+SUMIFS('1BS'!AD$69:AD$124,'1BS'!$X$69:$X$124,'1CF'!$A55) -> 0 | AI55: =-SUMIFS('1BS'!AE$3:AE$68,'1BS'!$X$3:$X$68,'1CF'!$A55)+SUMIFS('1BS'!AE$69:AE$124,'1BS'!$X$69:$X$124,'1CF'!$A55) -> 0 | AJ55: =-SUMIFS('1BS'!AF$3:AF$68,'1BS'!$X$3:$X$68,'1CF'!$A55)+SUMIFS('1BS'!AF$69:AF$124,'1BS'!$X$69:$X$124,'1CF'!$A55) -> 0 | AM55: leave
AM56: leave
A57: 70 | B57: Cash [and cash equivalents] at end of period | D57: =D55+D53+D51 -> 4268599 | E57: =E55+E53+E51 -> 4467392 | F57: =F55+F53+F51 -> 4115885 | G57: =G55+G53+G51 -> 2726137 | H57: =H55+H53+H51 -> 3606455 | I57: =I55+I53+I51 -> 4069464 | J57: =J55+J53+J51 -> 5039908 | K57: =K55+K53+K51 -> 4477502 | ... R57: =R55+R53+R51 -> 9805123.4 | AC57: =AC55+AC53+AC51 -> 10197432 | AD57: =AD55+AD53+AD51 -> 16794161 | AE57: =AE55+AE53+AE51 -> 22540352 | AF57: =AF55+AF53+AF51 -> 29720990 | AG57: =AG55+AG53+AG51 -> 37263283 | AH57: =AH55+AH53+AH51 -> 44435369 | AI57: =AI55+AI53+AI51 -> 52034991 | AJ57: =AJ55+AJ53+AJ51 -> 58843486 | AM57: leave
C59: Check | D59: =ROUND('1BS'!G4-CF!K54,0) -> 0 | E59: =ROUND('1BS'!H4-CF!L54,0) -> 0 | F59: =ROUND('1BS'!I4-CF!M54,0) -> 0 | G59: =ROUND('1BS'!J4-CF!N54,0) -> 0 | H59: =ROUND('1BS'!K4-CF!O54,0) -> 0 | I59: =ROUND('1BS'!L4-CF!P54,0) -> 0 | J59: =ROUND('1BS'!M4-CF!Q54,0) -> 0 | K59: =ROUND('1BS'!N4-CF!R54,0) -> 0 | L59: =ROUND('1BS'!O4-CF!S54,0) -> 0 | M59: =ROUND('1BS'!P4-'1CF'!M57,0) -> 0 | N59: =ROUND('1BS'!Q4-'1CF'!N57,0) -> 0 | O59: =ROUND('1BS'!R4-'1CF'!O57,0) -> 0 | P59: =ROUND('1BS'!S4-'1CF'!P57,0) -> 0 | Q59: =ROUND('1BS'!T4-'1CF'!Q57,0) -> 0 | R59: =ROUND('1BS'!U4-'1CF'!R57,0) -> 0 | T59: =SUM(T6:T57) -> 0 | U59: =SUM(U6:U57) -> 0 | V59: =SUM(V6:V57) -> 0 | W59: =SUM(W6:W57) -> 0 | X59: =SUM(X6:X57) -> 0 | Y59: =SUM(Y6:Y57) -> 0 | Z59: =SUM(Z6:Z57) -> 0 | AA59: =SUM(AA6:AA57) -> 0

Sheet Equity
B1: CHECK CF ERROR | G1: chưa dự phóng 2026
B2: SAB
B3: Units: VND billion, except per share data | K3: Historical | P3: Projected
B4: SHAREHOLDER EQUITY | C4: 2013 | D4: 2014 | E4: 2015 | F4: 2016 | G4: 2017 | H4: 2018 | I4: 2019 | J4: 2020 | K4: 2021 | L4: 2022 | M4: 2023 | N4: 2024 | O4: 2025 | P4: =O4+1 -> 2026 | Q4: =P4+1 -> 2027 | R4: =Q4+1 -> 2028 | S4: =R4+1 -> 2029 | T4: =S4+1 -> 2030 | U4: =T4+1 -> 2031
A5: 1 | B5: Chartered capital | G5: =G37 -> 6412812 | H5: =H37 -> 6412812 | I5: =I37 -> 6412812 | J5: =J37 -> 6412812 | K5: =K37 -> 6412812 | L5: =L37 -> 6412812 | M5: =M37 -> 12825624 | N5: =N37 -> 12825624 | ... U5: =U37 -> 12825624
A6: 2 | B6: Share premium | G6: =F40 -> 0 | H6: =G40 -> 0 | I6: =H40 -> 0 | J6: =I40 -> 0 | K6: =K40 -> 0 | L6: =L40 -> 0 | M6: =M40 -> 0 | N6: =N40 -> 0 | O6: =O40 -> 0 | P6: =P40 -> 0 | Q6: =Q40 -> 0 | R6: =R40 -> 0 | ... U6: =U40 -> 0
A7: =A6+1 -> 3 | B7: Owner's other capital | G7: =F50 -> 0 | H7: =G50 -> 3209 | I7: =H50 -> 3209 | J7: =I50 -> 3209 | K7: =J50 -> 3209 | L7: =K50 -> 3209 | M7: =L50 -> 3209 | N7: =M50 -> 3209 | O7: =N50 -> 3209 | P7: =P50 -> 3409 | Q7: =Q50 -> 3409 | R7: =R50 -> 3409 | S7: =S50 -> 3409 | T7: =T50 -> 3409 | U7: =U50 -> 3409
A8: =A7+1 -> 4 | B8: Treasury shares | G8: =G57 -> 0 | H8: =H57 -> 0 | I8: =I57 -> 0 | J8: =J57 -> 0 | K8: =K57 -> 0 | L8: =L57 -> 0 | M8: =M57 -> 0 | N8: =N57 -> 0 | ... U8: =U57 -> 0
A9: =A8+1 -> 5 | B9: Differences upon asset revaluation | G9: =G64 -> 0 | H9: =H64 -> 0 | I9: =I64 -> 0 | J9: =J64 -> 0 | K9: =K64 -> 0 | L9: =L64 -> 0 | M9: =M64 -> 0 | N9: =N64 -> 0 | ... U9: =U64 -> 0
A10: =A9+1 -> 6 | B10: Foreign exchange differences | G10: =G71 -> 19114 | H10: =H71 -> 21099 | I10: =I71 -> 27273 | J10: =J71 -> 26865 | K10: =K71 -> 27339 | L10: =L71 -> 37136 | M10: =M71 -> 43954 | N10: =N71 -> 53776 | ... U10: =U71 -> 89863
A11: =A10+1 -> 7 | B11: Investment and development fund | G11: =G78 -> 1118963 | H11: =H78 -> 1130147 | I11: =I78 -> 1130373 | J11: =J78 -> 1122846 | K11: =K78 -> 1122241 | L11: =L78 -> 1122241 | M11: =M78 -> 1122241 | N11: =N78 -> 1181710 | ... U11: =U78 -> 1186744
A12: =A11+1 -> 8 | B12: Enterprise arrangement fund | G12: =G85 -> 0 | H12: =H85 -> 0 | I12: =I85 -> 0 | J12: =J85 -> 0 | K12: =K85 -> 0 | L12: =L85 -> 0 | M12: =M85 -> 0 | N12: =N85 -> 0 | ... U12: =U85 -> 0
A13: =A12+1 -> 9 | B13: Financial reserve fund | G13: =G92 -> 0 | H13: =H92 -> 0 | I13: =I92 -> 0 | J13: =J92 -> 0 | K13: =K92 -> 0 | L13: =L92 -> 0 | M13: =M92 -> 0 | N13: =N92 -> 0 | ... U13: =U92 -> 0
A14: =A13+1 -> 10 | B14: Other funds | G14: =G99 -> 5327 | H14: =H99 -> 5327 | I14: =I99 -> 0 | J14: =J99 -> 0 | K14: =K99 -> 0 | L14: =L99 -> 0 | M14: =M99 -> 0 | N14: =N99 -> 0 | ... U14: =U99 -> 0
A15: =A14+1 -> 11 | B15: Retained earnings | G15: =G28 -> 5823904 | H15: =H28 -> 7473778 | I15: =I28 -> 11231596 | J15: =J28 -> 12374499 | K15: =K28 -> 13655871 | L15: =L28 -> 15564896 | M15: =M28 -> 10217284 | N15: =N28 -> 9217801 | ... U15: =U28 -> 9146469.3
A16: 12 | B16: Non-controlling interest | G16: ='1BS'!G118 -> 1037160 | H16: ='1BS'!H118 -> 1065496 | I16: ='1BS'!I118 -> 1270984 | J16: ='1BS'!J118 -> 1275046 | K16: ='1BS'!K118 -> 1373313 | L16: ='1BS'!L118 -> 1450552 | M16: ='1BS'!M118 -> 1272846 | N16: ='1BS'!N118 -> 1154973 | O16: ='1BS'!O118 -> 1847031 | P16: =P132 -> 1674130.9 | Q16: =Q132 -> 1537643.1 | R16: =R132 -> 1441463.2 | S16: =S132 -> 1366336.7 | T16: =T132 -> 1313802.2 | U16: =U132 -> 1279025
B17: Total shareholder equity | D17: =SUM(D5:D15) -> 0 | E17: =SUM(E5:E15) -> 0 | F17: =SUM(F5:F15) -> 0 | G17: ='1BS'!G100 -> 14420526 | H17: ='1BS'!H100 -> 16111906 | I17: ='1BS'!I100 -> 20076247 | J17: ='1BS'!J100 -> 21215276 | K17: ='1BS'!K100 -> 22594786 | L17: ='1BS'!L100 -> 24590846 | M17: ='1BS'!M100 -> 25485158 | N17: ='1BS'!N100 -> 24437093 | O17: ='1BS'!O100 -> 22999815 | P17: =SUM(P5:P15) -> 20935671 | Q17: =SUM(Q5:Q15) -> 20860187 | R17: =SUM(R5:R15) -> 21206094 | S17: =SUM(S5:S15) -> 21652155 | T17: =SUM(T5:T15) -> 22341015 | U17: =SUM(U5:U15) -> 23252109
B18: Retained Earnings | C18: =C4 -> 2013 | D18: =D4 -> 2014 | E18: =E4 -> 2015 | F18: =F4 -> 2016 | G18: 2017 | H18: 2018 | I18: 2019 | J18: 2020 | K18: 2021 | L18: 2022 | M18: 2023 | N18: 2024 | O18: 2025 | P18: =P4 -> 2026 | Q18: =Q4 -> 2027 | R18: =R4 -> 2028 | S18: =S4 -> 2029 | T18: =T4 -> 2030 | U18: =U4 -> 2031
A19: 11 | B19: Beginning balance | G19: ='1BS'!F115 -> 3852925 | H19: ='1BS'!G115 -> 5823904 | I19: =H28 -> 7473778 | J19: =I28 -> 11231596 | K19: =J28 -> 12374499 | L19: =K28 -> 13655871 | M19: =L28 -> 15564896 | N19: =M28 -> 10217284 | O19: =N28 -> 9217801 | P19: =O28 -> 7047144 | ... U19: =T28 -> 8235374.9
B20: Profit for the year | G20: ='1IS'!F23 -> 4477972 | H20: ='1IS'!G23 -> 4711485 | I20: ='1IS'!H23 -> 4177432 | J20: ='1IS'!I23 -> 5053364 | K20: ='1IS'!J23 -> 4723497 | L20: ='1IS'!K23 -> 3677252 | M20: ='1IS'!L23 -> 5223851 | N20: ='1IS'!M23 -> 4117605 | O20: ='1IS'!N23 -> 4330113 | P20: ='1IS'!P23 -> 4399449.4 | Q20: ='1IS'!Q23 -> 4545308.3 | R20: ='1IS'!R23 -> 4979285.5 | S20: ='1IS'!S23 -> 5082431.6 | T20: ='1IS'!T23 -> 5332482.4 | U20: ='1IS'!U23 -> 5561354.6
B21: Transfer to funds | G21: =SUM(G22:G24) -> -565 | H21: =SUM(H22:H24) -> -404985 | I21: =SUM(I22:I24) -> -260747 | J21: =SUM(J22:J24) -> -322868 | K21: =SUM(K22:K24) -> -170112 | L21: =SUM(L22:L24) -> -170371 | M21: =SUM(M22:M24) -> -121347 | N21: =SUM(N22:N24) -> -201885 | ... U21: =SUM(U22:U24) -> -161291.77
B22: Investment & Development fund | G22: =-G76 -> -565 | H22: =-H76 -> -11184 | I22: =-I76 -> -226 | J22: =-J76 -> 0 | K22: =-K76 -> 0 | L22: =-L76 -> 0 | M22: =-M76 -> 0 | N22: =-N76 -> -59469 | ... U22: =-U76 -> 0
B23: Financial Reserve (10% chartered) | I23: =I90 -> 0 | J23: =J90 -> 0 | K23: =K90 -> 0 | L23: =L90 -> 0 | M23: =M90 -> 0 | N23: =N90 -> 0 | O23: =O90 -> 0 | P23: =P90 -> 0 | ... U23: =U90 -> 0
B24: Bonus funds | G24: =-F105 -> 0 | H24: =-G105 -> -393801 | I24: =-H105 -> -260521 | J24: =-I105 -> -322868 | K24: =-J105 -> -170112 | L24: =-K105 -> -170371 | M24: =-L105 -> -121347 | N24: =-M105 -> -142416 | O24: =-N105 -> -125583 | P24: =-P105 -> -127593.91 | Q24: =-Q105 -> -131824.15 | R24: =-R105 -> -144410.46 | S24: =-S105 -> -147401.93 | T24: =-T105 -> -154653.96 | U24: =-U105 -> -161291.77
B25: Dividend payment | G25: =CF!K47 -> -1008865 | H25: =CF!L47 -> -3888749 | I25: =CF!M47 -> -1136965 | J25: =CF!N47 -> -3734027 | K25: =CF!O47 -> -1096307 | L25: =CF!P47 -> -2418865 | M25: =CF!Q47 -> -3354093 | N25: =CF!R47 -> -4658550 | O25: =CF!S47 -> -6512668 | P25: =-P34*P113 -> -4488968.4 | Q25: =-Q34*Q113 -> -4488968.4 | R25: =-R34*R113 -> -4488968.4 | S25: =-S34*S113 -> -4488968.4 | T25: =-T34*T113 -> -4488968.4 | U25: =-U34*U113 -> -4488968.4
B26: Increase chartered capital | G26: =-G35 -> 0 | H26: =-H35 -> 0 | I26: =-I35 -> 0 | J26: =-J35 -> 0 | K26: 0 | L26: 0 | M26: 0 | N26: =-N35 -> 0 | O26: 0 | P26: 0 | Q26: 0 | R26: 0 | S26: 0 | T26: 0 | U26: 0
B27: Others | H27: -39 | I27: -41 | J27: -43 | K27: 116 | L27: 18 | M27: 12 | N27: -44 | O27: =O28-SUM(O19:O26) -> 273132 | P27: 0 | Q27: 0 | R27: 0 | S27: 0 | T27: 0 | U27: 0
B28: Ending balance | E28: =SUM(E19:E21,E25:E27) -> 0 | F28: =SUM(F19:F21,F25:F27) -> 0 | G28: ='1BS'!G115 -> 5823904 | H28: ='1BS'!H115 -> 7473778 | I28: ='1BS'!I115 -> 11231596 | J28: ='1BS'!J115 -> 12374499 | K28: ='1BS'!K115 -> 13655871 | L28: ='1BS'!L115 -> 15564896 | M28: ='1BS'!M115 -> 10217284 | N28: ='1BS'!N115 -> 9217801 | O28: ='1BS'!O115 -> 7047144 | P28: =SUM(P19:P21,P25:P27) -> 6830031.1 | Q28: =SUM(Q19:Q21,Q25:Q27) -> 6754546.9 | R28: =SUM(R19:R21,R25:R27) -> 7100453.6 | S28: =SUM(S19:S21,S25:S27) -> 7546514.9 | T28: =SUM(T19:T21,T25:T27) -> 8235374.9 | U28: =SUM(U19:U21,U25:U27) -> 9146469.3
B32: Detailed Calculation | C32: =C4 -> 2013 | D32: 2014 | E32: 2015 | F32: 2016 | G32: 2017 | H32: 2018 | I32: =I18 -> 2019 | J32: =J18 -> 2020 | K32: =K18 -> 2021 | L32: =L18 -> 2022 | M32: =M18 -> 2023 | N32: =N18 -> 2024 | O32: =O18 -> 2025 | P32: =P18 -> 2026 | ... T32: =T18 -> 2030 | U32: 2030
A33: 1 | B33: Chartered capital
B34: Beginning balance | G34: ='1BS'!F102 -> 6412812 | H34: ='1BS'!G102 -> 6412812 | I34: ='1BS'!H102 -> 6412812 | J34: ='1BS'!I102 -> 6412812 | K34: ='1BS'!J102 -> 6412812 | L34: ='1BS'!K102 -> 6412812 | M34: ='1BS'!L102 -> 6412812 | N34: ='1BS'!M102 -> 12825624 | O34: ='1BS'!N102 -> 12825624 | P34: =O37 -> 12825624 | Q34: =P37 -> 12825624 | R34: =Q37 -> 12825624 | S34: =R37 -> 12825624 | T34: =S37 -> 12825624 | U34: =T37 -> 12825624
B35: New capital | H35: 0 | I35: 0 | J35: 0 | K35: 0 | L35: 0 | M35: 6412812 | N35: 0 | O35: 0 | P35: 0 | Q35: 0 | R35: 0 | S35: 0 | T35: 0 | U35: 0
B36: Bonus/Right issue | I36: 0 | J36: 0 | K36: 0 | L36: 0 | M36: 0 | N36: 0 | O36: 0 | P36: 0 | Q36: 0 | R36: 0 | S36: 0 | T36: 0 | U36: 0
B37: Ending balance | G37: =SUM(G34:G36) -> 6412812 | H37: =SUM(H34:H36) -> 6412812 | I37: =SUM(I34:I36) -> 6412812 | J37: =SUM(J34:J36) -> 6412812 | K37: =SUM(K34:K36) -> 6412812 | L37: =SUM(L34:L36) -> 6412812 | M37: =SUM(M34:M36) -> 12825624 | N37: =SUM(N34:N36) -> 12825624 | ... U37: =SUM(U34:U36) -> 12825624
G38: ='1BS'!G103-Equity!G37 -> 0 | H38: ='1BS'!H103-Equity!H37 -> 0 | I38: ='1BS'!I103-Equity!I37 -> 0 | J38: ='1BS'!J103-Equity!J37 -> 0 | K38: ='1BS'!K103-Equity!K37 -> 0 | L38: ='1BS'!L103-Equity!L37 -> 0 | M38: ='1BS'!M103-Equity!M37 -> 0 | N38: ='1BS'!N103-Equity!N37 -> 0 | ... U38: ='1BS'!U103-Equity!U37 -> 0
A39: 2 | B39: Share premium
B40: Beginning balance | G40: ='1BS'!E105 -> 0 | H40: ='1BS'!F105 -> 0 | I40: ='1BS'!G105 -> 0 | J40: ='1BS'!H105 -> 0 | K40: ='1BS'!I105 -> 0 | L40: ='1BS'!J105 -> 0 | M40: ='1BS'!K105 -> 0 | N40: ='1BS'!L105 -> 0 | O40: ='1BS'!M105 -> 0 | P40: =O43 -> 0 | Q40: =P43 -> 0 | R40: =Q43 -> 0 | S40: =R43 -> 0 | T40: =S43 -> 0 | U40: =T43 -> 0
B41: Increase | G41: ='1BS'!I105 -> 0 | H41: ='1BS'!J105 -> 0 | I41: ='1BS'!K105 -> 0 | J41: ='1BS'!L105 -> 0 | K41: ='1BS'!M105 -> 0 | L41: ='1BS'!N105 -> 0 | M41: ='1BS'!O105 -> 0 | N41: ='1BS'!P105 -> 0 | O41: ='1BS'!Q105 -> 0 | P41: 0 | Q41: 0 | R41: 0 | S41: 0 | T41: 0 | U41: 0
B42: Decrease | G42: ='1BS'!E105 -> 0 | H42: ='1BS'!F105 -> 0 | I42: ='1BS'!G105 -> 0 | J42: ='1BS'!H105 -> 0 | K42: ='1BS'!I105 -> 0 | L42: ='1BS'!J105 -> 0 | M42: ='1BS'!K105 -> 0 | N42: ='1BS'!L105 -> 0 | O42: ='1BS'!M105 -> 0 | P42: 0 | Q42: 0 | R42: 0 | S42: 0 | T42: 0 | U42: 0
B43: Ending balance | G43: =SUM(G40:G42) -> 0 | H43: =SUM(H40:H42) -> 0 | I43: =SUM(I40:I42) -> 0 | J43: =SUM(J40:J42) -> 0 | K43: =SUM(K40:K42) -> 0 | L43: =SUM(L40:L42) -> 0 | M43: =SUM(M40:M42) -> 0 | N43: =SUM(N40:N42) -> 0 | ... U43: =SUM(U40:U42) -> 0
P44: ='1BS'!P105-P43 -> 0 | Q44: ='1BS'!Q105-Q43 -> 0 | R44: ='1BS'!R105-R43 -> 0 | S44: ='1BS'!S105-S43 -> 0 | T44: ='1BS'!T105-T43 -> 0 | U44: ='1BS'!U105-U43 -> 0
A46: 3 | B46: Owner's other capital
B47: Beginning balance | G47: ='1BS'!E107 -> 3209 | H47: ='1BS'!F107 -> 3209 | I47: ='1BS'!G107 -> 3209 | J47: ='1BS'!H107 -> 3209 | K47: ='1BS'!I107 -> 3209 | L47: ='1BS'!J107 -> 3209 | M47: ='1BS'!K107 -> 3209 | N47: ='1BS'!L107 -> 3209 | O47: ='1BS'!M107 -> 3209 | P47: =O50 -> 3409 | Q47: =P50 -> 3409 | R47: =Q50 -> 3409 | S47: =R50 -> 3409 | T47: =S50 -> 3409 | U47: =T50 -> 3409
B48: Increase | G48: 0 | H48: 0 | I48: 0 | J48: 0 | K48: 0 | L48: 0 | M48: 0 | N48: 0 | O48: 200 | P48: 0 | Q48: 0 | R48: 0 | S48: 0 | T48: 0 | U48: 0
B49: Decrease | G49: 0 | H49: 0 | I49: 0 | J49: 0 | K49: 0 | M49: 0 | N49: 0 | O49: 0 | P49: 0 | Q49: 0 | R49: 0 | S49: 0 | T49: 0 | U49: 0
B50: Ending balance | G50: =SUM(G47:G49) -> 3209 | H50: =SUM(H47:H49) -> 3209 | I50: =SUM(I47:I49) -> 3209 | J50: =SUM(J47:J49) -> 3209 | K50: =SUM(K47:K49) -> 3209 | L50: =SUM(L47:L49) -> 3209 | M50: =SUM(M47:M49) -> 3209 | N50: =SUM(N47:N49) -> 3209 | ... U50: =SUM(U47:U49) -> 3409
G51: ='1BS'!G107-Equity!G50 -> 0 | H51: ='1BS'!H107-Equity!H50 -> 0 | I51: ='1BS'!I107-Equity!I50 -> 0 | J51: ='1BS'!J107-Equity!J50 -> 0 | K51: ='1BS'!K107-Equity!K50 -> 0 | L51: ='1BS'!L107-Equity!L50 -> 0 | M51: ='1BS'!M107-Equity!M50 -> 0 | N51: ='1BS'!N107-Equity!N50 -> 0 | ... U51: ='1BS'!U107-Equity!U50 -> 0
A53: 4 | B53: Treasury stock
B54: Beginning balance | G54: ='1BS'!F108 -> -23450 | H54: ='1BS'!G108 -> 0 | I54: ='1BS'!H108 -> 0 | J54: ='1BS'!I108 -> 0 | K54: ='1BS'!J108 -> 0 | L54: ='1BS'!K108 -> 0 | M54: ='1BS'!L108 -> 0 | N54: ='1BS'!M108 -> 0 | O54: ='1BS'!N108 -> 0 | P54: =O57 -> 0 | Q54: =P57 -> 0 | R54: =Q57 -> 0 | S54: =R57 -> 0 | T54: =S57 -> 0 | U54: =T57 -> 0
B55: Increase | G55: 0 | H55: 0 | I55: 0 | J55: 0 | K55: 0 | L55: 0 | M55: 0 | N55: 0 | O55: 0 | Q55: 0 | R55: 0 | S55: 0 | T55: 0 | U55: 0
B56: Decrease | G56: 23450 | H56: 0 | I56: 0 | J56: 0 | K56: 0 | L56: 0 | M56: 0 | N56: 0 | O56: 0 | P56: 0 | Q56: 0 | R56: 0 | S56: 0 | T56: 0 | U56: 0
B57: Ending balance | G57: =SUM(G54:G56) -> 0 | H57: =SUM(H54:H56) -> 0 | I57: =SUM(I54:I56) -> 0 | J57: =SUM(J54:J56) -> 0 | K57: =SUM(K54:K56) -> 0 | L57: =SUM(L54:L56) -> 0 | M57: =SUM(M54:M56) -> 0 | N57: =SUM(N54:N56) -> 0 | ... U57: =SUM(U54:U56) -> 0
G58: ='1BS'!G108-G57 -> 0 | H58: ='1BS'!H108-H57 -> 0 | I58: ='1BS'!I108-I57 -> 0 | J58: ='1BS'!J108-J57 -> 0 | K58: ='1BS'!K108-K57 -> 0 | L58: ='1BS'!L108-L57 -> 0 | M58: ='1BS'!M108-M57 -> 0 | N58: ='1BS'!N108-N57 -> 0 | ... U58: ='1BS'!U108-U57 -> 0
A60: 5 | B60: Differences upon asset revaluation
B61: Beginning balance | G61: ='1BS'!E109 -> 0 | H61: ='1BS'!F109 -> 0 | I61: ='1BS'!G109 -> 0 | J61: ='1BS'!H109 -> 0 | K61: ='1BS'!I109 -> 0 | L61: ='1BS'!J109 -> 0 | M61: ='1BS'!K109 -> 0 | N61: ='1BS'!L109 -> 0 | O61: ='1BS'!M109 -> 0 | P61: =O64 -> 0 | Q61: =P64 -> 0 | R61: =Q64 -> 0 | S61: =R64 -> 0 | T61: =S64 -> 0 | U61: =T64 -> 0
B62: Increase | G62: 0 | H62: 0 | I62: 0 | J62: 0 | K62: 0 | L62: 0 | M62: 0 | N62: 0 | O62: 0 | Q62: 0 | R62: 0 | S62: 0 | T62: 0 | U62: 0
B63: Decrease | G63: 0 | H63: 0 | I63: 0 | J63: 0 | K63: 0 | L63: 0 | M63: 0 | N63: 0 | O63: 0 | P63: 0 | Q63: 0 | R63: 0 | S63: 0 | T63: 0 | U63: 0
B64: Ending balance | G64: =SUM(G61:G63) -> 0 | H64: =SUM(H61:H63) -> 0 | I64: =SUM(I61:I63) -> 0 | J64: =SUM(J61:J63) -> 0 | K64: =SUM(K61:K63) -> 0 | L64: =SUM(L61:L63) -> 0 | M64: =SUM(M61:M63) -> 0 | N64: =SUM(N61:N63) -> 0 | ... U64: =SUM(U61:U63) -> 0
G65: ='1BS'!G109-Equity!G64 -> 0 | H65: ='1BS'!H109-Equity!H64 -> 0 | I65: ='1BS'!I109-Equity!I64 -> 0 | J65: ='1BS'!J109-Equity!J64 -> 0 | K65: ='1BS'!K109-Equity!K64 -> 0 | L65: ='1BS'!L109-Equity!L64 -> 0 | M65: ='1BS'!M109-Equity!M64 -> 0 | N65: ='1BS'!N109-Equity!N64 -> 0 | ... U65: ='1BS'!U109-Equity!U64 -> 0
A67: 6 | B67: Foreign exchange differences
B68: Beginning balance | G68: ='1BS'!F110 -> 17007 | H68: ='1BS'!G110 -> 19114 | I68: ='1BS'!H110 -> 21099 | J68: ='1BS'!I110 -> 27273 | K68: ='1BS'!J110 -> 26865 | L68: ='1BS'!K110 -> 27339 | M68: ='1BS'!L110 -> 37136 | N68: ='1BS'!M110 -> 43954 | O68: ='1BS'!N110 -> 53776 | P68: =O71 -> 89863 | Q68: =P71 -> 89863 | R68: =Q71 -> 89863 | S68: =R71 -> 89863 | T68: =S71 -> 89863 | U68: =T71 -> 89863
B69: Increase | G69: =G71-G68 -> 2107 | H69: =H71-H68 -> 1985 | I69: =I71-I68 -> 6174 | J69: 0 | K69: =K71-K68 -> 474 | L69: =L71-L68 -> 9797 | M69: =M71-M68 -> 6818 | N69: =N71-N68 -> 9822 | O69: =O71-O68 -> 36087 | P69: 0 | Q69: 0 | R69: 0 | S69: 0 | T69: 0 | U69: 0
B70: Decrease | G70: 0 | H70: 0 | I70: 0 | J70: =J71-J68 -> -408 | K70: 0 | L70: 0 | M70: 0 | N70: 0 | O70: 0 | P70: 0 | Q70: 0 | R70: 0 | S70: 0 | T70: 0 | U70: 0
B71: Ending balance | G71: ='1BS'!G110 -> 19114 | H71: ='1BS'!H110 -> 21099 | I71: ='1BS'!I110 -> 27273 | J71: ='1BS'!J110 -> 26865 | K71: ='1BS'!K110 -> 27339 | L71: ='1BS'!L110 -> 37136 | M71: ='1BS'!M110 -> 43954 | N71: ='1BS'!N110 -> 53776 | O71: ='1BS'!O110 -> 89863 | P71: =SUM(P68:P70) -> 89863 | Q71: =SUM(Q68:Q70) -> 89863 | R71: =SUM(R68:R70) -> 89863 | S71: =SUM(S68:S70) -> 89863 | T71: =SUM(T68:T70) -> 89863 | U71: =SUM(U68:U70) -> 89863
G72: ='1BS'!G110-Equity!G71 -> 0 | H72: ='1BS'!H110-Equity!H71 -> 0 | I72: ='1BS'!I110-Equity!I71 -> 0 | J72: ='1BS'!J110-Equity!J71 -> 0 | K72: ='1BS'!K110-Equity!K71 -> 0 | L72: ='1BS'!L110-Equity!L71 -> 0 | M72: ='1BS'!M110-Equity!M71 -> 0 | N72: ='1BS'!N110-Equity!N71 -> 0 | ... U72: ='1BS'!U110-Equity!U71 -> 0
A74: 7 | B74: Investment & development Fund
B75: Beginning balance | G75: ='1BS'!F111 -> 1118398 | H75: ='1BS'!G111 -> 1118963 | I75: ='1BS'!H111 -> 1130147 | J75: ='1BS'!I111 -> 1130373 | K75: ='1BS'!J111 -> 1122846 | L75: ='1BS'!K111 -> 1122241 | M75: ='1BS'!L111 -> 1122241 | N75: ='1BS'!M111 -> 1122241 | O75: ='1BS'!N111 -> 1181710 | P75: =O78 -> 1186744 | Q75: =P78 -> 1186744 | R75: =Q78 -> 1186744 | S75: =R78 -> 1186744 | T75: =S78 -> 1186744 | U75: =T78 -> 1186744
B76: Increase | G76: =G78-G75 -> 565 | H76: =H78-H75 -> 11184 | I76: =I78-I75 -> 226 | J76: 0 | K76: 0 | L76: =L78-L75 -> 0 | M76: =M78-M75 -> 0 | N76: =N78-N75 -> 59469 | O76: =O78-O75 -> 5034 | P76: 0 | Q76: 0 | R76: 0 | S76: 0 | T76: 0 | U76: 0
B77: Decrease | G77: 0 | J77: =J78-J75 -> -7527 | K77: =K78-K75 -> -605 | L77: =L78-L75 -> 0 | M77: =M78-M75 -> 0 | N77: 0 | O77: 0 | P77: 0 | Q77: 0 | R77: 0 | S77: 0 | T77: 0 | U77: 0
B78: Ending balance | G78: ='1BS'!G111 -> 1118963 | H78: ='1BS'!H111 -> 1130147 | I78: ='1BS'!I111 -> 1130373 | J78: ='1BS'!J111 -> 1122846 | K78: ='1BS'!K111 -> 1122241 | L78: ='1BS'!L111 -> 1122241 | M78: ='1BS'!M111 -> 1122241 | N78: ='1BS'!N111 -> 1181710 | O78: ='1BS'!O111 -> 1186744 | P78: =SUM(P75:P77) -> 1186744 | Q78: =SUM(Q75:Q77) -> 1186744 | R78: =SUM(R75:R77) -> 1186744 | S78: =SUM(S75:S77) -> 1186744 | T78: =SUM(T75:T77) -> 1186744 | U78: =SUM(U75:U77) -> 1186744
G79: =G78-'1BS'!G111 -> 0 | H79: =H78-'1BS'!H111 -> 0 | I79: =I78-'1BS'!I111 -> 0 | J79: =J78-'1BS'!J111 -> 0 | K79: =K78-'1BS'!K111 -> 0 | L79: =L78-'1BS'!L111 -> 0 | M79: =M78-'1BS'!M111 -> 0 | N79: =N78-'1BS'!N111 -> 0 | ... U79: =U78-'1BS'!U111 -> 0
A81: 8 | B81: Enterprise arrangement fund
B82: Beginning balance | G82: ='1BS'!F112 -> 0 | H82: ='1BS'!G112 -> 0 | I82: ='1BS'!H112 -> 0 | J82: ='1BS'!I112 -> 0 | K82: ='1BS'!J112 -> 0 | L82: ='1BS'!K112 -> 0 | M82: ='1BS'!L112 -> 0 | N82: ='1BS'!M112 -> 0 | O82: ='1BS'!N112 -> 0 | P82: =O85 -> 0 | Q82: =P85 -> 0 | R82: =Q85 -> 0 | S82: =R85 -> 0 | T82: =S85 -> 0 | U82: =T85 -> 0
B83: Increase | G83: =G85-G82 -> 0 | H83: =H85-H82 -> 0 | I83: =I85-I82 -> 0 | J83: =J85-J82 -> 0 | K83: =K85-K82 -> 0 | L83: =L85-L82 -> 0 | M83: =M85-M82 -> 0 | N83: =N85-N82 -> 0 | O83: =O85-O82 -> 0 | P83: =AVERAGE(M83:O83) -> 0 | Q83: =AVERAGE(N83:P83) -> 0 | R83: =AVERAGE(O83:Q83) -> 0 | S83: =AVERAGE(P83:R83) -> 0 | T83: =AVERAGE(Q83:S83) -> 0 | U83: =AVERAGE(R83:T83) -> 0
B84: Decrease | G84: =G82-G85 -> 0 | H84: =H82-H85 -> 0 | I84: =I82-I85 -> 0 | J84: =J82-J85 -> 0 | K84: =K82-K85 -> 0 | L84: =L82-L85 -> 0 | M84: =M82-M85 -> 0 | N84: =N82-N85 -> 0 | O84: =O82-O85 -> 0 | P84: 0 | Q84: 0 | R84: 0 | S84: 0 | T84: 0 | U84: 0
B85: Ending balance | G85: ='1BS'!G112 -> 0 | H85: ='1BS'!H112 -> 0 | I85: ='1BS'!I112 -> 0 | J85: ='1BS'!J112 -> 0 | K85: ='1BS'!K112 -> 0 | L85: ='1BS'!L112 -> 0 | M85: ='1BS'!M112 -> 0 | N85: ='1BS'!N112 -> 0 | O85: ='1BS'!O112 -> 0 | P85: =SUM(P82:P84) -> 0 | Q85: =SUM(Q82:Q84) -> 0 | R85: =SUM(R82:R84) -> 0 | S85: =SUM(S82:S84) -> 0 | T85: =SUM(T82:T84) -> 0 | U85: =SUM(U82:U84) -> 0
G86: =G85-'1BS'!G112 -> 0 | H86: =H85-'1BS'!H112 -> 0 | I86: =I85-'1BS'!I112 -> 0 | J86: =J85-'1BS'!J112 -> 0 | K86: =K85-'1BS'!K112 -> 0 | L86: =L85-'1BS'!L112 -> 0 | M86: =M85-'1BS'!M112 -> 0 | N86: =N85-'1BS'!N112 -> 0 | ... U86: =U85-'1BS'!U112 -> 0
A88: 9 | B88: Financial reserve (Max 10% chartered)
B89: Beginning balance | G89: ='1BS'!F113 -> 0 | H89: ='1BS'!G113 -> 0 | I89: ='1BS'!H113 -> 0 | J89: ='1BS'!I113 -> 0 | K89: ='1BS'!J113 -> 0 | L89: ='1BS'!K113 -> 0 | M89: ='1BS'!L113 -> 0 | N89: ='1BS'!M113 -> 0 | O89: ='1BS'!N113 -> 0 | P89: =O92 -> 0 | Q89: =P92 -> 0 | R89: =Q92 -> 0 | S89: =R92 -> 0 | T89: =S92 -> 0 | U89: =T92 -> 0
B90: Increase | G90: =G92-G89 -> 0 | H90: =H92-H89 -> 0 | I90: =I92-I89 -> 0 | J90: =J92-J89 -> 0 | K90: =K92-K89 -> 0 | L90: =L92-L89 -> 0 | M90: =M92-M89 -> 0 | N90: =N92-N89 -> 0 | O90: =O92-O89 -> 0 | P90: =MIN(P34*10%-P89,P$20*P116) -> 0 | Q90: =MIN(Q34*10%-Q89,Q$20*Q116) -> 0 | R90: =MIN(R34*10%-R89,R$20*R116) -> 0 | S90: =MIN(S34*10%-S89,S$20*S116) -> 0 | T90: =MIN(T34*10%-T89,T$20*T116) -> 0 | U90: =MIN(U34*10%-U89,U$20*U116) -> 0
B91: Decrease | G91: =G92-G89 -> 0 | H91: =H92-H89 -> 0 | I91: =I92-I89 -> 0 | J91: =J92-J89 -> 0 | K91: =K92-K89 -> 0 | L91: =L92-L89 -> 0 | M91: =M92-M89 -> 0 | N91: =N92-N89 -> 0 | O91: =O92-O89 -> 0 | P91: 0 | Q91: 0 | R91: 0 | S91: 0 | T91: 0 | U91: 0
B92: Ending balance | G92: ='1BS'!G113 -> 0 | H92: ='1BS'!H113 -> 0 | I92: ='1BS'!I113 -> 0 | J92: ='1BS'!J113 -> 0 | K92: ='1BS'!K113 -> 0 | L92: ='1BS'!L113 -> 0 | M92: ='1BS'!M113 -> 0 | N92: ='1BS'!N113 -> 0 | O92: ='1BS'!O113 -> 0 | P92: 0 | Q92: 0 | R92: 0 | S92: 0 | T92: 0 | U92: 0
G93: =G92-'1BS'!G113 -> 0 | H93: =H92-'1BS'!H113 -> 0 | I93: =I92-'1BS'!I113 -> 0 | J93: =J92-'1BS'!J113 -> 0 | K93: =K92-'1BS'!K113 -> 0 | L93: =L92-'1BS'!L113 -> 0 | M93: =M92-'1BS'!M113 -> 0 | N93: =N92-'1BS'!N113 -> 0 | ... U93: =U92-'1BS'!U113 -> 0
A95: 10 | B95: Others
B96: Beginning balance | G96: ='1BS'!F114 -> 6041 | H96: ='1BS'!G114 -> 5327 | I96: ='1BS'!H114 -> 5327 | J96: ='1BS'!I114 -> 0 | K96: ='1BS'!J114 -> 0 | L96: ='1BS'!K114 -> 0 | M96: ='1BS'!L114 -> 0 | N96: ='1BS'!M114 -> 0 | O96: ='1BS'!N114 -> 0 | P96: =O99 -> 0 | Q96: =P99 -> 0 | R96: =Q99 -> 0 | S96: =R99 -> 0 | T96: =S99 -> 0 | U96: =T99 -> 0
B97: Increase | G97: 0 | H97: 0 | I97: 0 | J97: 0 | K97: 0 | L97: 0 | M97: 0 | N97: 0 | O97: 0 | P97: =MIN(P41*10%-P96,P$20*P123) -> 0 | Q97: =MIN(Q41*10%-Q96,Q$20*Q123) -> 0 | R97: =MIN(R41*10%-R96,R$20*R123) -> 0 | S97: =MIN(S41*10%-S96,S$20*S123) -> 0 | T97: =MIN(T41*10%-T96,T$20*T123) -> 0 | U97: =MIN(U41*10%-U96,U$20*U123) -> 0
B98: Decrease | G98: =G99-G96 -> -714 | H98: =H99-H96 -> 0 | I98: =I99-I96 -> -5327 | J98: =J99-J96 -> 0 | K98: =K99-K96 -> 0 | L98: =L99-L96 -> 0 | M98: =M99-M96 -> 0 | N98: =N99-N96 -> 0 | O98: =O99-O96 -> 0 | P98: 0 | Q98: 0 | R98: 0 | S98: 0 | T98: 0 | U98: 0
B99: Ending balance | G99: ='1BS'!G114 -> 5327 | H99: ='1BS'!H114 -> 5327 | I99: ='1BS'!I114 -> 0 | J99: ='1BS'!J114 -> 0 | K99: ='1BS'!K114 -> 0 | L99: ='1BS'!L114 -> 0 | M99: ='1BS'!M114 -> 0 | N99: ='1BS'!N114 -> 0 | O99: ='1BS'!O114 -> 0 | P99: 0 | Q99: 0 | R99: 0 | S99: 0 | T99: 0 | U99: 0
G100: ='1BS'!G114-G99 -> 0 | H100: ='1BS'!H114-H99 -> 0 | I100: ='1BS'!I114-I99 -> 0 | J100: ='1BS'!J114-J99 -> 0 | K100: ='1BS'!K114-K99 -> 0 | L100: ='1BS'!L114-L99 -> 0 | M100: ='1BS'!M114-M99 -> 0 | N100: ='1BS'!N114-N99 -> 0 | ... U100: ='1BS'!U114-U99 -> 0
B102: Non-equity funds
B103: Bonus fund
B104: Beginning balance | G104: ='1BS'!F82 -> 330525 | H104: =G107 -> 296743 | I104: =H107 -> 222305 | J104: =I107 -> 294925 | K104: =J107 -> 183521 | L104: =K107 -> 238251 | M104: =L107 -> 222390 | N104: =M107 -> 194370 | O104: =N107 -> 199419 | ... U104: =T107 -> 287925.05
B105: Increase | G105: =317017+76784 -> 393801 | H105: =231462+29059 -> 260521 | I105: =290010+32858 -> 322868 | J105: 170112 | K105: 170371 | L105: 121347 | M105: =116321+26095 -> 142416 | N105: 125583 | O105: =150126+2378+13003 -> 165507 | P105: =P117*P20 -> 127593.91 | Q105: =Q117*Q20 -> 131824.15 | R105: =R117*R20 -> 144410.46 | S105: =S117*S20 -> 147401.93 | T105: =T117*T20 -> 154653.96 | U105: =U117*U20 -> 161291.77
B106: Decrease | G106: -427583 | H106: -334959 | I106: -250238 | J106: =-224031-57485 -> -281516 | K106: =-106944-8696 -> -115640 | L106: =-(96498+40710) -> -137208 | M106: -170436 | N106: =-115823-4711 -> -120534 | O106: =-133609 -> -133609 | P106: =-P119*SUM(P104:P105) -> -118547.56 | Q106: =-Q119*SUM(Q104:Q105) -> -122932.78 | R106: =-R119*SUM(R104:R105) -> -130026.8 | S106: =-S119*SUM(S104:S105) -> -135765.75 | T106: =-T119*SUM(T104:T105) -> -142004.47 | U106: =-U119*SUM(U104:U105) -> -148375.01
B107: Ending balance | G107: ='1BS'!G82 -> 296743 | H107: ='1BS'!H82 -> 222305 | I107: ='1BS'!I82 -> 294925 | J107: ='1BS'!J82 -> 183521 | K107: ='1BS'!K82 -> 238251 | L107: ='1BS'!L82 -> 222390 | M107: ='1BS'!M82 -> 194370 | N107: ='1BS'!N82 -> 199419 | O107: ='1BS'!O82 -> 231318 | P107: =SUM(P104:P106) -> 240364.35 | Q107: =SUM(Q104:Q106) -> 249255.71 | R107: =SUM(R104:R106) -> 263639.38 | S107: =SUM(S104:S106) -> 275275.56 | T107: =SUM(T104:T106) -> 287925.05 | U107: =SUM(U104:U106) -> 300841.8
P108: ='1BS'!P82-Equity!P107 -> 0 | Q108: ='1BS'!Q82-Equity!Q107 -> 0 | R108: ='1BS'!R82-Equity!R107 -> 0 | S108: ='1BS'!S82-Equity!S107 -> 0 | T108: ='1BS'!T82-Equity!T107 -> 0 | U108: ='1BS'!U82-Equity!U107 -> 0
B111: Equity Assumption | D111: =D32 -> 2014 | E111: =E32 -> 2015 | F111: =F32 -> 2016 | G111: =G32 -> 2017 | H111: =H32 -> 2018 | I111: =I32 -> 2019 | J111: =J32 -> 2020 | K111: =K32 -> 2021 | ... S111: =S32 -> 2029 | T111: =S111+1 -> 2030 | U111: =T111+1 -> 2031
B112: Dividend Payout Ratio | H112: =-H25/H20 -> 0.8253765 | I112: =-I25/I20 -> 0.2721684 | J112: =-J25/J20 -> 0.73891906 | K112: =-K25/K20 -> 0.23209647 | L112: =-L25/L20 -> 0.65779147 | M112: =-M25/M20 -> 0.64207287 | N112: =-N25/N20 -> 1.1313737 | O112: =-O25/O20 -> 1.5040411 | ... U112: =-U25/U20 -> 0.80717176
B113: Dividend Ratio (per face value) | P113: 0.35 | Q113: 0.35 | R113: 0.35 | S113: 0.35 | T113: 0.35 | U113: 0.35
B114: Transfer to funds (% NPAT)
...

Sheet Report
N3: =N7/M7-1 -> 0.046322609
B5: Statement of financial position | L5: Statement of comprehensive income
B6: Year to Dec. (bn VND) | C6: 2023 | D6: 2024 | E6: 2025 | F6: 2026F | G6: 2027F | H6: 2028F | I6: 2029F | J6: 2030F | L6: Year to Dec. (bn VND) | M6: =C6 -> 2023 | N6: =D6 -> 2024 | O6: =E6 -> 2025 | P6: =F6 -> 2026F | Q6: =G6 -> 2027F | R6: =H6 -> 2028F | S6: =I6 -> 2029F | T6: 2030F
B7: Total assets | C7: =SUM(C8,C14) -> 34056625 | D7: =SUM(D8,D14) -> 33439407 | E7: =SUM(E8,E14) -> 32597354 | F7: =SUM(F8,F14) -> 31392670 | G7: =SUM(G8,G14) -> 31025233 | H7: =SUM(H8,H14) -> 31831627 | I7: =SUM(I8,I14) -> 32298620 | J7: =SUM(J8,J14) -> 33326358 | K7: =C7-SUM(C8,C14) -> 0 | L7: Net Revenue | M7: ='1IS'!M3 -> 30461367 | N7: ='1IS'!N3 -> 31872417 | O7: ='1IS'!O3 -> 25888192 | P7: ='1IS'!P3 -> 27013433 | Q7: ='1IS'!Q3 -> 27701284 | R7: ='1IS'!R3 -> 28968445 | S7: ='1IS'!S3 -> 29683645 | T7: ='1IS'!T3 -> 30867609
B8: Current assets | C8: ='1BS'!M3 -> 26553406 | D8: ='1BS'!N3 -> 25066733 | E8: ='1BS'!O3 -> 22140978 | F8: ='1BS'!P3 -> 21786543 | G8: ='1BS'!Q3 -> 22218601 | H8: ='1BS'!R3 -> 23752581 | I8: ='1BS'!S3 -> 24975052 | J8: ='1BS'!T3 -> 26566335 | K8: =C8-SUM(C9:C13) -> 1 | L8: Growth (%) | M8: =('1IS'!M3/'1IS'!L3-1)*100 -> -12.915481 | N8: =('1IS'!N3/'1IS'!M3-1)*100 -> 4.6322609 | O8: =('1IS'!O3/'1IS'!N3-1)*100 -> -18.775561 | P8: =('1IS'!P3/'1IS'!O3-1)*100 -> 4.3465424 | Q8: =('1IS'!Q3/'1IS'!P3-1)*100 -> 2.5463296 | R8: =('1IS'!R3/'1IS'!Q3-1)*100 -> 4.5743754 | S8: =('1IS'!S3/'1IS'!R3-1)*100 -> 2.4688937 | T8: =('1IS'!T3/'1IS'!S3-1)*100 -> 3.9886075
B9: Cash & equivalents | C9: ='1BS'!M4 -> 5039908 | D9: ='1BS'!N4 -> 4477502 | E9: ='1BS'!O4 -> 4016882 | F9: ='1BS'!P4 -> 3747577.4 | G9: ='1BS'!Q4 -> 4922413.3 | H9: ='1BS'!R4 -> 6413066.7 | I9: ='1BS'!S4 -> 7541761.5 | J9: ='1BS'!T4 -> 9076879.8 | L9: COGS | M9: ='1IS'!M4 -> -21370005 | N9: ='1IS'!N4 -> -22554221 | O9: ='1IS'!O4 -> -16587631 | P9: ='1IS'!P4 -> -17682700 | Q9: ='1IS'!Q4 -> -18223910 | R9: ='1IS'!R4 -> -18936439 | S9: ='1IS'!S4 -> -19393083 | T9: ='1IS'!T4 -> -20096200
B10: Short-term financial asset | C10: ='1BS'!M7 -> 17741052 | D10: ='1BS'!N7 -> 16566239 | E10: ='1BS'!O7 -> 14985489 | F10: ='1BS'!P7 -> 14838769 | G10: ='1BS'!Q7 -> 14108562 | H10: ='1BS'!R7 -> 13884887 | I10: ='1BS'!S7 -> 13930853 | J10: ='1BS'!T7 -> 13869148 | L10: Gross profit | M10: =M7+M9 -> 9091362 | N10: =N7+N9 -> 9318196 | O10: =O7+O9 -> 9300561 | P10: =P7+P9 -> 9330733.5 | Q10: =Q7+Q9 -> 9477374.2 | R10: =R7+R9 -> 10032006 | S10: =S7+S9 -> 10290562 | T10: =T7+T9 -> 10771409
B11: Accounts receivable | C11: ='1BS'!M11 -> 1229401 | D11: ='1BS'!N11 -> 1818472 | E11: ='1BS'!O11 -> 902823 | F11: ='1BS'!P11 -> 1047528.8 | G11: ='1BS'!Q11 -> 1015073.3 | H11: ='1BS'!R11 -> 1093678 | I11: ='1BS'!S11 -> 1131510.5 | J11: ='1BS'!T11 -> 1152919.5 | L11: GPM (%) | M11: =M10/M7*100 -> 29.845548 | N11: =N10/N7*100 -> 29.235925 | O11: =O10/O7*100 -> 35.925881 | P11: =P10/P7*100 -> 34.541087 | Q11: =Q10/Q7*100 -> 34.212761 | R11: =R10/R7*100 -> 34.630805 | S11: =S10/S7*100 -> 34.667448 | T11: =T10/T7*100 -> 34.895508
B12: Inventories | C12: ='1BS'!M20 -> 2317505 | D12: ='1BS'!N20 -> 1978544 | E12: ='1BS'!O20 -> 2027352 | F12: ='1BS'!P20 -> 1949659 | G12: ='1BS'!Q20 -> 1963349.4 | H12: ='1BS'!R20 -> 2137713.7 | I12: ='1BS'!S20 -> 2145593.4 | J12: ='1BS'!T20 -> 2232284.9 | L12: SG&A | M12: ='1IS'!M10+'1IS'!M11 -> -5279920 | N12: ='1IS'!N10+'1IS'!N11 -> -4880971 | O12: ='1IS'!O10+'1IS'!O11 -> -5005928 | P12: ='1IS'!P10+'1IS'!P11 -> -4916444.9 | Q12: ='1IS'!Q10+'1IS'!Q11 -> -4847724.8 | R12: ='1IS'!R10+'1IS'!R11 -> -4881183 | S12: ='1IS'!S10+'1IS'!S11 -> -5023956.9 | T12: ='1IS'!T10+'1IS'!T11 -> -5212767.5
B13: Other short-term assets | C13: ='1BS'!M23 -> 225539 | D13: ='1BS'!N23 -> 225976 | E13: ='1BS'!O23 -> 208433 | F13: =F8-SUM(F9:F12) -> 203009.22 | G13: =G8-SUM(G9:G12) -> 209203.65 | H13: =H8-SUM(H9:H12) -> 223235.91 | I13: =I8-SUM(I9:I12) -> 225332.75 | J13: =J8-SUM(J9:J12) -> 235102.58 | L13: Operating profit | M13: =M10+M12 -> 3811442 | N13: =N10+N12 -> 4437225 | O13: =O10+O12 -> 4294633 | P13: =P10+P12 -> 4414288.7 | Q13: =Q10+Q12 -> 4629649.5 | R13: =R10+R12 -> 5150822.7 | S13: =S10+S12 -> 5266605.4 | T13: =T10+T12 -> 5558641.4
B14: Non-current assets | C14: ='1BS'!M29 -> 7503219 | D14: ='1BS'!N29 -> 8372674 | E14: ='1BS'!O29 -> 10456376 | F14: ='1BS'!P29 -> 9606126.3 | G14: ='1BS'!Q29 -> 8806631.5 | H14: ='1BS'!R29 -> 8079045.8 | I14: ='1BS'!S29 -> 7323568.2 | J14: ='1BS'!T29 -> 6760023.4 | L14: Growth (%) | M14: =(('1IS'!M5+SUM('1IS'!M10:M11))/('1IS'!L5+SUM('1IS'!L10:L11))-1)*100 -> -30.675487 | N14: =(('1IS'!N5+SUM('1IS'!N10:N11))/('1IS'!M5+SUM('1IS'!M10:M11))-1)*100 -> 16.418532 | O14: =(('1IS'!O5+SUM('1IS'!O10:O11))/('1IS'!N5+SUM('1IS'!N10:N11))-1)*100 -> -3.2135618 | P14: =(('1IS'!P5+SUM('1IS'!P10:P11))/('1IS'!O5+SUM('1IS'!O10:O11))-1)*100 -> 2.7861676 | Q14: =(('1IS'!Q5+SUM('1IS'!Q10:Q11))/('1IS'!P5+SUM('1IS'!P10:P11))-1)*100 -> 4.8787205 | R14: =(('1IS'!R5+SUM('1IS'!R10:R11))/('1IS'!Q5+SUM('1IS'!Q10:Q11))-1)*100 -> 11.257293 | S14: =(('1IS'!S5+SUM('1IS'!S10:S11))/('1IS'!R5+SUM('1IS'!R10:R11))-1)*100 -> 2.2478485 | T14: =(('1IS'!T5+SUM('1IS'!T10:T11))/('1IS'!S5+SUM('1IS'!S10:S11))-1)*100 -> 5.5450526
B15: Net fixed assets | C15: ='1BS'!M38 -> 3969724 | D15: ='1BS'!N38 -> 3593254 | E15: ='1BS'!O38 -> 5068260 | F15: ='1BS'!P38 -> 4374176.1 | G15: ='1BS'!Q38 -> 3531907.7 | H15: ='1BS'!R38 -> 2774676.7 | I15: ='1BS'!S38 -> 1999346.5 | J15: ='1BS'!T38 -> 1409046.2 | L15: OPM (%) | M15: =M13/M7*100 -> 12.51238 | N15: =N13/N7*100 -> 13.921834 | O15: =O13/O7*100 -> 16.589158 | P15: =P13/P7*100 -> 16.341087 | Q15: =Q13/Q7*100 -> 16.712761 | R15: =R13/R7*100 -> 17.780805 | S15: =S13/S7*100 -> 17.742448 | T15: =T13/T7*100 -> 18.008008
B16: Investment assets | C16: ='1BS'!M49 -> 279065 | D16: ='1BS'!N49 -> 268305 | E16: ='1BS'!O49 -> 238599 | F16: ='1BS'!P49 -> 228521.42 | G16: ='1BS'!Q49 -> 218450.38 | H16: ='1BS'!R49 -> 208386.07 | I16: ='1BS'!S49 -> 198328.7 | J16: ='1BS'!T49 -> 188278.46 | L16: Non-operating profit | M16: =M17+M18+M20 -> 1558968 | N16: =N17+N18+N20 -> 1210132 | O16: =O17+O18+O20 -> 1357333 | P16: =P17+P18+P20 -> 1220238.5 | Q16: =Q17+Q18+Q20 -> 1173071.2 | R16: =R17+R18+R20 -> 1164928 | S16: =S17+S18+S20 -> 1159355.4 | T16: =T17+T18+T20 -> 1154837.7
B17: Other long-term assets | C17: =C14-C15 -> 3533495 | D17: =D14-D15 -> 4779420 | E17: =E14-E15 -> 5388116 | F17: =F14-F15 -> 5231950.2 | G17: =G14-G15 -> 5274723.8 | H17: =H14-H15 -> 5304369.1 | I17: =I14-I15 -> 5324221.7 | J17: =J14-J15 -> 5350977.2 | L17: Financial income | M17: ='1IS'!M6 -> 1432569 | N17: ='1IS'!N6 -> 1067078 | O17: ='1IS'!O6 -> 1006647 | P17: ='1IS'!P6 -> 977523.7 | Q17: ='1IS'!Q6 -> 927502.7 | R17: ='1IS'!R6 -> 922159.3 | S17: ='1IS'!S6 -> 919283.02 | T17: ='1IS'!T6 -> 916482.27
B18: Total liabilities | C18: ='1BS'!M69 -> 8571467 | D18: ='1BS'!N69 -> 9002313 | E18: ='1BS'!O69 -> 9597539 | F18: ='1BS'!P69 -> 8782869.7 | G18: ='1BS'!Q69 -> 8627404.8 | H18: ='1BS'!R69 -> 9184072.1 | I18: ='1BS'!S69 -> 9280130.3 | J18: ='1BS'!T69 -> 9671543.4 | L18: Financial expense | M18: ='1IS'!M7 -> -73434 | N18: ='1IS'!N7 -> -24788 | O18: ='1IS'!O7 -> -26257 | P18: ='1IS'!P7 -> -29677.657 | Q18: ='1IS'!Q7 -> -26823.982 | R18: ='1IS'!R7 -> -29623.78 | S18: ='1IS'!S7 -> -32320.092 | T18: ='1IS'!T7 -> -34037.104
B19: Current liabilities | C19: ='1BS'!M70 -> 8224608 | D19: ='1BS'!N70 -> 8657141 | E19: ='1BS'!O70 -> 8880281 | F19: ='1BS'!P70 -> 8068629.7 | G19: ='1BS'!Q70 -> 7916180.8 | H19: ='1BS'!R70 -> 8475864.1 | I19: ='1BS'!S70 -> 8574938.3 | J19: ='1BS'!T70 -> 8969367.4 | L19: In which: interest expenses | M19: ='1IS'!M8 -> -50215 | N19: ='1IS'!N8 -> -27450 | O19: ='1IS'!O8 -> -34346 | P19: ='1IS'!P8 -> -33228.324 | Q19: ='1IS'!Q8 -> -34924.037 | R19: ='1IS'!R8 -> -37866.271 | S19: ='1IS'!S8 -> -39228.538 | T19: ='1IS'!T8 -> -41647.58
B20: Accounts payable | C20: ='1BS'!M71 -> 2476373 | D20: ='1BS'!N71 -> 2642248 | E20: ='1BS'!O71 -> 2403618 | F20: ='1BS'!P71 -> 2314532.7 | G20: ='1BS'!Q71 -> 2413960.9 | H20: ='1BS'!R71 -> 2565343.9 | I20: ='1BS'!S71 -> 2586235.7 | J20: ='1BS'!T71 -> 2704266.8 | L20: Net other non-operating profit | M20: ='1IS'!M9+'1IS'!M15 -> 199833 | N20: ='1IS'!N9+'1IS'!N15 -> 167842 | O20: ='1IS'!O9+'1IS'!O15 -> 376943 | P20: ='1IS'!P9+'1IS'!P15 -> 272392.5 | Q20: ='1IS'!Q9+'1IS'!Q15 -> 272392.5 | R20: ='1IS'!R9+'1IS'!R15 -> 272392.5 | S20: ='1IS'!S9+'1IS'!S15 -> 272392.5 | T20: ='1IS'!T9+'1IS'!T15 -> 272392.5
B21: Short-term borrowings | C21: ='1BS'!M80 -> 530129 | D21: ='1BS'!N80 -> 245384 | E21: ='1BS'!O80 -> 267584 | F21: ='1BS'!P80 -> 293301.63 | G21: ='1BS'!Q80 -> 319701.63 | H21: ='1BS'!R80 -> 348490.16 | I21: ='1BS'!S80 -> 379883.34 | J21: ='1BS'!T80 -> 414116.8 | L21: Pre-tax profit | M21: ='1IS'!M17 -> 5370410 | N21: ='1IS'!N17 -> 5647359 | O21: ='1IS'!O17 -> 5651966 | P21: ='1IS'!P17 -> 5634527.2 | Q21: ='1IS'!Q17 -> 5802720.7 | R21: ='1IS'!R17 -> 6315750.7 | S21: ='1IS'!S17 -> 6425960.8 | T21: ='1IS'!T17 -> 6713479.1
B22: Others | C22: =C19-SUM(C20:C21) -> 5218106 | D22: =D19-SUM(D20:D21) -> 5769509 | E22: =E19-SUM(E20:E21) -> 6209079 | F22: =F19-SUM(F20:F21) -> 5460795.4 | G22: =G19-SUM(G20:G21) -> 5182518.2 | H22: =H19-SUM(H20:H21) -> 5562030.1 | I22: =I19-SUM(I20:I21) -> 5608819.2 | J22: =J19-SUM(J20:J21) -> 5850983.8 | L22: Income tax | M22: ='1IS'!M20 -> -1115357 | N22: ='1IS'!N20 -> -1152585 | O22: ='1IS'!O20 -> -1078841 | P22: ='1IS'!P20 -> -1075512.3 | Q22: ='1IS'!Q20 -> -1092556.6 | R22: ='1IS'!R20 -> -1155869.3 | S22: ='1IS'!S20 -> -1159192.3 | T22: ='1IS'!T20 -> -1187590.6
B23: Non-current liabilities | C23: ='1BS'!M85 -> 346858 | D23: ='1BS'!N85 -> 345173 | E23: ='1BS'!O85 -> 717257 | F23: ='1BS'!P85 -> 714240 | G23: ='1BS'!Q85 -> 711224 | H23: ='1BS'!R85 -> 708208 | I23: ='1BS'!S85 -> 705192 | J23: ='1BS'!T85 -> 702176 | L23: Net profit | M23: =M21+M22 -> 4255053 | N23: =N21+N22 -> 4494774 | O23: =O21+O22 -> 4573125 | P23: =P21+P22 -> 4559014.9 | Q23: =Q21+Q22 -> 4710164.1 | R23: =R21+R22 -> 5159881.4 | S23: =S21+S22 -> 5266768.5 | T23: =T21+T22 -> 5525888.5
B24: Long-term borrowings | C24: ='1BS'!M93 -> 170828 | D24: ='1BS'!N93 -> 169444 | E24: ='1BS'!O93 -> 167936 | F24: ='1BS'!P93 -> 164919 | G24: ='1BS'!Q93 -> 161903 | H24: ='1BS'!R93 -> 158887 | I24: ='1BS'!S93 -> 155871 | J24: ='1BS'!T93 -> 152855 | L24: Growth (%) | M24: =('1IS'!M21/'1IS'!L21-1)*100 -> -22.632559 | N24: =('1IS'!N21/'1IS'!M21-1)*100 -> 5.6337959 | O24: =('1IS'!O21/'1IS'!N21-1)*100 -> 1.7431577 | P24: =('1IS'!P21/'1IS'!O21-1)*100 -> -0.30854368 | Q24: =('1IS'!Q21/'1IS'!P21-1)*100 -> 3.315391 | R24: =('1IS'!R21/'1IS'!Q21-1)*100 -> 9.5478057 | S24: =('1IS'!S21/'1IS'!R21-1)*100 -> 2.0715038 | T24: =('1IS'!T21/'1IS'!S21-1)*100 -> 4.9199045
B25: Other financial liabilities | C25: =C23-C24 -> 176030 | D25: =D23-D24 -> 175729 | E25: =E23-E24 -> 549321 | F25: =F23-F24 -> 549321 | G25: =G23-G24 -> 549321 | H25: =H23-H24 -> 549321 | I25: =I23-I24 -> 549321 | J25: =J23-J24 -> 549321 | L25: NPM (%) | M25: =M23/M7*100 -> 13.968687 | N25: =N23/N7*100 -> 14.102395 | O25: =O23/O7*100 -> 17.664907 | P25: =P23/P7*100 -> 16.876844 | Q25: =Q23/Q7*100 -> 17.003414 | R25: =R23/R7*100 -> 17.812076 | S25: =S23/S7*100 -> 17.742998 | T25: =T23/T7*100 -> 17.9019
B26: Total shareholders' equity | C26: ='1BS'!M100 -> 25485158 | D26: ='1BS'!N100 -> 24437093 | E26: ='1BS'!O100 -> 22999815 | F26: ='1BS'!P100 -> 22609802 | G26: ='1BS'!Q100 -> 22397830 | H26: ='1BS'!R100 -> 22647557 | I26: ='1BS'!S100 -> 23018492 | J26: ='1BS'!T100 -> 23654817 | L26: Controlling interest | M26: ='1IS'!M23 -> 4117605 | N26: ='1IS'!N23 -> 4330113 | O26: ='1IS'!O23 -> 4423540 | P26: ='1IS'!P23 -> 4399449.4 | Q26: ='1IS'!Q23 -> 4545308.3 | R26: ='1IS'!R23 -> 4979285.5 | S26: ='1IS'!S23 -> 5082431.6 | T26: ='1IS'!T23 -> 5332482.4
B27: Capital stock | C27: ='1BS'!M103 -> 12825624 | D27: ='1BS'!N103 -> 12825624 | E27: ='1BS'!O103 -> 12825624 | F27: ='1BS'!P103 -> 12825624 | G27: ='1BS'!Q103 -> 12825624 | H27: ='1BS'!R103 -> 12825624 | I27: ='1BS'!S103 -> 12825624 | J27: ='1BS'!T103 -> 12825624 | L27: Non-controlling interest | M27: =M23-M26 -> 137448 | N27: =N23-N26 -> 164661 | O27: =O23-O26 -> 149585 | P27: =P23-P26 -> 159565.52 | Q27: =Q23-Q26 -> 164855.74 | R27: =R23-R26 -> 180595.85 | S27: =S23-S26 -> 184336.9 | T27: =T23-T26 -> 193406.1
B28: Capital surplus | C28: ='1BS'!M105 -> 0 | D28: ='1BS'!N105 -> 0 | E28: ='1BS'!O105 -> 0 | F28: ='1BS'!P105 -> 0 | G28: ='1BS'!Q105 -> 0 | H28: ='1BS'!R105 -> 0 | I28: ='1BS'!S105 -> 0 | J28: ='1BS'!T105 -> 0 | L28: EBIT | M28: ='1IS'!M42 -> 5420625 | N28: ='1IS'!N42 -> 5674809 | O28: ='1IS'!O42 -> 5686312 | P28: ='1IS'!P42 -> 5667755.5 | Q28: ='1IS'!Q42 -> 5837644.7 | R28: ='1IS'!R42 -> 6353617 | S28: ='1IS'!S42 -> 6465189.3 | T28: ='1IS'!T42 -> 6755126.7
B29: Other capital | C29: =C26-SUM(C27:C28,C30) -> 2442250 | D29: =D26-SUM(D27:D28,D30) -> 2393668 | E29: =E26-SUM(E27:E28,E30) -> 3127047 | F29: =F26-SUM(F27:F28,F30) -> 2954146.9 | G29: =G26-SUM(G27:G28,G30) -> 2817659.1 | H29: =H26-SUM(H27:H28,H30) -> 2721479.2 | I29: =I26-SUM(I27:I28,I30) -> 2646352.7 | J29: =J26-SUM(J27:J28,J30) -> 2593818.2 | L29: Growth (%) | M29: =('1IS'!M42/'1IS'!L42-1)*100 -> -20.969862 | N29: =('1IS'!N42/'1IS'!M42-1)*100 -> 4.689201 | O29: =('1IS'!O42/'1IS'!N42-1)*100 -> 0.20270286 | P29: =(P28/O28-1)*100 -> -0.3263356 | Q29: =(Q28/P28-1)*100 -> 2.9974686 | R29: =(R28/Q28-1)*100 -> 8.8387057 | S29: =(S28/R28-1)*100 -> 1.7560449 | T29: =(T28/S28-1)*100 -> 4.4845913
B30: Retained earnings | C30: ='1BS'!M115 -> 10217284 | D30: ='1BS'!N115 -> 9217801 | E30: ='1BS'!O115 -> 7047144 | F30: ='1BS'!P115 -> 6830031.1 | G30: ='1BS'!Q115 -> 6754546.9 | H30: ='1BS'!R115 -> 7100453.6 | I30: ='1BS'!S115 -> 7546514.9 | J30: ='1BS'!T115 -> 8235374.9 | L30: EBIT Margin (%) | M30: =M28/M7*100 -> 17.795081 | N30: =N28/N7*100 -> 17.804765 | O30: =O28/O7*100 -> 21.964887 | P30: =P28/P7*100 -> 20.981248 | Q30: =Q28/Q7*100 -> 21.073553 | R30: =R28/R7*100 -> 21.932889 | S30: =S28/S7*100 -> 21.780308 | T30: =T28/T7*100 -> 21.884191
B31: Non-controlling interest equity | C31: ='1BS'!M118 -> 1272846 | D31: ='1BS'!N118 -> 1154973 | E31: ='1BS'!O118 -> 1847031 | F31: ='1BS'!P118 -> 1674130.9 | G31: ='1BS'!Q118 -> 1537643.1 | H31: ='1BS'!R118 -> 1441463.2 | I31: ='1BS'!S118 -> 1366336.7 | J31: ='1BS'!T118 -> 1313802.2 | L31: EBITDA | M31: =M28+C39 -> 5990657 | N31: =N28+D39 -> 6223693 | O31: =O28+E39 -> 6416584 | P31: =P28+F39 -> 6468244.1 | Q31: =Q28+G39 -> 6649871 | R31: =R28+H39 -> 7153300.1 | S31: =S28+I39 -> 7278566.4 | T31: =T28+J39 -> 7386107.9
B32: *Total debt | C32: =C21+C24 -> 700957 | D32: =D21+D24 -> 414828 | E32: =E21+E24 -> 435520 | F32: =F21+F24 -> 458220.63 | G32: =G21+G24 -> 481604.63 | H32: =H21+H24 -> 507377.16 | I32: =I21+I24 -> 535754.34 | J32: =J21+J24 -> 566971.8 | L32: Growth (%) | M32: =('1IS'!M43/'1IS'!L43-1)*100 -> -19.263807 | N32: =('1IS'!N43/'1IS'!M43-1)*100 -> 3.8899907 | O32: =('1IS'!O43/'1IS'!N43-1)*100 -> 3.0993013 | P32: =(P31/O31-1)*100 -> 0.80510345 | Q32: =(Q31/P31-1)*100 -> 2.8079779 | R32: =(R31/Q31-1)*100 -> 7.5705097 | S32: =(S31/R31-1)*100 -> 1.7511675 | T32: =(T31/S31-1)*100 -> 1.477509 | W32: QNS VN EQUITY
B33: *Net debt (cash) | C33: =C32-SUM(C9,C10) -> -22080003 | D33: =D32-SUM(D9,D10) -> -20628913 | E33: =E32-SUM(E9,E10) -> -18566851 | F33: =F32-SUM(F9,F10) -> -18128126 | G33: =G32-SUM(G9,G10) -> -18549370 | H33: =H32-SUM(H9,H10) -> -19790576 | I33: =I32-SUM(I9,I10) -> -20936861 | J33: =J32-SUM(J9,J10) -> -22379056 | L33: EBITDA margin (%) | M33: =M31/M7*100 -> 19.666409 | N33: =N31/N7*100 -> 19.526894 | O33: =O31/O7*100 -> 24.785756 | P33: =P31/P7*100 -> 23.944547 | Q33: =Q31/Q7*100 -> 24.005642 | R33: =R31/R7*100 -> 24.693421 | S33: =S31/S7*100 -> 24.52046 | T33: =T31/T7*100 -> 23.928344
B35: Statement of cash flow | L35: Key ratios
B36: Year to Dec. (bn VND) | C36: =C6 -> 2023 | D36: =D6 -> 2024 | E36: =E6 -> 2025 | F36: =F6 -> 2026F | G36: =G6 -> 2027F | H36: =H6 -> 2028F | I36: =I6 -> 2029F | J36: =J6 -> 2030F | L36: Year to Dec. | M36: =M6 -> 2023 | N36: =N6 -> 2024 | O36: =O6 -> 2025 | P36: =P6 -> 2026F | Q36: =Q6 -> 2027F | R36: =R6 -> 2028F | S36: =S6 -> 2029F | T36: =T6 -> 2030F
B37: Cash flow from operations | C37: ='1CF'!J26 -> 1940064 | D37: ='1CF'!K26 -> 4362510 | E37: ='1CF'!L26 -> 3904076 | F37: ='1CF'!M26 -> 3372366.5 | G37: ='1CF'!N26 -> 4310974.5 | H37: ='1CF'!O26 -> 5172453.3 | I37: ='1CF'!P26 -> 5048209.6 | J37: ='1CF'!Q26 -> 5343280.7 | L37: EPS (VND) | M37: ='1IS'!M24 -> 3132 | N37: ='1IS'!N24 -> 3291 | O37: ='1IS'!O24 -> 3347 | P37: ='1IS'!P24 -> 3330.7195 | Q37: ='1IS'!Q24 -> 3441.1459 | R37: ='1IS'!R24 -> 3769.6998 | S37: ='1IS'!S24 -> 3847.7892 | T37: ='1IS'!T24 -> 4037.0968 | W37: 2023 | X37: =W37+1 -> 2024 | Y37: =X37+1 -> 2025 | Z37: =Y37+1 -> 2026 | AA37: =Z37+1 -> 2027 | AB37: =AA37+1 -> 2028 | AC37: =AB37+1 -> 2029 | AD37: =AC37+1 -> 2030
B38: Net profit | C38: ='1CF'!J6 -> 5370410 | D38: ='1CF'!K6 -> 5647359 | E38: ='1CF'!L6 -> 5651966 | F38: ='1CF'!M6 -> 5634527.2 | G38: ='1CF'!N6 -> 5802720.7 | H38: ='1CF'!O6 -> 6315750.7 | I38: ='1CF'!P6 -> 6425960.8 | J38: ='1CF'!Q6 -> 6713479.1 | L38: BPS (VND) | M38: ='1IS'!M36 -> 18878.078 | N38: ='1IS'!N36 -> 18152.817 | O38: ='1IS'!O36 -> 16492.597 | P38: ='1IS'!P36 -> 16323.316 | Q38: ='1IS'!Q36 -> 16264.462 | R38: ='1IS'!R36 -> 16534.162 | S38: ='1IS'!S36 -> 16881.951 | T38: ='1IS'!T36 -> 17419.048 | U38: PE_RATIO
B39: Depreciation & Amortization | C39: ='1CF'!J8 -> 570032 | D39: ='1CF'!K8 -> 548884 | E39: ='1CF'!L8 -> 730272 | F39: ='1CF'!M8 -> 800488.6 | G39: ='1CF'!N8 -> 812226.28 | H39: ='1CF'!O8 -> 799683.17 | I39: ='1CF'!P8 -> 813377.07 | J39: ='1CF'!Q8 -> 630981.22 | L39: DPS | M39: =W46/Valuation!$B$12 -> 2616.2972 | N39: =X46/Valuation!$B$12 -> 3633.8144 | O39: =Y46/Valuation!$B$12 -> 5080.0842 | P39: =Z46/Valuation!$B$12 -> 3760.8689 | Q39: =AA46/Valuation!$B$12 -> 3736.5928 | R39: =AB46/Valuation!$B$12 -> 3717.4291 | S39: =AC46/Valuation!$B$12 -> 3703.9249 | T39: =AD46/Valuation!$B$12 -> 3693.3768 | U39: PX_TO_BOOK_RATIO
B40: (Gain) from Investing activities | C40: ='1CF'!J11 -> -1393861 | D40: ='1CF'!K11 -> -1051087 | E40: ='1CF'!L11 -> -1273875 | F40: ='1CF'!M11 -> -960583.2 | G40: ='1CF'!N11 -> -913313.45 | H40: ='1CF'!O11 -> -906594.42 | I40: ='1CF'!P11 -> -904404.96 | J40: ='1CF'!Q11 -> -901260.3 | L40: PER (x) | M40: ='1IS'!M54 -> 16.395135 | N40: ='1IS'!N54 -> 15.441276 | O40: ='1IS'!O54 -> 14.105919 | P40: ='1IS'!P54 -> 16.716792 | Q40: ='1IS'!Q54 -> 16.18035 | R40: ='1IS'!R54 -> 14.770127 | S40: ='1IS'!S54 -> 14.470373 | T40: ='1IS'!T54 -> 13.791828 | U40: ev/ebitda
B41: Change in working capital | C41: =SUM('1CF'!J16:J19) -> -1108889 | D41: =SUM('1CF'!K16:K19) -> 691269 | E41: =SUM('1CF'!L16:L19) -> -38289 | F41: =SUM('1CF'!M16:M19) -> -655074.92 | G41: =SUM('1CF'!N16:N19) -> -85454.636 | H41: =SUM('1CF'!O16:O19) -> 179069.22 | I41: =SUM('1CF'!P16:P19) -> 21975.552 | J41: =SUM('1CF'!Q16:Q19) -> 209368.54 | L41: PBR (x) | M41: ='1IS'!M55 -> 2.709492 | N41: ='1IS'!N55 -> 2.7885479 | O41: ='1IS'!O55 -> 2.8497635 | P41: ='1IS'!P55 -> 3.411007 | Q41: ='1IS'!Q55 -> 3.42335 | R41: ='1IS'!R55 -> 3.3675094 | S41: ='1IS'!S55 -> 3.2981346 | T41: ='1IS'!T55 -> 3.1964403 | U41: ENTERPRISE_VALUE
B42: Others | C42: =C37-C38-C39-C40-C41 -> -1497628 | D42: =D37-D38-D39-D40-D41 -> -1473915 | E42: =E37-E38-E39-E40-E41 -> -1165998 | F42: =F37-F38-F39-F40-F41 -> -1446991.2 | G42: =G37-G38-G39-G40-G41 -> -1305204.4 | H42: =H37-H38-H39-H40-H41 -> -1215455.4 | I42: =I37-I38-I39-I40-I41 -> -1308698.8 | J42: =J37-J38-J39-J40-J41 -> -1309287.8 | L42: EV/EBITDA (x) | M42: ='1IS'!M59/M31 -> 10.950897 | N42: ='1IS'!N59/N31 -> 10.431637 | O42: ='1IS'!O59/O31 -> 9.394474 | P42: ='1IS'!P59/P31 -> 11.040356 | Q42: ='1IS'!Q59/Q31 -> 10.738813 | R42: ='1IS'!R59/R31 -> 9.9830454 | S42: ='1IS'!S59/S31 -> 9.8112343 | T42: ='1IS'!T59/T31 -> 9.6683831 | U42: EBITDA
B43: Cash flow from investments | C43: ='1CF'!J37 -> 2715583 | D43: ='1CF'!K37 -> 18884 | E43: ='1CF'!L37 -> 2423075 | F43: ='1CF'!M37 -> 1157062.3 | G43: ='1CF'!N37 -> 1630789.4 | H43: ='1CF'!O37 -> 1058171.7 | I43: ='1CF'!P37 -> 800539.81 | J43: ='1CF'!Q37 -> 895529.07 | L43: Dividend payout ratio (%) | M43: =Equity!M112*100 -> 64.207287 | N43: =Equity!N112*100 -> 113.13737 | O43: =Equity!O112*100 -> 150.40411 | P43: =Equity!P112*100 -> 102.03478 | Q43: =Equity!Q112*100 -> 98.760482 | R43: =Equity!R112*100 -> 90.152861 | S43: =Equity!S112*100 -> 88.323242 | T43: =Equity!T112*100 -> 84.181588 | U43: DVD_PAYOUT_RATIO
B44: Change in fixed assets | C44: =SUM('1CF'!J29:J30) -> -281250 | D44: =SUM('1CF'!K29:K30) -> -292493 | E44: =SUM('1CF'!L29:L30) -> -240244 | F44: =SUM('1CF'!M29:M30) -> 49759.081 | G44: =SUM('1CF'!N29:N30) -> -12731.453 | H44: =SUM('1CF'!O29:O30) -> -72097.476 | I44: =SUM('1CF'!P29:P30) -> -57898.51 | J44: =SUM('1CF'!Q29:Q30) -> -67436.359 | L44: Dividend yield (%) | M44: 6.5 | N44: 10.5 | O44: 11.2 | P44: =-Equity!P25/(Valuation!$B$13)*100 -> 7.9041431 | Q44: =-Equity!Q25/(Valuation!$B$13)*100 -> 7.9041431 | R44: =-Equity!R25/(Valuation!$B$13)*100 -> 7.9041431 | S44: =-Equity!S25/(Valuation!$B$13)*100 -> 7.9041431 | T44: =-Equity!T25/(Valuation!$B$13)*100 -> 7.9041431
B45: Change in investment assets | C45: =SUM('1CF'!J31:J32) -> 1633297 | D45: =SUM('1CF'!K31:K32) -> -121467 | E45: =SUM('1CF'!L31:L32) -> 1075151 | F45: =SUM('1CF'!M31:M32) -> 146720.03 | G45: =SUM('1CF'!N31:N32) -> 730207.4 | H45: =SUM('1CF'!O31:O32) -> 223674.78 | I45: =SUM('1CF'!P31:P32) -> -45966.644 | J45: =SUM('1CF'!Q31:Q32) -> 61705.126 | L45: Profitability | U45: PX_LAST | W45: 158000 | X45: 158000 | Y45: 158000 | Z45: 158000 | AA45: 158000 | AB45: 158000
B46: Others | C46: =C43-C44-C45 -> 1363536 | D46: =D43-D44-D45 -> 432844 | E46: =E43-E44-E45 -> 1588168 | F46: =F43-F44-F45 -> 960583.2 | G46: =G43-G44-G45 -> 913313.45 | H46: =H43-H44-H45 -> 906594.42 | I46: =I43-I44-I45 -> 904404.96 | J46: =J43-J44-J45 -> 901260.3 | L46: EBITDA margin (%) | M46: =M33 -> 19.666409 | N46: =N33 -> 19.526894 | O46: =O33 -> 24.785756 | P46: =P33 -> 23.944547 | Q46: =Q33 -> 24.005642 | R46: =R33 -> 24.693421 | S46: =S33 -> 24.52046 | T46: =T33 -> 23.928344 | U46: Divident | W46: =-'1CF'!J46 -> 3354093 | X46: =-'1CF'!K46 -> 4658550 | Y46: =-'1CF'!L46 -> 6512668 | Z46: =-'1CF'!M46 -> 4821434 | AA46: =-'1CF'!N46 -> 4790312 | AB46: =-'1CF'!O46 -> 4765744.2 | AC46: =-'1CF'!P46 -> 4748431.8 | AD46: =-'1CF'!Q46 -> 4734909
B47: Cash flow from financing | C47: ='1CF'!J48 -> -3685025 | D47: ='1CF'!K48 -> -4943450 | E47: ='1CF'!L48 -> -6787750 | F47: ='1CF'!M48 -> -4798733.3 | G47: ='1CF'!N48 -> -4766928 | H47: ='1CF'!O48 -> -4739971.6 | I47: ='1CF'!P48 -> -4720054.6 | J47: ='1CF'!Q48 -> -4703691.5 | L47: OPM (%) | M47: =M15 -> 12.51238 | N47: =N15 -> 13.921834 | O47: =O15 -> 16.589158 | P47: =P15 -> 16.341087 | Q47: =Q15 -> 16.712761 | R47: =R15 -> 17.780805 | S47: =S15 -> 17.742448 | T47: =T15 -> 18.008008 | U47: Divident yield | W47: =W46*100/W45 -> 2122.8437 | X47: =X46*100/X45 -> 2948.4494 | Y47: =Y46*100/Y45 -> 4121.9418 | Z47: =Z46*100/Z45 -> 3051.5405 | AA47: =AA46*100/AA45 -> 3031.843 | AB47: =AB46*100/AB45 -> 3016.2938
B48: Change in equity | C48: =SUM('1CF'!J41:J42) -> 0 | D48: =SUM('1CF'!K41:K42) -> 0 | E48: =SUM('1CF'!L41:L42) -> 0 | F48: =SUM('1CF'!M41:M42) -> 0 | G48: =SUM('1CF'!N41:N42) -> 0 | H48: =SUM('1CF'!O41:O42) -> 0 | I48: =SUM('1CF'!P41:P42) -> 0 | J48: =SUM('1CF'!Q41:Q42) -> 0 | L48: NPM (%) | M48: =M25 -> 13.968687 | N48: =N25 -> 14.102395 | O48: =O25 -> 17.664907 | P48: =P25 -> 16.876844 | Q48: =Q25 -> 17.003414 | R48: =R25 -> 17.812076 | S48: =S25 -> 17.742998 | T48: =T25 -> 17.9019 | W48: =M43*100 -> 6420.7287 | X48: =N43*100 -> 11313.737 | Y48: =O43*100 -> 15040.411 | Z48: =P43*100 -> 10203.478 | AA48: =Q43*100 -> 9876.0482 | AB48: =R43*100 -> 9015.2861
B49: Net borrowing | C49: =SUM('1CF'!J43:J44) -> -330933 | D49: =SUM('1CF'!K43:K44) -> -284900 | E49: =SUM('1CF'!L43:L44) -> -275081 | F49: =SUM('1CF'!M43:M44) -> 22700.633 | G49: =SUM('1CF'!N43:N44) -> 23383.997 | H49: =SUM('1CF'!O43:O44) -> 25772.534 | I49: =SUM('1CF'!P43:P44) -> 28377.173 | J49: =SUM('1CF'!Q43:Q44) -> 31217.467 | L49: ROA (%) | M49: =M23*100/C7 -> 12.494054 | N49: =N23*100/AVERAGE(C7:D7) -> 13.318632 | O49: =O23*100/AVERAGE(D7:E7) -> 13.85024 | P49: =P23*100/AVERAGE(E7:F7) -> 14.249143 | Q49: =Q23*100/AVERAGE(F7:G7) -> 15.09235 | R49: =R23*100/AVERAGE(G7:H7) -> 16.417878 | S49: =S23*100/AVERAGE(H7:I7) -> 16.425225 | T49: =T23*100/AVERAGE(I7:J7) -> 16.840809 | W49: =W48*100/W45 -> 4.0637523 | X49: =X48*100/X45 -> 7.160593 | Y49: =Y48*100/Y45 -> 9.5192476 | Z49: =Z48*100/Z45 -> 6.4578973 | AA49: =AA48*100/AA45 -> 6.2506634 | AB49: =AB48*100/AB45 -> 5.7058773
